Workbook

Sheet Introduction
B1: MBc360 Development & Quality System
A2: Topic | B2: Instruction
A3: Purpose | B3: This workbook is the controlled project evidence record for MBc360. It now includes the product-development lifecycle, Skincare for Two checks, PIF mapping, study approvals and HCP/distributor evidence outputs.
A4: How to select multiple options | B4: Use the one-click checkbox cells. Multiple checkboxes can be selected in each section.
A5: How to use dropdowns | B5: Use dropdowns only where one status/decision/value should be selected.
A6: Notes / free typing | B6: Use the notes areas and notes/action columns on each form.
A7: Evidence requirement | B7: Every checked item that supports a decision should include evidence/reference, method reference, internal link, date and initials.
A8: Template style | B8: Workbook uses the Max Biocare / MBc360 controlled document style.
A9: Skincare for Two | B9: Maternal products must include maternal use plus baby-contact/infant exposure consideration; this is mandatory, not optional.
A10: Study paperwork | B10: Human/consumer studies require proposal, participant plan, consent, adverse-event log and signatures before results support claims.
A11: Approval route | B11: Current route: Chris prepares study proposal, George/Head of Department signs off, Sekar or nominated independent reviewer signs off outside the department.
A12: PIF layer | B12: ASEAN PIF mapping is mandatory before dossier export or market submission.
A13: Ingredient proof | B13: Use Prohibited_Ingredients, PB_Caution_Limits and Ingredient_Substitution to answer distributor/HCP questions.
... A32: External use | B32: No external HCP/distributor/pharmacy claim use until PIF attachment status and approval are closed.

Sheet Guide To Using This Document
B1: MBc360 Development & Quality System
A2: Data Entry Guide
A4: Feature | B4: How to use
A5: Checkboxes | B5: Click once in the checkbox cell to select or clear. Multiple options can be selected in the same section.
A6: Dropdowns | B6: Use dropdowns for single-choice controlled fields such as stage status, decision, priority and Y/N/NA.
A7: Notes | B7: Use notes/action columns or the free-type notes areas for explanations, caveats, customer comments or internal decisions.
A8: Evidence | B8: Each completed check should reference evidence, method reference and internal link where applicable.
A9: Costing | B9: Use the Costing_Calc, Formula_BOM and Packaging_BOM sheets for numeric inputs and formulas.
A10: Packaging / regulatory | B10: Use the dedicated support sheets plus the relevant stage forms. Packaging is included in the main workbook.

Sheet Requirements
B1: MBc360 Development & Quality System
A2: Metric | B2: Value | C2: Notes
A3: Controlled gates | B3: 12 | C3: Renamed for non-technical navigation; Gate IDs retained in Stage_Map
A4: Skincare for Two checks | B4: Mandatory | C4: Maternal products must include baby-contact/infant exposure assessment
A5: Study approval trail | B5: Required | C5: Proposal + Head sign-off + independent reviewer + saved records
A6: Participant evidence | B6: Required when claims need human support | C6: Sample size target, consent, recruitment log and final report
A7: PIF / dossier mapping | B7: Required | C7: ASEAN_PIF_Map before dossier export
A8: Prohibited ingredient proof | B8: Required | C8: Prohibited_Ingredients formula check and evidence link
A9: Pregnancy/BF caution limits | B9: Required | C9: PB_Caution_Limits concentration/status check
A10: HCP/distributor pack | B10: Required for partner questions | C10: Medical_Summary output
A11: Twinkle 5 claim mapping | B11: Required where used | C11: Twinkle5_Claims_Map and evidence links
A12: Post-market learning | B12: Required | C12: Gate 12/PostMarket feedback and CAPA
A13: Topical efficacy assurance | B13: Required | C13: Problem -> mechanism -> potency/source -> formula/process -> evidence -> claim wording
A14: Mechanism of action map | B14: Required for benefit claims | C14: Use Mechanism_Claims_Map before HCP/distributor use
A15: Potency/process controls | B15: Required | C15: Use Potency_Process_Control for heat-sensitive ingredients, active markers, pH, processing and GMP controls
... A26: PIF checklist | B26: Required | C26: PIF_Checklist_ASEAN imports the PIF List into the project file.

Sheet Template_Index
A1: MBc360 Development & Quality System
A2: Evidence Template Index
A4: EVIDENCE TEMPLATE MAP
A5: Evidence concept | B5: Template tab | C5: Evidence captured | D5: When to complete | E5: Gate | F5: Owner | G5: Status | H5: Notes
A6: 1. Commercial costing | B6: Formula_BOM | C6: Formula composition, ingredient cost, evidence links | D6: Complete once per formula version | E6: 05 | F6: R&I / Finance | G6: Not Started | H6: Feeds Costing_Calc and Formulation_Safety
A7: 1. Commercial costing | B7: Packaging_BOM | C7: Packaging components, pack cost, spec/artwork links | D7: Complete once per SKU/pack | E7: 06 | F7: Packaging / Finance | G7: Not Started | H7: Feeds Costing_Calc
A8: 1. Commercial costing | B8: Costing_Calc | C8: COGS, margin and forecast assumptions | D8: Complete once per SKU scenario | E8: 05 | F8: Finance / Project owner | G8: Not Started | H8: Inputs only; formulas calculate outputs
A9: 2. Ingredient evidence | B9: Supplier_RM_Evidence | C9: SDS, CoA, TDS, allergens, origin, impurities | D9: Complete per raw material | E9: 04 | F9: Procurement / R&I / Quality | G9: Not Started | H9: Links into safety and PIF
A10: 2. Ingredient evidence | B10: Prohibited_Ingredients | C10: Absence/review evidence for prohibited watch-list | D10: Complete per formula | E10: 07 | F10: Regulatory | G10: Not Started | H10: Formula match formulas flag possible matches
A11: 2. Ingredient evidence | B11: PB_Caution_Limits | C11: Pregnancy/breastfeeding caution-limit logic | D11: Complete per formula | E11: 07 | F11: Safety / Regulatory | G11: Not Started | H11: Use for maternal positioning
A12: 2. Ingredient evidence | C12: Substitution decision and evidence when a material is changed | D12: Use when triggered | E12: 04/07 | F12: R&I | G12: Not Started | H12: Avoids repeating change-control details
A13: 3. Product safety | B13: Formulation_Safety | C13: Full formula-level safety matrix and final sign-off | D13: Complete per formula version | E13: 07/10 | F13: Safety / Regulatory | G13: Not Started | H13: Primary safety evidence tab
A14: 3. Product safety | B14: Fragrance_Safety | C14: IFRA, allergen, PBW caution and fragrance evidence | D14: Complete where fragranced | E14: 07 | F14: R&I / Regulatory | G14: Not Started | H14: Feeds artwork and PIF
A15: 4. Packaging / artwork | B15: Packaging_Specs_Artwork | C15: Component specs, label checks and artwork approval evidence | D15: Complete per SKU/market | E15: 06/10/11 | F15: Packaging / Regulatory | G15: Not Started | H15: Development evidence, not change log
A16: 5. Quality testing | B16: Micro_PET_Evidence | C16: Micro, PET/challenge and preservative rationale | D16: Complete where relevant | E16: 08 | F16: Quality | G16: Not Started | H16: Feeds PIF and release
A17: 5. Quality testing | B17: Stability_Release | C17: Stability, compatibility and release decision evidence | D17: Complete per formula/pack | E17: 09/11 | F17: Quality | G17: Not Started | H17: Report links only
A18: 5. Quality testing | B18: Eye_Safety_Evidence | C18: Eye irritation/safe-zone evidence | D18: Complete where eye-contact risk or claim | E18: 07/08 | F18: Safety / Quality | G18: Not Started | H18: Separate from broader formulation safety
A19: 6. Efficacy / claims | B19: Mechanism_Claims_Map | C19: Claim, mechanism, ingredient and evidence mapping | D19: Complete before claim approval | E19: 03/10 | F19: R&I / Claims | G19: Not Started | H19: Source of approved claim logic
A20: 6. Efficacy / claims | B20: Efficacy_Assurance | C20: Checks whether efficacy is controlled by formula/process/testing | D20: Complete where efficacy claim | E20: 05/08 | F20: R&I / Quality | G20: Not Started | H20: Prevents unsupported claim drift
A21: 6. Efficacy / claims | B21: Functional_Efficacy | C21: Functional assay evidence and claim result | D21: Complete where assay-based claim | E21: 08/10 | F21: R&I / Quality | G21: Not Started | H21: Links reports in Test_Report_Index
A22: 6. Efficacy / claims | B22: Clinical_Human_Evidence | C22: Human/consumer/clinical proof | D22: Complete where human support is needed | E22: 08/10 | F22: Clinical / R&I | G22: Not Started | H22: Study_Protocol holds participant details
A23: 7. Regulatory / PIF | B23: ASEAN_PIF_Map | C23: High-level dossier map | D23: Complete per market | E23: 10 | F23: Regulatory | G23: Not Started | H23: Overview only
A24: 7. Regulatory / PIF | B24: PIF_Checklist_ASEAN | C24: Detailed PIF checklist | D24: Complete per SKU/market | E24: 10 | F24: Regulatory | G24: Not Started | H24: Full closure checklist
... A35: 9. Development records | B35: Product_Development_Report | C35: Iterative formula development record: each improved version, driving feedback and competitor benchmarking | D35: Per SKU under development | E35: 04/05/08 | F35: NPD (Tuan) / Project owner | G35: Not Started | H35: Answers "is development being recorded?"; links Change Register + Feedback Form

Sheet PHASE1 G1-3 MKTG
A1: REVIEW OWNER: Kaukab (Facility / PM Operations) | Co-sign: Chris (Project Manager)
A2: MBc360 Development & Quality System | E2: PHASE 1 | G2: MBc360: GATES 1-3
A3: User & Product Definition | C3: RESPONSIBLE DEPARTMENT: MARKETING / SALES / PROJECT OWNER | E3: Success Criteria Package | G3: Competitor Analysis | I3: Marketing Campaign Brief | K3: Project Evidence Folder
E4: (provide link here) | G4: (provide link here) | I4: (provide link here) | K4: (provide link here)
A6: PROJECT IDENTIFICATION
A7: Parameter | B7: Identity / Value | C7: Date / Version | D7: Parameter | E7: Identity / Value | F7: Date / Version
A8: Project ID | D8: Date opened
A9: Product Code | D9: Target launch date
A10: Project Lead | D10: Product / SKU
A11: Product Group | D11: Owner / Department
A12: Brand / Customer | D12: Countries / Markets
A14: PHASE GATE FLOW - COMPLETE IN ORDER UNLESS A BACKTRACK / HOLD IS RECORDED
A15: Gate | B15: Plain-English stage | C15: Objective / minimum output | D15: Stage status | E15: Gate decision | F15: Owner | G15: Due date | H15: Evidence / workbook link | I15: Notes / blockers
A16: 01 | B16: Request & Opportunity | C16: Capture the request, opportunity, requester, commercial reason and first screening decision. | D16: Not Started | H16: Stage_Map
A17: 02 | B17: Target User & Brief | C17: Define target user, life stage, markets, use context, success criteria and constraints. | D17: Not Started | H17: Stage_Map
A18: 03 | B18: Product Concept & Claims | C18: Lock the product concept, claim direction, benchmark products and evidence needs. | D18: Not Started | H18: Stage_Map
A20: TARGET AREA OF BODY
A21: Gate | B21: Target User & Brief | C21: Select | D21: Owner / function | E21: Status / Y-N-NA | F21: Evidence / internal link | G21: Free-type notes / rationale
A22: 02 | B22: Face | C22: FALSE | D22: Marketing / Project owner
A23: 02 | B23: Hair | C23: FALSE | D23: Marketing / Project owner
A24: 02 | B24: Hands | C24: FALSE | D24: Marketing / Project owner
A25: 02 | B25: Muscle | C25: FALSE | D25: Marketing / Project owner
A26: 02 | B26: Skin (Whole Body) | C26: FALSE | D26: Marketing / Project owner
A27: 02 | B27: Feet | C27: FALSE | D27: Marketing / Project owner
A28: 02 | B28: Nails | C28: FALSE | D28: Marketing / Project owner
A29: 02 | B29: Internal | C29: FALSE | D29: Marketing / Project owner
A30: 02 | B30: Eyes | C30: FALSE | D30: Marketing / Project owner
A31: 02 | B31: Lips | C31: FALSE | D31: Marketing / Project owner
A32: 02 | B32: Intimate Zone | C32: FALSE | D32: Marketing / Project owner
A33: 02 | B33: Other - specify | C33: FALSE | D33: Marketing / Project owner
A35: PRODUCT TYPE
A36: Gate | B36: Type | C36: Select | D36: Owner / function | E36: Status / Y-N-NA | F36: Evidence / internal link | G36: Free-type notes / rationale
A37: 02 | B37: Cream | C37: FALSE | D37: Marketing / NPD
A38: 02 | B38: Lotion | C38: FALSE | D38: Marketing / NPD
A39: 02 | B39: Balm | C39: FALSE | D39: Marketing / NPD
A40: 02 | B40: Serum | C40: FALSE | D40: Marketing / NPD
A41: 02 | B41: Oil | C41: FALSE | D41: Marketing / NPD
A42: 02 | B42: Body oil | C42: FALSE | D42: Marketing / NPD
A43: 02 | B43: Hair oil | C43: FALSE | D43: Marketing / NPD
A44: 02 | B44: Wash | C44: FALSE | D44: Marketing / NPD
A45: 02 | B45: Body wash | C45: FALSE | D45: Marketing / NPD
A46: 02 | B46: Shower gel | C46: FALSE | D46: Marketing / NPD
A47: 02 | B47: Shampoo | C47: FALSE | D47: Marketing / NPD
A48: 02 | B48: 2-in-1 wash | C48: FALSE | D48: Marketing / NPD
... A63: 02 | B63: Other - specify | C63: FALSE | D63: Marketing / NPD
A65: TARGET USERS / LIFE STAGE
A66: Gate | B66: Target | C66: Select | D66: Owner / function | E66: Status / Y-N-NA | F66: Evidence / internal link | G66: Free-type notes / rationale
A67: 02 | B67: General adult | C67: FALSE | D67: Marketing / Regulatory
A68: 02 | B68: Pregnancy | C68: FALSE | D68: Marketing / Regulatory
A69: 02 | B69: Breastfeeding | C69: FALSE | D69: Marketing / Regulatory
A70: 02 | B70: Postpartum | C70: FALSE | D70: Marketing / Regulatory
A71: 02 | B71: Infant 0+ | C71: FALSE | D71: Marketing / Regulatory
A72: 02 | B72: Child 2+ | C72: FALSE | D72: Marketing / Regulatory
A73: 02 | B73: Child 3+ | C73: FALSE | D73: Marketing / Regulatory
A74: 02 | B74: Sensitive skin | C74: FALSE | D74: Marketing / Regulatory
A75: 02 | B75: Dry / eczema-prone skin | C75: FALSE | D75: Marketing / Regulatory
A76: 02 | B76: Oily skin | C76: FALSE | D76: Marketing / Regulatory
A77: 02 | B77: Intimate area | C77: FALSE | D77: Marketing / Regulatory
A78: 02 | B78: Swimmers | C78: FALSE | D78: Marketing / Regulatory
... A83: 02 | B83: Other - specify | C83: FALSE | D83: Marketing / Regulatory
A85: TARGET COUNTRIES / MARKETS
A86: Gate | B86: Target | C86: Select | D86: Owner / function | E86: Status / Y-N-NA | F86: Evidence / internal link | G86: Free-type notes / rationale
A87: 02 | B87: Australia | C87: FALSE | D87: Marketing / Regulatory
A88: 02 | B88: Malaysia | C88: FALSE | D88: Marketing / Regulatory
A89: 02 | B89: Vietnam | C89: FALSE | D89: Marketing / Regulatory
A90: 02 | B90: Singapore | C90: FALSE | D90: Marketing / Regulatory
A91: 02 | B91: Thailand | C91: FALSE | D91: Marketing / Regulatory
A92: 02 | B92: Indonesia | C92: FALSE | D92: Marketing / Regulatory
A93: 02 | B93: Philippines | C93: FALSE | D93: Marketing / Regulatory
A94: 02 | B94: China | C94: FALSE | D94: Marketing / Regulatory
A95: 02 | B95: Hong Kong | C95: FALSE | D95: Marketing / Regulatory
A96: 02 | B96: Taiwan | C96: FALSE | D96: Marketing / Regulatory
A97: 02 | B97: Japan | C97: FALSE | D97: Marketing / Regulatory
A98: 02 | B98: Korea | C98: FALSE | D98: Marketing / Regulatory
... A107: 02 | B107: Other - specify | C107: FALSE | D107: Marketing / Regulatory
A109: CLAIM / BENEFIT AREAS
A110: Gate | B110: Claim/Benefit | C110: Select | D110: Owner / function | E110: Status / Y-N-NA | F110: Evidence / internal link | G110: Free-type notes / rationale
A111: 03 | B111: Moisturising | C111: FALSE | D111: Marketing / Regulatory
A112: 03 | B112: Hydrating | C112: FALSE | D112: Marketing / Regulatory
A113: 03 | B113: Nourishing | C113: FALSE | D113: Marketing / Regulatory
A114: 03 | B114: Clarifying | C114: FALSE | D114: Marketing / Regulatory
A115: 03 | B115: Brightening | C115: FALSE | D115: Marketing / Regulatory
A116: 03 | B116: Radiance | C116: FALSE | D116: Marketing / Regulatory
A117: 03 | B117: Soothing | C117: FALSE | D117: Marketing / Regulatory
A118: 03 | B118: Calming | C118: FALSE | D118: Marketing / Regulatory
A119: 03 | B119: Barrier support | C119: FALSE | D119: Marketing / Regulatory
A120: 03 | B120: Protection | C120: FALSE | D120: Marketing / Regulatory
A121: 03 | B121: Anti-redness appearance | C121: FALSE | D121: Marketing / Regulatory
A122: 03 | B122: Comfort | C122: FALSE | D122: Marketing / Regulatory
... A142: 03 | B142: Other (Please Describe) | C142: FALSE | D142: Marketing / Regulatory
A144: INITIAL EVIDENCE / PROOF ROUTE
A145: Gate | B145: Option / choice transferred from legacy sheet | C145: Select | D145: Owner / function | E145: Status / Y-N-NA | F145: Evidence / internal link | G145: Free-type notes / rationale
A146: 03 | B146: Clinical / human study | C146: FALSE | D146: Regulatory / Scientific Review
A147: 03 | B147: Authority monograph | C147: FALSE | D147: Regulatory / Scientific Review
A148: 03 | B148: TGA accepted reference | C148: FALSE | D148: Regulatory / Scientific Review
A149: 03 | B149: FDA / EU / authority guidance | C149: FALSE | D149: Regulatory / Scientific Review
A150: 03 | B150: Peer-reviewed article | C150: FALSE | D150: Regulatory / Scientific Review
A151: 03 | B151: Supplier evidence | C151: FALSE | D151: Regulatory / Scientific Review
A152: 03 | B152: In-vitro / ex-vivo test | C152: FALSE | D152: Regulatory / Scientific Review
A153: 03 | B153: Internal test report | C153: FALSE | D153: Regulatory / Scientific Review
...

Sheet PHASE2 G4-6 NPD
A1: REVIEW OWNER: Kaukab (Facility / PM Operations) | Co-sign: Chris (Project Manager)
A2: MBc360 Development & Quality System | E2: PHASE 2 | G2: MBc360: GATES 4-6
A3: Ingredient & Formula Qualification | C3: RESPONSIBLE DEPARTMENT: NPD / R&I / PROCUREMENT / PACKAGING | E3: Ingredient Registry | G3: Formula BOM | I3: Packaging BOM | K3: Costing Calculator
E4: Clink for link | G4: (provide link here) | I4: (provide link here) | K4: (provide link here)
A6: PROJECT IDENTIFICATION
A7: Parameter | B7: Identity / Value | C7: Date / Version | D7: Parameter | E7: Identity / Value | F7: Date / Version
A8: Project ID | D8: Date opened
A9: Product Code | D9: Target launch date
A10: Project Lead | D10: Product / SKU
A11: Product Group | D11: Owner / Department
A12: Brand / Customer | D12: Countries / Markets
A14: PHASE GATE FLOW - COMPLETE IN ORDER UNLESS A BACKTRACK / HOLD IS RECORDED
A15: Gate | B15: Plain-English stage | C15: Objective / minimum output | D15: Stage status | E15: Gate decision | F15: Owner | G15: Due date | H15: Evidence / workbook link | I15: Notes / blockers
A16: 04 | B16: Ingredient & Supplier Screening | C16: Screen raw materials, suppliers, regulatory status, evidence pack, availability and risk flags. | D16: Not Started | H16: 04_Ingredient_Screening
A17: 05 | B17: Formula, Efficacy Route, BOM & Costing | C17: Confirm formula route, process targets, BOM, costing, active levels and technical feasibility. | D17: Not Started | H17: 05_Formula_BOM_Costing
A18: 06 | B18: Packaging & Artwork Requirements | C18: Confirm pack type, components, artwork needs, compatibility needs and supplier approvals. | D18: Not Started | H18: 06_Packaging_Artwork
A20: Do not re-enter Phase 1 target user/product/market/claim selections here. Use those choices as inputs and record only ingredient, formula, costing, packaging and artwork decisions.
A21: RAW MATERIAL DOCUMENT PACK
A22: Gate | B22: Documentation | C22: Select | D22: Owner / function | E22: Status / Y-N-NA | F22: Evidence / internal link | G22: Free-type notes / rationale
A23: 04 | B23: Specification | C23: FALSE | D23: R&I / Procurement
A24: 04 | B24: CoA | C24: FALSE | D24: R&I / Procurement
A25: 04 | B25: SDS | C25: FALSE | D25: R&I / Procurement
A26: 04 | B26: TDS | C26: FALSE | D26: R&I / Procurement
A27: 04 | B27: Composition statement | C27: FALSE | D27: R&I / Procurement
A28: 04 | B28: Allergen statement | C28: FALSE | D28: R&I / Procurement
A29: 04 | B29: Impurity statement | C29: FALSE | D29: R&I / Procurement
A30: 04 | B30: Heavy metal statement | C30: FALSE | D30: R&I / Procurement
A31: 04 | B31: Residual solvent statement | C31: FALSE | D31: R&I / Procurement
A32: 04 | B32: Micro statement | C32: FALSE | D32: R&I / Procurement
A33: 04 | B33: Origin statement | C33: FALSE | D33: R&I / Procurement
A34: 04 | B34: GMO statement | C34: FALSE | D34: R&I / Procurement
... A42: 04 | B42: Other (Please Describe) | C42: FALSE | D42: R&I / Procurement
A44: FORMULATION DESIGN REQUIREMENTS
A45: Gate | B45: Requirement / field | C45: Minimum requirement | D45: Rationale / control reason | E45: Owner | F45: Status | G45: Evidence link | H45: Notes / action
A46: 05 | B46: Target pH / pH range | C46: Target and accepted range entered | D46: Controls skin compatibility, stability and preservative performance | E46: R&I / Quality | F46: Not Started
A47: 05 | B47: Appearance / colour / odour | C47: Target sensory appearance defined | D47: Gives manufacturing and QC a visible acceptance point | E47: R&I / Marketing | F47: Not Started
A48: 05 | B48: Texture / viscosity / sensory requirement | C48: Target texture and viscosity defined | D48: Aligns consumer promise with formula and pack feasibility | E48: R&I / Marketing | F48: Not Started
A49: 05 | B49: Fragrance requirement | C49: Fragrance-free/fragranced/natural scent requirement recorded | D49: Controls allergen, claim and sensory implications | E49: R&I / Regulatory | F49: Not Started
A50: 05 | B50: Key actives and target levels | C50: Active levels, grade/marker and purpose recorded | D50: Prevents ingredient-presence-only efficacy claims | E50: R&I / Scientific Review | F50: Not Started
A51: 05 | B51: Compatibility / use-with constraints | C51: Use-with, pack and ingredient interactions recorded | D51: Controls formula compatibility and real-world use risks | E51: R&I / Quality | F51: Not Started
A52: 05 | B52: Formula constraints / exclusions | C52: Restricted, prohibited or customer-excluded ingredients recorded | D52: Prevents rework and regulatory gaps | E52: R&I / Regulatory | F52: Not Started
A53: 05 | B53: Scale-up or manufacturing notes | C53: Critical process parameters and scale-up notes recorded | D53: Maintains formula performance during manufacturing | E53: Manufacturing / Quality | F53: Not Started
A55: EFFICACY AND PROCESS PROTECTION CHECKS
A56: Gate | B56: Requirement / field | C56: Minimum requirement | D56: Rationale / control reason | E56: Owner | F56: Status | G56: Evidence link | H56: Notes / action
A57: 05 | B57: Mechanism-to-formula route | C57: Claim mechanism linked to formula ingredients and levels | D57: Prevents unsupported efficacy claims | E57: R&I | F57: Not Started
A58: 05 | B58: Heat/light/pH sensitivity | C58: Max temperature, hold time, pH range and handling defined for sensitive actives | D58: Protects efficacy during manufacturing | E58: R&I / Manufacturing | F58: Not Started
A59: 05 | B59: Pre-processing method | C59: Dispersion, hydration or activation method documented where relevant | D59: Ensures consistent performance | E59: R&I / Manufacturing | F59: Not Started
A60: 05 | B60: Scale-up equivalence | C60: Critical process parameters and in-process QC defined for pilot/production | D60: Ensures the product delivers intended benefit | E60: Manufacturing / Quality | F60: Not Started
A61: 05 | B61: Finished product efficacy markers | C61: pH/viscosity/appearance/active marker checked as needed | D61: Supports release and stability conclusion | E61: Quality | F61: Not Started
A63: SENSORY / APPEARANCE CHOICES
A64: Gate | B64: Sensory/Appearance | C64: Select | D64: Owner / function | E64: Status / Y-N-NA | F64: Evidence / internal link | G64: Free-type notes / rationale
A65: 05 | B65: Lightweight | C65: FALSE | D65: R&I / Marketing
A66: 05 | B66: Rich | C66: FALSE | D66: R&I / Marketing
A67: 05 | B67: Non-greasy | C67: FALSE | D67: R&I / Marketing
A68: 05 | B68: Fast absorbing | C68: FALSE | D68: R&I / Marketing
A69: 05 | B69: Silky | C69: FALSE | D69: R&I / Marketing
A70: 05 | B70: Creamy | C70: FALSE | D70: R&I / Marketing
A71: 05 | B71: Foaming | C71: FALSE | D71: R&I / Marketing
A72: 05 | B72: Low foam | C72: FALSE | D72: R&I / Marketing
A73: 05 | B73: Clear | C73: FALSE | D73: R&I / Marketing
A74: 05 | B74: Pearlescent | C74: FALSE | D74: R&I / Marketing
A75: 05 | B75: White | C75: FALSE | D75: R&I / Marketing
A76: 05 | B76: Tinted | C76: FALSE | D76: R&I / Marketing
... A86: 05 | B86: Pipette-friendly | C86: FALSE | D86: R&I / Marketing
A88: PACKAGING OPTIONS
A89: Gate | B89: Packaging | C89: Select | D89: Owner / function | E89: Status / Y-N-NA | F89: Evidence / internal link | G89: Free-type notes / rationale
A90: 06 | B90: Tube | C90: FALSE | D90: Packaging / NPD
A91: 06 | B91: Bottle | C91: FALSE | D91: Packaging / NPD
A92: 06 | B92: Pump bottle | C92: FALSE | D92: Packaging / NPD
A93: 06 | B93: Airless pump | C93: FALSE | D93: Packaging / NPD
A94: 06 | B94: Jar | C94: FALSE | D94: Packaging / NPD
A95: 06 | B95: Sachet | C95: FALSE | D95: Packaging / NPD
A96: 06 | B96: Spray bottle | C96: FALSE | D96: Packaging / NPD
A97: 06 | B97: Mist pump | C97: FALSE | D97: Packaging / NPD
A98: 06 | B98: Dropper / pipette | C98: FALSE | D98: Packaging / NPD
A99: 06 | B99: Roll-on | C99: FALSE | D99: Packaging / NPD
A100: 06 | B100: Foamer | C100: FALSE | D100: Packaging / NPD
A101: 06 | B101: Cap / flip top | C101: FALSE | D101: Packaging / NPD
... A109: 06 | B109: Other (Please Describe) | C109: FALSE | D109: Packaging / NPD
A111: ARTWORK / REGULATORY READINESS TRIGGERS
A112: Gate | B112: Option / choice transferred from legacy sheet | C112: Select | D112: Owner / function | E112: Status / Y-N-NA | F112: Evidence / internal link | G112: Free-type notes / rationale
A113: 06 | B113: Artwork/label route required | C113: FALSE | D113: Packaging / Regulatory
A114: 06 | B114: Product classification checked | C114: FALSE | D114: Packaging / Regulatory
A115: 06 | B115: Claims wording review required | C115: FALSE | D115: Packaging / Regulatory
A116: 06 | B116: Disease / therapeutic risk screen | C116: FALSE | D116: Packaging / Regulatory
A117: 06 | B117: Label compliance check | C117: FALSE | D117: Packaging / Regulatory
A118: 06 | B118: Ingredient restrictions reviewed | C118: FALSE | D118: Packaging / Regulatory
A119: 06 | B119: Allergen declaration needed | C119: FALSE | D119: Packaging / Regulatory
A120: 06 | B120: PIF / evidence file link needed | C120: FALSE | D120: Packaging / Regulatory
A121: 06 | B121: Authority submission needed | C121: FALSE | D121: Packaging / Regulatory
A122: 06 | B122: Registration needed | C122: FALSE | D122: Packaging / Regulatory
A123: 06 | B123: Distributor evidence pack | C123: FALSE | D123: Packaging / Regulatory
A124: 06 | B124: Sales FAQ / approved wording | C124: FALSE | D124: Packaging / Regulatory
... A126: 06 | B126: Other (Please Describe) | C126: FALSE | D126: Packaging / Regulatory
A128: KEY GATE CHECKS - GATES 4-6
A129: Gate | B129: Key check | C129: Done | D129: Y/N/NA | E129: Date | F129: Evidence / reference | G129: Method reference | H129: Internal link | I129: Initials | J129: Notes / action
A130: 04 | B130: Ingredient functions identified and RM document pack requested | C130: FALSE | D130: N/A
A131: 04 | B131: Restrictions, exclusions and supplier risks screened | C131: FALSE | D131: N/A
A132: 04 | B132: Ingredient evidence / registry links added or gap actions opened | C132: FALSE | D132: N/A
A133: 05 | B133: Formula route, BOM and costing started | C133: FALSE | D133: N/A
...

Sheet PHASE3 G7-9 QUAL
A1: REVIEW OWNER: Kaukab (Facility / PM Operations) | Co-sign: Chris (Project Manager)
A2: MBc360 Development & Quality System | E2: PHASE 3 | G2: MBc360: GATES 7-9
A3: Validation & Quality Control | C3: RESPONSIBLE DEPARTMENT: QUALITY / SAFETY / R&I / MANUFACTURING | E3: Study Protocol | G3: Evidence Register | I3: Test Report Index | K3: GMP Links
E4: (provide link here) | G4: (provide link here) | I4: (provide link here) | K4: (provide link here)
A6: PROJECT IDENTIFICATION
A7: Parameter | B7: Identity / Value | C7: Date / Version | D7: Parameter | E7: Identity / Value | F7: Date / Version
A8: Project ID | D8: Date opened
A9: Product Code | D9: Target launch date
A10: Project Lead | D10: Product / SKU
A11: Product Group | D11: Owner / Department
A12: Brand / Customer | D12: Countries / Markets
A14: PHASE GATE FLOW - COMPLETE IN ORDER UNLESS A BACKTRACK / HOLD IS RECORDED
A15: Gate | B15: Plain-English stage | C15: Objective / minimum output | D15: Stage status | E15: Gate decision | F15: Owner | G15: Due date | H15: Evidence / workbook link | I15: Notes / blockers
A16: 07 | B16: Maternal & Baby-Contact Safety | C16: Complete maternal use, pregnancy/breastfeeding, infant-contact exposure and sensitive-user screening. | D16: Not Started | H16: 07_Maternal_Baby_Safety
A17: 08 | B17: Efficacy Testing, Methods & Validation | C17: Define testing, participant study requirements, method validation, QC and evidence generation plan. | D17: Not Started | H17: 08_Testing_Validation
A18: 09 | B18: Stability, Compatibility & Release Readiness | C18: Confirm stability, preservation, pack compatibility, pilot/scale-up and release readiness. | D18: Not Started | H18: 09_Stability_Release
A20: Phase 3 proves whether the Phase 1-2 choices are safe, valid, stable and releasable. It does not repeat product positioning choices unless a backtrack is required.
A21: SKINCARE FOR TWO MANDATORY SAFETY CHECKS
A22: Gate | B22: Requirement / field | C22: Minimum requirement | D22: Rationale / control reason | E22: Owner | F22: Status | G22: Evidence link | H22: Notes / action
A23: 07 | B23: Pregnancy & breastfeeding review | C23: Mandatory for maternal products | D23: Maternal use is a defined vulnerable-use context | E23: Safety | F23: Not Started
A24: 07 | B24: Infant/baby contact exposure | C24: Assess skin-to-skin, residue transfer, nipple/breast contact and indirect exposure | D24: Baby contact is considered from the start | E24: Safety | F24: Not Started
A25: 07 | B25: Dermal exposure / MOS logic | C25: Route, concentration, frequency, body area and limit/MOS conclusion recorded | D25: Needed for HCP/distributor confidence | E25: Safety | F25: Not Started
A26: 07 | B26: Prohibited ingredient check | C26: Complete Prohibited_Ingredients and attach evidence | D26: Proves absence of banned/high-risk substances | E26: Regulatory | F26: Not Started
A27: 07 | B27: Caution-limit check | C27: Complete PB_Caution_Limits and document formula status | D27: Concentration-based validation | E27: Safety | F27: Not Started
A28: 07 | B28: Medical summary input | C28: Complete summary fields required for HCP/distributor pack | D28: Creates ready-to-answer output | E28: Project owner | F28: Not Started
A30: TESTING FAMILIES / RELEASE TEST ROUTES (Note: Only To Be Ticked When All RM Are Approved)
A31: Gate | B31: Test | C31: Select | D31: Owner / function | E31: Status / Y-N-NA | F31: Evidence / internal link | G31: Free-type notes / rationale | H31: Link To RM Review Sheet
A32: 08-09 | B32: Stability - accelerated | C32: FALSE | D32: Quality / R&I
A33: 08-09 | B33: Stability - real time | C33: FALSE | D33: Quality / R&I
A34: 08-09 | B34: Microbiological quality | C34: FALSE | D34: Quality / R&I
A35: 08-09 | B35: PET / preservative efficacy | C35: FALSE | D35: Quality / R&I
A36: 08-09 | B36: Pack compatibility | C36: FALSE | D36: Quality / R&I
A37: 08-09 | B37: pH / viscosity / appearance | C37: FALSE | D37: Quality / R&I
A38: 08-09 | B38: Heavy metals | C38: FALSE | D38: Quality / R&I
A39: 08-09 | B39: Residual solvents | C39: FALSE | D39: Quality / R&I
A40: 08-09 | B40: 1,4-dioxane | C40: FALSE | D40: Quality / R&I
A41: 08-09 | B41: Nitrosamines / NDELA | C41: FALSE | D41: Quality / R&I
A42: 08-09 | B42: PAH | C42: FALSE | D42: Quality / R&I
A43: 08-09 | B43: Pesticides / herbicides | C43: FALSE | D43: Quality / R&I
... A51: 08-09 | B51: Other (Please Describe) | C51: FALSE | D51: Quality / R&I
A53: HUMAN / CONSUMER STUDY AND METHOD VALIDATION CHECKS
A54: Gate | B54: Requirement / field | C54: Minimum requirement | D54: Rationale / control reason | E54: Owner | F54: Status | G54: Evidence link | H54: Notes / action
A55: 08 | B55: Study protocol required? | C55: Required if human, clinical, consumer, tolerance or efficacy evidence supports claims | D55: Prevents unsupported or informal claims | E55: Study owner | F55: Not Started
A56: 08 | B56: Participant number justified | C56: Target participant number and sample-size rationale recorded | D56: Supports stronger product claims | E56: Study owner | F56: Not Started
A57: 08 | B57: Approval trail | C57: Proposal, Head/HOD sign-off and independent reviewer sign-off saved | D57: Independent paper trail | E57: Project owner | F57: Not Started
A58: 08 | B58: Consent and recruitment log | C58: Participant information, consent and coded registry saved | D58: Paper trail and participant protection | E58: Study owner | F58: Not Started
A59: 08 | B59: AE / stop rules | C59: Adverse event pathway, stop rules and escalation contact defined | D59: Safety control | E59: Quality / Safety | F59: Not Started
A60: 08 | B60: Final report | C60: Participant count, deviations, data location and claim conclusion recorded | D60: Evidence usable by HCP/distributor | E60: Study owner | F60: Not Started
A62: STABILITY / COMPATIBILITY / RELEASE READINESS CHECKS
A63: Gate | B63: Requirement / field | C63: Minimum requirement | D63: Rationale / control reason | E63: Owner | F63: Status | G63: Evidence link | H63: Notes / action
A64: 09 | B64: Stability program selected | C64: Accelerated and/or real-time plan selected with acceptance criteria | D64: Supports shelf-life and PIF readiness | E64: Quality | F64: Not Started
A65: 09 | B65: Preservation / microbiology checks selected | C65: Micro/PET pathway selected or justified as N/A | D65: Controls microbiological risk | E65: Quality | F65: Not Started
A66: 09 | B66: Pack compatibility assessed | C66: Pack compatibility, leakage, transport or interaction testing selected | D66: Confirms package protects product | E66: Packaging / Quality | F66: Not Started
A67: 09 | B67: Release readiness risks closed | C67: Open stability, micro, pack and pilot-batch blockers closed or conditionally accepted | D67: Prevents uncontrolled launch | E67: Quality / Manufacturing | F67: Not Started
A68: 09 | B68: Retest or CAPA pathway defined | C68: Retest, deviation or CAPA actions assigned where required | D68: Makes failures visible and traceable | E68: Quality | F68: Not Started
A70: KEY GATE CHECKS - GATES 7-9
A71: Gate | B71: Key check | C71: Done | D71: Y/N/NA | E71: Date | F71: Evidence / reference | G71: Method reference | H71: Internal link | I71: Initials | J71: Notes / action
A72: 07 | B72: Safety/tolerance questions defined and vulnerable-user risks reviewed | C72: FALSE | D72: N/A
A73: 07 | B73: Pregnancy/breastfeeding and baby-contact screen completed where triggered | C73: FALSE | D73: N/A
A74: 07 | B74: Restrictions, conditions and safety evidence linked | C74: FALSE | D74: N/A
A75: 08 | B75: Testing families selected and methods/protocols referenced | C75: FALSE | D75: N/A
A76: 08 | B76: Validation report linked or placeholder/action used | C76: FALSE | D76: N/A
A77: 08 | B77: Acceptance criteria, results and CAPA pathway defined | C77: FALSE | D77: N/A
A78: 09 | B78: Stability, preservation/micro and pack compatibility program selected | C78: FALSE | D78: N/A
A79: 09 | B79: Pilot/scale-up and release criteria assessed | C79: FALSE | D79: N/A
A80: 09 | B80: Release readiness risks closed or conditionally accepted | C80: FALSE | D80: N/A
A82: 8 ANGLES COVERAGE - APPLY TO THE PHASE BEFORE GATE CLOSURE
A83: Angle | B83: Y/N/NA | C83: Covered | D83: Date | E83: Evidence / reference | F83: Internal link | G83: Initials | H83: Comments
A84: Consumer need | B84: N/A
A85: Use context & life stage | B85: N/A
A86: Ingredient suitability | B86: N/A
A87: Formula compatibility | B87: N/A
A88: Safety | B88: N/A
A89: Quality | B89: N/A
A90: Claims evidence | B90: N/A
A91: Real-world performance | B91: N/A
A93: EVIDENCE SUMMARY, DECISION AND SIGN-OFF
A94: Evidence summary / decision rationale
A99: Role | B99: Name | C99: Signature / initials | D99: Date | E99: Decision | F99: Comments / conditions
A100: Prepared by
A101: Reviewed by
A102: Approved by
A104: Next action | H104: Next due date | J104: Owner
A108: EXTENDED USER-SAFETY COMPARTMENTS - PREGNANCY / BREASTFEEDING / INFANT / SWIMMER
A109: Each compartment is add-only. Complete per formula/SKU where the use context applies. Y/N/NA + Status controlled. Links to PB_Caution_Limits, Eye_Safety_Evid, Formulation_Safety and Stability_Release where relevant.
A111: COMPARTMENT 1 - PREGNANCY SAFETY & CHARACTERISTICS
A112: Ref | B112: Requirement / characteristic | C112: Minimum requirement / what to capture | D112: Rationale / control reason | E112: Owner | F112: Status | G112: Y/N/NA | H112: Evidence link / notes
A113: PRG-01 | B113: Pregnancy suitability decision | C113: State whether product is suitable / cautioned / not recommended during pregnancy | D113: Defined vulnerable-use context; must not be assumed safe | E113: Safety | F113: Not Started | H113: See PB_Caution_Limits
A114: PRG-02 | B114: Ingredient caution-limit check (pregnancy) | C114: Each active/retinoid/salicylate/essential-oil checked vs pregnancy caution limits | D114: Concentration-based validation for maternal use | E114: Safety / Regulatory | F114: Not Started | H114: ChiChu-PB_Caution_Limits
A115: PRG-03 | B115: Prohibited / restricted actives | C115: Confirm absence of pregnancy-contraindicated actives (e.g. retinoids, high-dose salicylic) | D115: Proves absence of high-risk substances | E115: Regulatory | F115: Not Started
A116: PRG-04 | B116: Dermal exposure / MOS (pregnancy) | C116: Route, body area, frequency, concentration and MOS conclusion recorded | D116: HCP/distributor confidence for maternal claim | E116: Safety | F116: Not Started
A117: PRG-05 | B117: Fragrance / allergen review | C117: IFRA + allergen review appropriate for pregnancy sensitivity | D117: Heightened sensory sensitivity in pregnancy | E117: R&I / Regulatory | F117: Not Started | H117: ChiChu-Fragrance_Safety
A118: PRG-06 | B118: Claim wording control (pregnancy) | C118: Approved maternal wording; no implied medical/therapeutic claim | D118: Prevents unsupported maternal claims | E118: Claims / Regulatory | F118: Not Started | H118: George-Mechanism_Claims
A119: PRG-07 | B119: Label / PIF statement | C119: Pregnancy usage statement matches released label and PIF | D119: Consistency between label, PIF and evidence | E119: Regulatory | F119: Not Started | H119: Lily-Released_Label_Ctrl
A120: PRG-08 | B120: Sign-off (pregnancy compartment) | C120: Prepared / reviewed / independent sign-off recorded | D120: Controlled approval trail | E120: Safety / HOD | F120: Not Started
A122: COMPARTMENT 2 - BREASTFEEDING SAFETY & CHARACTERISTICS
A123: Ref | B123: Requirement / characteristic | C123: Minimum requirement / what to capture | D123: Rationale / control reason | E123: Owner | F123: Status | G123: Y/N/NA | H123: Evidence link / notes
A124: BF-01 | B124: Breastfeeding suitability decision | C124: State suitable / cautioned / not recommended while breastfeeding | D124: Maternal use with infant proximity | E124: Safety | F124: Not Started
A125: BF-02 | B125: Nipple / breast-contact exposure | C125: Assess residue transfer and indirect infant ingestion risk if applied near breast | D125: Infant indirect exposure control | E125: Safety | F125: Not Started
A126: BF-03 | B126: Ingredient caution-limit check (lactation) | C126: Actives checked vs breastfeeding caution limits | D126: Concentration-based validation | E126: Safety / Regulatory | F126: Not Started | H126: ChiChu-PB_Caution_Limits
...

Sheet PHASE4 G10-12 REG
A1: REVIEW OWNER: Kaukab (Facility / PM Operations) | Co-sign: Chris (Project Manager)
A2: MBc360 Development & Quality System | E2: PHASE 4 | G2: MBc360: GATES 10-12
A3: Evidence, Release & Improvement | C3: RESPONSIBLE DEPARTMENT: REGULATORY / QUALITY / MANAGEMENT / SALES | E3: PIF Checklist | G3: Published Info Approval | I3: Change Control | K3: Post-Market Log
E4: (provide link here) | G4: (provide link here) | I4: (provide link here) | K4: (provide link here)
A6: PROJECT IDENTIFICATION
A7: Parameter | B7: Identity / Value | C7: Date / Version | D7: Parameter | E7: Identity / Value | F7: Date / Version
A8: Project ID | D8: Date opened
A9: Product Code | D9: Target launch date
A10: Project Lead | D10: Product / SKU
A11: Product Group | D11: Owner / Department
A12: Brand / Customer | D12: Countries / Markets
A14: PHASE GATE FLOW - COMPLETE IN ORDER UNLESS A BACKTRACK / HOLD IS RECORDED
A15: Gate | B15: Plain-English stage | C15: Objective / minimum output | D15: Stage status | E15: Gate decision | F15: Owner | G15: Due date | H15: Evidence / workbook link | I15: Notes / blockers
A16: 10 | B16: Regulatory Dossier, Claims & Efficacy Evidence | C16: Complete claims evidence, country matching, PIF/CPSR mapping and distributor/HCP evidence pack needs. | D16: Not Started | H16: 10_Dossier_Claims
A17: 11 | B17: Production, Launch & Sales Support Sign-Off | C17: Confirm production readiness, Cosmetri/system records, launch sign-off and approved sales support. | D17: Not Started | H17: 11_Launch_SignOff
A18: 12 | B18: Post-Market Monitoring & Improvement | C18: Capture market feedback, complaints, PV/PMS, CAPA, real-world performance and improvement actions. | D18: Not Started | H18: 12_PostMarket_Improve
A20: Phase 4 converts the approved development record into dossier evidence, launch approval and a monitored post-market improvement loop. Claim/market/product choices are referenced from Phase 1, not re-entered.
A21: DOSSIER / HCP EVIDENCE CHECKS
A22: Gate | B22: Requirement / field | C22: Minimum requirement | D22: Rationale / control reason | E22: Owner | F22: Status | G22: Evidence link | H22: Notes / action
A23: 10 | B23: ASEAN PIF mapped | C23: Complete ASEAN_PIF_Map and PIF_Checklist_ASEAN | D23: Regulatory dossier completeness | E23: Regulatory | F23: Not Started
A24: 10 | B24: Product Safety Summary | C24: Complete Medical_Summary safety sections | D24: Ready-to-answer output | E24: Safety | F24: Not Started
A25: 10 | B25: Ingredient Risk Table | C25: Prohibited + caution ingredient conclusions complete | D25: Answers distributor/HCP risk questions | E25: Safety / Regulatory | F25: Not Started
A26: 10 | B26: Substitution Table | C26: Ingredient_Substitution complete where relevant | D26: Answers ingredient substitution questions | E26: R&I / Safety | F26: Not Started
A27: 10 | B27: Efficacy evidence summary | C27: Human, in-vitro/ex-vivo, clinical/literature and internal evidence summarised | D27: Answers efficacy proof questions | E27: R&I / Study owner | F27: Not Started
A28: 10 | B28: Approved HCP wording | C28: Explain evidence without unsupported pregnancy-safe or therapeutic label claims | D28: Controls external wording | E28: Regulatory / Marketing | F28: Not Started
A29: 10 | B29: PIF/CPSR export-ready | C29: Dossier package reviewed and approved | D29: Market/distributor readiness | E29: Regulatory | F29: Not Started
A30: 10 | B30: Country-specific restrictions | C30: Vietnam/ASEAN/EU/Australia/US wording checked as applicable | D30: Claim and advertising control | E30: Regulatory | F30: Not Started
A32: REGULATORY / CLAIMS CLOSURE CHECKS
A33: Gate | B33: Check | C33: Select | D33: Owner / function | E33: Status / Y-N-NA | F33: Evidence / internal link | G33: Free-type notes / rationale
A34: 10 | B34: Artwork/label route required | C34: FALSE | D34: Regulatory / Claims
A35: 10 | B35: Product classification checked | C35: FALSE | D35: Regulatory / Claims
A36: 10 | B36: Claims wording review required | C36: FALSE | D36: Regulatory / Claims
A37: 10 | B37: Disease / therapeutic risk screen | C37: FALSE | D37: Regulatory / Claims
A38: 10 | B38: Label compliance check | C38: FALSE | D38: Regulatory / Claims
A39: 10 | B39: Ingredient restrictions reviewed | C39: FALSE | D39: Regulatory / Claims
A40: 10 | B40: Allergen declaration needed | C40: FALSE | D40: Regulatory / Claims
A41: 10 | B41: PIF / evidence file link needed | C41: FALSE | D41: Regulatory / Claims
A42: 10 | B42: Authority submission needed | C42: FALSE | D42: Regulatory / Claims
A43: 10 | B43: Registration needed | C43: FALSE | D43: Regulatory / Claims
A44: 10 | B44: Distributor evidence pack | C44: FALSE | D44: Regulatory / Claims
A45: 10 | B45: Sales FAQ / approved wording | C45: FALSE | D45: Regulatory / Claims
... A47: 10 | B47: Other (Please Describe) | C47: FALSE | D47: Regulatory / Claims
A49: PRODUCTION / LAUNCH RECORDS
A50: Gate | B50: Record | C50: Select | D50: Owner / function | E50: Status / Y-N-NA | F50: Evidence / internal link | G50: Free-type notes / rationale
A51: 11 | B51: Product record | C51: FALSE | D51: Manufacturing / Quality
A52: 11 | B52: Formula version | C52: FALSE | D52: Manufacturing / Quality
A53: 11 | B53: Raw material records | C53: FALSE | D53: Manufacturing / Quality
A54: 11 | B54: Packaging item records | C54: FALSE | D54: Manufacturing / Quality
A55: 11 | B55: Packaging set | C55: FALSE | D55: Manufacturing / Quality
A56: 11 | B56: LOI / INCI export | C56: FALSE | D56: Manufacturing / Quality
A57: 11 | B57: GMP batch record + in-process QC | C57: FALSE | D57: Manufacturing / Quality
A58: 11 | B58: PIF / dossier export | C58: FALSE | D58: Manufacturing / Quality
A59: 11 | B59: Formula version + process controls | C59: FALSE | D59: Manufacturing / Quality
A60: 11 | B60: MRP / shortages | C60: FALSE | D60: Manufacturing / Quality
A61: 11 | B61: QA test group | C61: FALSE | D61: Manufacturing / Quality
A62: 11 | B62: Batch ticket | C62: FALSE | D62: Manufacturing / Quality
... A64: 11 | B64: GMP deviation / CAPA trigger | C64: FALSE | D64: Manufacturing / Quality
A66: POST-MARKET / PV-PMS FEEDBACK SOURCES
A67: Gate | B67: Post-Market Option | C67: Select | D67: Owner / function | E67: Status / Y-N-NA | F67: Evidence / internal link | G67: Free-type notes / rationale
A68: 12 | B68: Consumer feedback | C68: FALSE | D68: Quality / PV-PMS
A69: 12 | B69: HCP feedback | C69: FALSE | D69: Quality / PV-PMS
A70: 12 | B70: Distributor feedback | C70: FALSE | D70: Quality / PV-PMS
A71: 12 | B71: Retailer feedback | C71: FALSE | D71: Quality / PV-PMS
A72: 12 | B72: Sales feedback | C72: FALSE | D72: Quality / PV-PMS
A73: 12 | B73: Social media feedback | C73: FALSE | D73: Quality / PV-PMS
A74: 12 | B74: Complaint | C74: FALSE | D74: Quality / PV-PMS
A75: 12 | B75: Adverse event / PV signal | C75: FALSE | D75: Quality / PV-PMS
A76: 12 | B76: PMS trend | C76: FALSE | D76: Quality / PV-PMS
A77: 12 | B77: Claim question | C77: FALSE | D77: Quality / PV-PMS
A78: 12 | B78: Packaging issue | C78: FALSE | D78: Quality / PV-PMS
A79: 12 | B79: Formula issue | C79: FALSE | D79: Quality / PV-PMS
... A83: 12 | B83: Product optimisation | C83: FALSE | D83: Quality / PV-PMS
A85: CHANGE CONTROL / COMMUNICATION CLOSURE CHECKS
A86: Gate | B86: Requirement / field | C86: Minimum requirement | D86: Rationale / control reason | E86: Owner | F86: Status | G86: Evidence link | H86: Notes / action
A87: ALL | B87: Change trigger opened | C87: Change_Control_Comm row opened for artwork, formula, label, claim, supplier, process, packaging or market change | D87: Prevents silent corrections | E87: Project owner / QA | F87: Not Started
A88: ALL | B88: Old-vs-new impact assessed | C88: Affected SKU, market, claim, PIF, safety, efficacy, cost, stock and launch timing reviewed | D88: Makes impact visible | E88: Relevant function owner | F88: Not Started
A89: ALL | B89: Approval and communication completed | C89: Required functions approved and Sales/Marketing notified where customer-facing | D89: Controls external messages | E89: Project owner | F89: Not Started
A90: ALL | B90: Obsolete versions controlled | C90: Old artwork/formula/claim/deck versions withdrawn or superseded | D90: Prevents wrong-file use | E90: QA / Document owner | F90: Not Started
A91: ALL | B91: Published information approved | C91: Public, pharmacy, HCP or distributor wording approved before use | D91: Avoids unsupported claims | E91: Regulatory / Marketing | F91: Not Started
A92: ALL | B92: Closure evidence saved | C92: Final file links, approvals, communication evidence and closure notes saved | D92: Completes audit trail | E92: Project owner | F92: Not Started
A94: KEY GATE CHECKS - GATES 10-12
A95: Gate | B95: Key check | C95: Done | D95: Y/N/NA | E95: Date | F95: Evidence / reference | G95: Method reference | H95: Internal link | I95: Initials | J95: Notes / action
A96: 10 | B96: Evidence hierarchy applied and claims wording checked | C96: FALSE | D96: N/A
A97: 10 | B97: Countries/regulatory pathway matched and PIF/evidence file mapped | C97: FALSE | D97: N/A
A98: 10 | B98: Approved wording / limitations recorded | C98: FALSE | D98: N/A
A99: 11 | B99: Final formula/version, packaging and artwork approved | C99: FALSE | D99: N/A
A100: 11 | B100: Cosmetri/production records ready and GMP links added | C100: FALSE | D100: N/A
A101: 11 | B101: Launch sign-off completed and blockers recorded | C101: FALSE | D101: N/A
A102: 12 | B102: Feedback sources monitored and PV/PMS signals classified | C102: FALSE | D102: N/A
A103: 12 | B103: Complaints/issues triaged and CAPA/improvement actions assigned | C103: FALSE | D103: N/A
A104: 12 | B104: Loopback to NPD or change control recorded where needed | C104: FALSE | D104: N/A
A106: 8 ANGLES COVERAGE - APPLY TO THE PHASE BEFORE GATE CLOSURE
A107: Angle | B107: Y/N/NA | C107: Covered | D107: Date | E107: Evidence / reference | F107: Internal link | G107: Initials | H107: Comments
B108: N/A | C108: FALSE
A109: Use context & life stage | B109: N/A | C109: FALSE
A110: Ingredient suitability | B110: N/A | C110: FALSE
A111: Formula compatibility | B111: N/A | C111: FALSE
A112: Safety | B112: N/A | C112: FALSE
A113: Quality | B113: N/A | C113: FALSE
A114: Claims evidence | B114: N/A | C114: FALSE
...

Sheet Stage_Map
A1: REVIEW OWNER: Kaukab (Facility / PM Operations) | Co-sign: Chris (Project Manager)
A2: MBc360 Development & Quality System | E2: PHASE MAP | G2: MBc360: GATES 1-12
A3: Stage Map and Workbook Navigation | C3: RESPONSIBLE DEPARTMENT: ALL FUNCTIONS | E3: Primary workbook tabs | G3: Legacy detail | I3: Rule | K3: Evidence
E4: 4 phase-gate tabs | G4: support/reference | I4: no duplicate entry | K4: supporting sheets
A6: CONSOLIDATED GATE MAP
A7: Gate | B7: Plain-English stage | C7: Primary working tab | D7: Phase | E7: Purpose | F7: Primary owner | G7: Key outputs | H7: Legacy/detail sheet
A8: SG01 | B8: Gate 01 - Request & Opportunity | C8: PHASE 1; GATE 1-3 (MARKETING) | D8: Phase 1 - User & Product Definition | E8: Capture request, opportunity, requester, business reason and first screening decision. | F8: Project owner / Sales / NPD | G8: Request triage, project record, first decision | H8: Stage_Map
A9: SG02 | B9: Gate 02 - Target User & Product Brief | C9: PHASE 1; GATE 1-3 (MARKETING) | D9: Phase 1 - User & Product Definition | E9: Define target user, life stage, market, brief, use context and success criteria. | F9: Project owner / Marketing / Regulatory | G9: Brief, target users, markets, success criteria | H9: Stage_Map
A10: SG03 | B10: Gate 03 - Product Concept & Claims | C10: PHASE 1; GATE 1-3 (MARKETING) | D10: Phase 1 - User & Product Definition | E10: Lock concept, claim direction, benchmark products and evidence needs. | F10: Marketing / Regulatory / R&I | G10: Claims brief, competitor review, evidence needs | H10: Evidence_Register
A11: SG04 | B11: Gate 04 - Ingredient & Supplier Screening | C11: PHASE 2; GATE 4-6 (NPD) | D11: Phase 2 - Ingredient & Formula Qualification | E11: Screen ingredients, raw materials, suppliers, regulatory status, availability and risk flags. | F11: R&I / Regulatory / Procurement | G11: RM evidence, supplier docs, risk flags | H11: 04_Ingredient_Screening
A12: SG05 | B12: Gate 05 - Formula, BOM & Costing | C12: PHASE 2; GATE 4-6 (NPD) | D12: Phase 2 - Ingredient & Formula Qualification | E12: Confirm formula route, BOM, pH/process targets, costing and technical feasibility. | F12: R&I / Manufacturing / Finance | G12: Formula/BOM/costing, pH/process targets | H12: 05_Formula_BOM_Costing
A13: SG06 | B13: Gate 06 - Packaging & Artwork Requirements | C13: PHASE 2; GATE 4-6 (NPD) | D13: Phase 2 - Ingredient & Formula Qualification | E13: Confirm pack type, components, artwork needs, compatibility needs and supplier approvals. | F13: Packaging / Artwork / Regulatory | G13: Pack components, artwork and compatibility plan | H13: 06_Packaging_Artwork
A14: SG07 | B14: Gate 07 - Maternal & Baby-Contact Safety | C14: PHASE 3; GATE 7-9 (QUALITY) | D14: Phase 3 - Validation & Quality Control | E14: Complete maternal use, pregnancy/breastfeeding, infant-contact exposure and sensitive-user safety screening. | F14: Safety / Scientific Review / Quality | G14: Maternal + baby-contact risk assessment | H14: 07_Maternal_Baby_Safety
A15: SG08 | B15: Gate 08 - Testing, Methods & Validation | C15: PHASE 3; GATE 7-9 (QUALITY) | D15: Phase 3 - Validation & Quality Control | E15: Define testing, participant study requirements, method validation, QC and evidence generation plan. | F15: Quality / R&I / Study owner | G15: Testing plan, participant protocol and methods | H15: 08_Testing_Validation
A16: SG09 | B16: Gate 09 - Stability, Compatibility & Release Readiness | C16: PHASE 3; GATE 7-9 (QUALITY) | D16: Phase 3 - Validation & Quality Control | E16: Confirm stability, preservation, pack compatibility, pilot/scale-up and release readiness. | F16: Quality / R&I / Manufacturing | G16: Stability, PET/micro, compatibility and release criteria | H16: 09_Stability_Release
A17: SG10 | B17: Gate 10 - Regulatory Dossier & Claims Evidence | C17: PHASE 4; GATE 10-12 (REG + MGT) | D17: Phase 4 - Evidence, Release & Improvement | E17: Complete claims evidence, country matching, PIF/CPSR mapping and distributor/HCP evidence pack needs. | F17: Regulatory / Claims / Safety | G17: PIF/CPSR map, claims evidence, HCP summary inputs | H17: 10_Dossier_Claims
A18: SG11 | B18: Gate 11 - Production, Launch & Sales Support Sign-Off | C18: PHASE 4; GATE 10-12 (REG + MGT) | D18: Phase 4 - Evidence, Release & Improvement | E18: Confirm production readiness, Cosmetri/system records, launch sign-off and approved sales support. | F18: Manufacturing / Quality / Sales | G18: Production readiness, launch approvals, sales support | H18: 11_Launch_SignOff
... A20: ALL | B20: Change Control & Communication | C20: PHASE 4; GATE 10-12 (REG + MGT) | D20: Applies across all phases | E20: Controls artwork, formula, label, claim, supplier, process and market changes so changes are not made silently. | F20: Project owner / QA / relevant function | G20: Change ID, approvals, communication record, closure evidence | H20: Change_Control_Comm

Sheet Chris Needs Document
A1: MBc360 Development & Quality System
A2: STEP 1 — NEEDS DEFINITION | [Product / SKU] | [Product type / category]
A3: Prepared for review by: [Project Manager] and [Head of Department] | Status: DRAFT for review — hold all formula work until sign-off
A4: Scope: What this product must do, based on the physiology and emotional needs of the intended user(s) (and, for maternal/infant products, BOTH infant and parent). Dot points only. Every need must be referenced (see Endnotes; provide full https links).
A6: A. USER / INFANT — PHYSICAL / PHYSIOLOGICAL NEEDS
A7: [Enter each physical/physiological need as a dot point — e.g. protect the skin barrier, reduce dryness/TEWL, be gentle/low-irritant, safe for hand-to-mouth exposure. Add a reference tag [n] to each need.]
A8: [Add a need that designs OUT a known formulation risk for this user group — e.g. an ingredient/lipid profile to avoid. Reference it. [n]]
A9: [Add further physical needs as required — one need per row.]
A16: B. USER / INFANT — EMOTIONAL / DEVELOPMENTAL NEEDS
A17: [Enter emotional/developmental needs — e.g. calming/self-regulation, sleep support, bonding/attachment, comforting sensory cues. Reference each. [n]]
A18: [Add further emotional/developmental needs as required — one per row.]
A22: C. PARENT / CAREGIVER / SECONDARY USER — EMOTIONAL NEEDS
... A55: NOTE ON REFERENCES: Gather links via live research. R&I to confirm each source meets the MBc360 'more than one reference' rule before any need is used to support a market claim. Where a lay/secondary source is cited, replace with the primary journal article at claims stage.

Sheet Chris Ingredient Review
A1: MBc360 — CARRIER / EMOLLIENT SYSTEM REVIEW | [Product / SKU]
A2: Question answered: Are the carriers correct, could they be improved, and are they research-backed? (Actives are reviewed separately.)
A4: Carrier / emollient | B4: % in current draft | C4: Role | D4: Assessment for [target user] skin | E4: Research-backed? | F4: Recommendation | G4: Reference
A5: Ingredient name | C5: [Role in the formula — e.g. primary carrier, light emollient, antioxidant] | D5: [Assessment for the target user’s skin — is it appropriate/gentle/suitable?] | E5: [Yes/No — is it research-backed? Summarise the evidence] | F5: [Recommendation — KEEP / IMPROVE / REVIEW-REDUCE / REPLACE, with reason] | G5: https://... [reference link]
A6: Ingredient name | C6: [Role in the formula — e.g. primary carrier, light emollient, antioxidant] | D6: [Assessment for the target user’s skin — is it appropriate/gentle/suitable?] | E6: [Yes/No — is it research-backed? Summarise the evidence] | F6: [Recommendation — KEEP / IMPROVE / REVIEW-REDUCE / REPLACE, with reason] | G6: https://... [reference link]
A7: Ingredient name | C7: [Role in the formula — e.g. primary carrier, light emollient, antioxidant] | D7: [Assessment for the target user’s skin — is it appropriate/gentle/suitable?] | E7: [Yes/No — is it research-backed? Summarise the evidence] | F7: [Recommendation — KEEP / IMPROVE / REVIEW-REDUCE / REPLACE, with reason] | G7: https://... [reference link]
A8: Ingredient name | C8: [Role in the formula — e.g. primary carrier, light emollient, antioxidant] | D8: [Assessment for the target user’s skin — is it appropriate/gentle/suitable?] | E8: [Yes/No — is it research-backed? Summarise the evidence] | F8: [Recommendation — KEEP / IMPROVE / REVIEW-REDUCE / REPLACE, with reason] | G8: https://... [reference link]
A9: Ingredient name | C9: [Role in the formula — e.g. primary carrier, light emollient, antioxidant] | D9: [Assessment for the target user’s skin — is it appropriate/gentle/suitable?] | E9: [Yes/No — is it research-backed? Summarise the evidence] | F9: [Recommendation — KEEP / IMPROVE / REVIEW-REDUCE / REPLACE, with reason] | G9: https://... [reference link]
A10: Ingredient name | C10: [Role in the formula — e.g. primary carrier, light emollient, antioxidant] | D10: [Assessment for the target user’s skin — is it appropriate/gentle/suitable?] | E10: [Yes/No — is it research-backed? Summarise the evidence] | F10: [Recommendation — KEEP / IMPROVE / REVIEW-REDUCE / REPLACE, with reason] | G10: https://... [reference link]
A11: Ingredient name | C11: [Role in the formula — e.g. primary carrier, light emollient, antioxidant] | D11: [Assessment for the target user’s skin — is it appropriate/gentle/suitable?] | E11: [Yes/No — is it research-backed? Summarise the evidence] | F11: [Recommendation — KEEP / IMPROVE / REVIEW-REDUCE / REPLACE, with reason] | G11: https://... [reference link]
A12: Ingredient name | C12: [Role in the formula — e.g. primary carrier, light emollient, antioxidant] | D12: [Assessment for the target user’s skin — is it appropriate/gentle/suitable?] | E12: [Yes/No — is it research-backed? Summarise the evidence] | F12: [Recommendation — KEEP / IMPROVE / REVIEW-REDUCE / REPLACE, with reason] | G12: https://... [reference link]
A13: Ingredient name | C13: [Role in the formula — e.g. primary carrier, light emollient, antioxidant] | D13: [Assessment for the target user’s skin — is it appropriate/gentle/suitable?] | E13: [Yes/No — is it research-backed? Summarise the evidence] | F13: [Recommendation — KEEP / IMPROVE / REVIEW-REDUCE / REPLACE, with reason] | G13: https://... [reference link]
A14: Ingredient name | C14: [Role in the formula — e.g. primary carrier, light emollient, antioxidant] | D14: [Assessment for the target user’s skin — is it appropriate/gentle/suitable?] | E14: [Yes/No — is it research-backed? Summarise the evidence] | F14: [Recommendation — KEEP / IMPROVE / REVIEW-REDUCE / REPLACE, with reason] | G14: https://... [reference link]
A15: Ingredient name | C15: [Role in the formula — e.g. primary carrier, light emollient, antioxidant] | D15: [Assessment for the target user’s skin — is it appropriate/gentle/suitable?] | E15: [Yes/No — is it research-backed? Summarise the evidence] | F15: [Recommendation — KEEP / IMPROVE / REVIEW-REDUCE / REPLACE, with reason] | G15: https://... [reference link]
A16: Ingredient name | C16: [Role in the formula — e.g. primary carrier, light emollient, antioxidant] | D16: [Assessment for the target user’s skin — is it appropriate/gentle/suitable?] | E16: [Yes/No — is it research-backed? Summarise the evidence] | F16: [Recommendation — KEEP / IMPROVE / REVIEW-REDUCE / REPLACE, with reason] | G16: https://... [reference link]
... A18: Ingredient name | C18: [Role in the formula — e.g. primary carrier, light emollient, antioxidant] | D18: [Assessment for the target user’s skin — is it appropriate/gentle/suitable?] | E18: [Yes/No — is it research-backed? Summarise the evidence] | F18: [Recommendation — KEEP / IMPROVE / REVIEW-REDUCE / REPLACE, with reason] | G18: https://... [reference link]
A20: SUMMARY — is the carrier system correct?
A21: [Overall verdict on the carrier/emollient system — e.g. sound / needs fixes. Summarise the backbone logic.]
A22: #1 PRIORITY FIX: [record the single most important carrier change for this user group, with the reason and evidence.]
A23: #2 CONSIDER: [second improvement — e.g. reduce/replace an ingredient, with rationale.]
A24: #3 KEEP & POSSIBLY LIFT: [note any ingredient(s) to retain or increase, with rationale.]
A25: ACTIVES (separate from carriers): [note which actives are retained/excluded and why. Cross-reference the Needs sheet endnotes for evidence.]
A26: NEXT: these carrier changes feed Step 3 (Backbone Technology) and then the final formula + testing plan. No changes are written into the formula file until the Needs sheet is reviewed and signed off.

Sheet NPD Front-End Roadmap
A1: MBc360 Development & Quality System — NPD FRONT-END ROADMAP & GAP CLOSURE
A2: Purpose: close the front-end scientific gaps identified in the 24-Jul-2026 NPD review. Every NEW product MUST complete the mandatory 4-part structure below, in order, before formula lock. Reference: 'Review Mbc360 against Standard NPD'.
A4: A. IF YOU WERE TO PRACTISE MBc360 — WHAT TO DO FIRST (mandatory order, hold formula work until Steps 1–3 are signed off)
A5: # | B5: Do this first | C5: What it must produce (minimum output) | D5: Controlled sheet to use | E5: Owner | F5: Sign-off gate
A6: 1 | B6: Define the NEEDS (physical + emotional) and the scientific basis | C6: Physical/physiological, emotional/developmental, caregiver & practical needs; needs→design implications; research questions; references; open questions. Formula work HELD until reviewed. | D6: Chris Needs Document (brief) → 1. Needs & Scientific Basis | E6: Project Manager / R&I | F6: SG02
A7: 2 | B7: Map COMPETITORS & current existing solutions | C7: Selected competitors with purchase evidence (country/retailer/date/lot), full INCI, claims, patents, disclosed testing, price/use, sensory + analytical comparison, and the Max Biocare design decision from each comparison. Also 'standard of care' / what users do now. | D7: 2. Competitor & Current-Solution Landscape | E7: Marketing / R&I | F7: SG03
A8: 3 | B8: Define the TARGET PRODUCT PROFILE + propose the BACKBONE TECHNOLOGY | C8: One agreed definition of success (min/target/ideal/unacceptable per attribute + measurement method). Technology platform: precise problem, routes considered, why selected, mechanism, critical attributes, evidence maturity, patent landscape, and HOW it is superior to existing products. | D8: 3. Target Product Profile & Tech Platform | E8: R&I / Project Manager | F8: SG03→SG05
A9: 4 | B9: Plan EVIDENCE / TESTING before formula lock, then FINAL FORMULA + testing to support the claim | C9: Prospective evidence plan (endpoint, comparator, method, minimum acceptable result, failure definition) BEFORE formula lock; detailed protocol AFTER prototype; then final formula + tests that substantiate each claim. | D9: 4. Evidence Plan & Claim Support (→ George- Efficacy/Study sheets, Tuan- Formula_BOM) | E9: R&I / Quality | F9: SG05 / SG08
A11: B. MANDATORY 4-PART STRUCTURE FOR EVERY NEW PRODUCT (same structure for all products, all team members)
A12: Part | B12: Mandatory element | C12: Question it answers | D12: New controlled sheet | E12: Status | F12: Notes
A13: 1 | B13: NEEDS — physical & emotional | C13: What needs are we trying to address (body + mind, user + caregiver)? | D13: 1. Needs & Scientific Basis | E13: New | F13: Executive summary stays in 'Chris Needs Document'; full science here.
A14: 2 | B14: COMPETITORS / existing solutions | C14: What already exists, how well does it work, where is the real unmet gap? | D14: 2. Competitor & Current-Solution Landscape | E14: New | F14: Includes purchased-sample & comparative-testing protocol.
A15: 3 | B15: BACKBONE technology / structure (must be superior) | C15: What platform will address the needs, and how is it better than the market? | D15: 3. Target Product Profile & Tech Platform | E15: New | F15: Combines Target Product Profile + Technology Platform.
A16: 4 | B16: FINAL formula + testing to support the claim | C16: Does the finished product deliver, and is every claim substantiated? | D16: 4. Evidence Plan & Claim Support | E16: New | F16: Feeds Tuan- Formula_BOM and George- Efficacy/Study sheets.
A18: C. GAP REGISTER — MISSING FRONT-END / SCIENTIFIC COMPONENTS (from the 24-Jul-2026 review). Retain existing operational controls unchanged.
A19: Priority | B19: Missing component | C19: Current coverage | D19: Action | E19: Sheet / owner | F19: Status
A20: Highest | B20: Human Needs & Scientific Basis Dossier | C20: Partly — Chris Needs Document is a good brief | D20: Add full scientific needs standard (research questions, search method, evidence quality, traceability) | E20: 1. Needs & Scientific Basis | F20: Template created
A21: Highest | B21: Market, Competitor & Current-Solution Landscape | C21: Weak — link + Gate 3 note only | D21: Add controlled competitor methodology + purchased-sample & comparative-testing protocol + standard-of-care analysis | E21: 2. Competitor & Current-Solution Landscape | F21: Template created
A22: Highest | B22: Target Product Profile + Evidence Development Plan | C22: Distributed across phases, not one document | D22: Consolidate one agreed success definition; split prospective plan vs post-prototype protocol | E22: 3. Target Product Profile & Tech Platform / 4. Evidence Plan | F22: Template created
A23: Highest | B23: Technology Platform & Evidence Dossier | C23: Largely missing ('Backbone Technology' mentioned) | D23: Add reusable technology-platform structure (routes, mechanism, critical attributes, patent landscape, SKU transfer) | E23: 3. Target Product Profile & Tech Platform | F23: Template created
A24: Highest | B24: Ingredient & Raw-Material Evidence Monograph | C24: Strong supplier control; weak science/story | D24: Add exact-material identity, provenance, patents, trial history, transferability, approved story | E24: 5. Ingredient Evidence Monograph | F24: Template created
A25: Highest | B25: Evidence hierarchy, transferability & inference rules | C25: Evidence level' field exists but undefined | D25: Add corporate evidence-grading + transferability + inference-boundary instruction | E25: 6. Evidence Hierarchy & Search Rules | F25: Template created
A26: Highest | B26: Corporate literature-search & referencing standard | C26: Largely missing | D26: Add databases, search strings/dates, inclusion/exclusion, DOI/PMID, patent & trial citation rules | E26: 6. Evidence Hierarchy & Search Rules | F26: Template created
A27: Also req. | B27: Portfolio, Range & Routine Architecture | C27: Missing (SKU-level only) | D27: Add portfolio/routine/technology-relationship structure | E27: Roadmap note — build when range work begins | F27: Logged
A28: Also req. | B28: Product Technical & Evidence Dossier structure | C28: Evidence indexed, narrative missing | D28: Define complete written product dossier structure | E28: 4. Evidence Plan & Claim Support (narrative section) | F28: Logged
A29: Also req. | B29: Patent / clinical-trial / provenance registers | C29: Missing | D29: Included as sections in Ingredient Monograph + Tech Platform | E29: 5. Ingredient Evidence Monograph | F29: Template created
A30: Also req. | B30: Scientific storytelling & training standard | C30: Partly (approval only) | D30: Add Need→solution→insight→technology→formula→evidence→claim story architecture | E30: Roadmap note — build with Marketing | F30: Logged

Sheet 1. Needs & Scientific Basis
A1: MBc360 — HUMAN NEEDS & SCIENTIFIC BASIS DOSSIER | [Product / SKU] | [Product type / category]
A2: Companion to 'Chris Needs Document' (executive summary). This dossier holds the FULL scientific needs analysis. Formula work is HELD until Steps 1-3 of the NPD Front-End Roadmap are signed off. Provide full https references.
A4: 1. FRAMED SCIENTIFIC RESEARCH QUESTIONS (what must be answered before design)
A5: Need domain | B5: Need (dot point) | C5: Framed research question (PICO/PECO where relevant) | D5: Population / life stage | E5: Measurement endpoint | F5: Evidence found (summary) | G5: Reference [n]
A6: Physical / physiological | B6: [need] | C6: [In <population>, does <exposure/ingredient> vs <comparator> change <endpoint>?] | D6: [population] | E6: [endpoint & instrument] | F6: [summary + evidence quality] | G6: https://... [1]
A7: Physical / physiological | B7: [need] | C7: [In <population>, does <exposure/ingredient> vs <comparator> change <endpoint>?] | D7: [population] | E7: [endpoint & instrument] | F7: [summary + evidence quality] | G7: https://... [2]
A8: Emotional / developmental | B8: [need] | C8: [In <population>, does <exposure/ingredient> vs <comparator> change <endpoint>?] | D8: [population] | E8: [endpoint & instrument] | F8: [summary + evidence quality] | G8: https://... [3]
A9: Caregiver emotional | B9: [need] | C9: [In <population>, does <exposure/ingredient> vs <comparator> change <endpoint>?] | D9: [population] | E9: [endpoint & instrument] | F9: [summary + evidence quality] | G9: https://... [4]
A10: Practical / functional | B10: [need] | C10: [In <population>, does <exposure/ingredient> vs <comparator> change <endpoint>?] | D10: [population] | E10: [endpoint & instrument] | F10: [summary + evidence quality] | G10: https://... [5]
A11: Disease vs cosmetic boundary | B11: [need] | C11: [In <population>, does <exposure/ingredient> vs <comparator> change <endpoint>?] | D11: [population] | E11: [endpoint & instrument] | F11: [summary + evidence quality] | G11: https://... [6]
A12: Exposure / hand-to-mouth | B12: [need] | C12: [In <population>, does <exposure/ingredient> vs <comparator> change <endpoint>?] | D12: [population] | E12: [endpoint & instrument] | F12: [summary + evidence quality] | G12: https://... [7]
A14: 2. LITERATURE-SEARCH METHOD (record so the search is reproducible)
A15: Database | B15: Search string | C15: Search date | D15: Inclusion criteria | E15: Exclusion criteria | F15: Records screened / included | G15: Notes
A16: PubMed | B16: [string] | C16: [YYYY-MM-DD] | D16: [inclusion] | E16: [exclusion] | F16: [n screened / n incl] | G16: [notes]
A17: Cochrane | B17: [string] | C17: [YYYY-MM-DD] | D17: [inclusion] | E17: [exclusion] | F17: [n screened / n incl] | G17: [notes]
A18: ClinicalTrials.gov | B18: [string] | C18: [YYYY-MM-DD] | D18: [inclusion] | E18: [exclusion] | F18: [n screened / n incl] | G18: [notes]
A19: Patent (Espacenet/Google Patents) | B19: [string] | C19: [YYYY-MM-DD] | D19: [inclusion] | E19: [exclusion] | F19: [n screened / n incl] | G19: [notes]
A20: Supplier / grey literature | B20: [string] | C20: [YYYY-MM-DD] | D20: [inclusion] | E20: [exclusion] | F20: [n screened / n incl] | G20: [notes]
A22: 3. ANATOMY, PHYSIOLOGY, EXPOSURE SCIENCE & CONTRADICTORY / NULL EVIDENCE
A23: Relevant anatomy / physiology: | B23: [e.g. skin barrier / TEWL / infant skin thinness / scalp exposure]
A24: Exposure science: | B24: [dose, frequency, surface area, hand-to-mouth, occlusion]
A25: Population-specific analysis: | B25: [infant vs adult vs pregnant/BF differences]
A26: Contradictory or null evidence found: | B26: [record honestly - what did NOT show benefit]
A27: Disease vs cosmetic boundary: | B27: [where does a cosmetic claim stop and a therapeutic claim begin?]
A28: Evidence gaps & research priorities: | B28: [what is still unknown; what to test first]
A30: 4. NEEDS -> TECHNOLOGY TRACEABILITY MATRIX (carries into Sheet 3: Tech Platform)
A31: Need ID | B31: Need | C31: Design implication | D31: Backbone/technology direction | E31: Critical attribute | F31: Evidence status | G31: Reference [n]
A32: N1 | B32: [need] | C32: [implication] | D32: [technology direction] | E32: [critical attribute + target] | F32: [demonstrated / ingredient-only / gap] | G32: https://... [1]
A33: N2 | B33: [need] | C33: [implication] | D33: [technology direction] | E33: [critical attribute + target] | F33: [demonstrated / ingredient-only / gap] | G33: https://... [2]
A34: N3 | B34: [need] | C34: [implication] | D34: [technology direction] | E34: [critical attribute + target] | F34: [demonstrated / ingredient-only / gap] | G34: https://... [3]
A35: N4 | B35: [need] | C35: [implication] | D35: [technology direction] | E35: [critical attribute + target] | F35: [demonstrated / ingredient-only / gap] | G35: https://... [4]
A36: N5 | B36: [need] | C36: [implication] | D36: [technology direction] | E36: [critical attribute + target] | F36: [demonstrated / ingredient-only / gap] | G36: https://... [5]
A38: 5. GATE SIGN-OFF (formula work may NOT proceed until complete)
A39: Prepared by: | B39: [name] | C39: Reviewed by (Head of Dept): | D39: [name] | E39: Independent reviewer: | F39: [name] | G39: Date: [YYYY-MM-DD]

Sheet 2. Competitor Landscape
A1: MBc360 — MARKET, COMPETITOR & CURRENT-SOLUTION LANDSCAPE DOSSIER | [Product / SKU]
A2: Controlled record of PURCHASED competitor samples + desktop research + standard-of-care analysis. One row per competitor product. Every important competitor must be purchased and physically evaluated, not just researched online.
A4: 1. COMPETITOR PRODUCT REGISTER — PURCHASE & IDENTITY (buy a real sample for every important competitor)
A5: Why selected / market role | B5: Brand & exact product | C5: Country / retailer | D5: Purchase date | E5: Batch / lot / expiry | F5: Price & cost per use | G5: Full label archived? (link) | H5: Dose / frequency
A6: [reason + category role] | B6: [brand — exact SKU] | C6: [country / retailer] | D6: [YYYY-MM-DD] | E6: [batch / lot / expiry] | F6: [price / cost-per-use] | G6: [Y/N — link] | H6: [dose & frequency]
A7: [reason + category role] | B7: [brand — exact SKU] | C7: [country / retailer] | D7: [YYYY-MM-DD] | E7: [batch / lot / expiry] | F7: [price / cost-per-use] | G7: [Y/N — link] | H7: [dose & frequency]
A8: [reason + category role] | B8: [brand — exact SKU] | C8: [country / retailer] | D8: [YYYY-MM-DD] | E8: [batch / lot / expiry] | F8: [price / cost-per-use] | G8: [Y/N — link] | H8: [dose & frequency]
A9: [reason + category role] | B9: [brand — exact SKU] | C9: [country / retailer] | D9: [YYYY-MM-DD] | E9: [batch / lot / expiry] | F9: [price / cost-per-use] | G9: [Y/N — link] | H9: [dose & frequency]
A10: [reason + category role] | B10: [brand — exact SKU] | C10: [country / retailer] | D10: [YYYY-MM-DD] | E10: [batch / lot / expiry] | F10: [price / cost-per-use] | G10: [Y/N — link] | H10: [dose & frequency]
A11: [reason + category role] | B11: [brand — exact SKU] | C11: [country / retailer] | D11: [YYYY-MM-DD] | E11: [batch / lot / expiry] | F11: [price / cost-per-use] | G11: [Y/N — link] | H11: [dose & frequency]
A13: 2. CLAIMS, INCI, IP & DISCLOSED TESTING (per competitor above — keep the same row order)
A14: Exact claims & qualifications | B14: Full INCI | C14: Highlighted actives & % (if disclosed) | D14: Patents / registered tech | E14: Publications / clinical trials | F14: Disclosed testing | G14: Packaging & dosing performance | H14: Strengths / weaknesses / uncertainties
A15: [claims] | B15: [INCI] | C15: [actives + %] | D15: [patent numbers] | E15: [refs / NCT] | F15: [what testing] | G15: [pack performance] | H15: [S/W/uncertainty]
A16: [claims] | B16: [INCI] | C16: [actives + %] | D16: [patent numbers] | E16: [refs / NCT] | F16: [what testing] | G16: [pack performance] | H16: [S/W/uncertainty]
A17: [claims] | B17: [INCI] | C17: [actives + %] | D17: [patent numbers] | E17: [refs / NCT] | F17: [what testing] | G17: [pack performance] | H17: [S/W/uncertainty]
A18: [claims] | B18: [INCI] | C18: [actives + %] | D18: [patent numbers] | E18: [refs / NCT] | F18: [what testing] | G18: [pack performance] | H18: [S/W/uncertainty]
A19: [claims] | B19: [INCI] | C19: [actives + %] | D19: [patent numbers] | E19: [refs / NCT] | F19: [what testing] | G19: [pack performance] | H19: [S/W/uncertainty]
A20: [claims] | B20: [INCI] | C20: [actives + %] | D20: [patent numbers] | E20: [refs / NCT] | F20: [what testing] | G20: [pack performance] | H20: [S/W/uncertainty]
A22: 3. COMPARATIVE TESTING PROTOCOL (blinded where possible — sensory, human-factors, analytical)
A23: Attribute tested | B23: Method / instrument | C23: Our product result | D23: Best competitor result | E23: Comparator winner | F23: Acceptance target | G23: Blinded? (Y/N) | H23: Notes
A24: Sensory (skin feel/absorption) | B24: [method] | C24: [result] | D24: [result] | E24: [us / competitor] | F24: [target] | G24: [Y/N] | H24: [notes]
A25: Fragrance liking | B25: [method] | C25: [result] | D25: [result] | E25: [us / competitor] | F25: [target] | G25: [Y/N] | H25: [notes]
A26: Spreadability / rub-in | B26: [method] | C26: [result] | D26: [result] | E26: [us / competitor] | F26: [target] | G26: [Y/N] | H26: [notes]
A27: Analytical (pH / viscosity) | B27: [method] | C27: [result] | D27: [result] | E27: [us / competitor] | F27: [target] | G27: [Y/N] | H27: [notes]
A28: Performance endpoint | B28: [method] | C28: [result] | D28: [result] | E28: [us / competitor] | F28: [target] | G28: [Y/N] | H28: [notes]
A29: Packaging dose accuracy | B29: [method] | C29: [result] | D29: [result] | E29: [us / competitor] | F29: [target] | G29: [Y/N] | H29: [notes]
A31: 4. CURRENT SOLUTIONS & STANDARD OF CARE (what users do now WITHOUT a specialised product)
A32: Current behaviour / solution | B32: Why users do it | C32: What works adequately | D32: What fails | E32: Medical / professional recommendation | F32: Gap that justifies a new product | G32: Evidence / reference | H32: Design decision
A33: Water-only / basic wash | B33: [why] | C33: [works] | D33: [fails] | E33: [recommendation] | F33: [the real unmet gap] | G33: https://... | H33: [Max Biocare decision]
A34: OTC lotion / cream / oil | B34: [why] | C34: [works] | D34: [fails] | E34: [recommendation] | F34: [the real unmet gap] | G34: https://... | H34: [Max Biocare decision]
A35: Home remedy | B35: [why] | C35: [works] | D35: [fails] | E35: [recommendation] | F35: [the real unmet gap] | G35: https://... | H35: [Max Biocare decision]
A36: Chelating / specialist product | B36: [why] | C36: [works] | D36: [fails] | E36: [recommendation] | F36: [the real unmet gap] | G36: https://... | H36: [Max Biocare decision]
A37: Professional / clinic advice | B37: [why] | C37: [works] | D37: [fails] | E37: [recommendation] | F37: [the real unmet gap] | G37: https://... | H37: [Max Biocare decision]
A38: Do nothing | B38: [why] | C38: [works] | D38: [fails] | E38: [recommendation] | F38: [the real unmet gap] | G38: https://... | H38: [Max Biocare decision]
A40: 5. LANDSCAPE DECISION SUMMARY
A41: Our position vs best competitor: | B41: [where we win / lose / match]
A42: Demonstrated unmet need (not just an internal idea): | B42: [state the evidence-based gap]
A43: Superiority target the backbone technology must beat: | B43: [the specific bar to clear — carries to Sheet 3]

Sheet 3. Target Product & Tech
A1: MBc360 — TARGET PRODUCT PROFILE (TPP) & TECHNOLOGY PLATFORM DOSSIER | [Product / SKU]
A2: ONE agreed definition of what success means, plus the backbone technology that will deliver it. The technology MUST be demonstrably superior in some way to the current market (Sheet 2). Complete before formula lock (Gate 5).
A4: SECTION 1 — TARGET PRODUCT PROFILE (agree BEFORE development; every row measurable)
A5: Attribute / parameter | B5: Minimum (must-have to launch) | C5: Target (the aim) | D5: Ideal (stretch) | E5: Unacceptable (auto-fail) | F5: Measurement method / evidence
A6: Core efficacy endpoint | B6: [e.g. measurable improvement in target parameter] | C6: [target value & timepoint] | D6: [stretch value] | E6: [below this = fail] | F6: [instrument / clinical / in-vitro method + ref]
A7: Onset / time to benefit | B7: [e.g. within X days] | C7: [X days] | D7: [faster] | E7: [no benefit by X] | F7: [study design + endpoint]
A8: Safety / tolerability (incl. infant contact) | B8: [zero unacceptable AEs; maternal + baby-contact safe] | C8: [target tolerability] | D8: [best-in-class] | E8: [any serious AE / prohibited ingredient] | F8: [HRIPT / patch / PB caution check]
A9: Sensory / usability | B9: [minimum acceptable sensory] | C9: [target sensory profile] | D9: [delightful] | E9: [sensory that breaks ritual] | F9: [consumer panel method]
A10: Stability / shelf life | B10: [min months at target conditions] | C10: [target months] | D10: [stretch] | E10: [fails stability spec] | F10: [ICH stability protocol]
A11: Cost / margin | B11: [max COGS to hit margin] | C11: [target COGS] | D11: [lower] | E11: [above margin ceiling] | F11: [Costing_Calc link]
A12: Claim(s) to be supported | B12: [minimum defensible claim] | C12: [target claim set] | D12: [ideal claim] | E12: [claim without evidence] | F12: [Sheet 4 evidence plan link]
A14: SECTION 2 — BACKBONE / PLATFORM TECHNOLOGY (the proposed superior solution)
A15: Question / field | B15: Answer (dot points) | F15: Reference [n] / evidence link
A16: Precise problem being solved | B16: [state the exact physiological/functional problem — from Sheet 1 needs] | F16: [n]
A17: Routes / platforms considered | B17: [list the candidate technologies/carriers/actives evaluated] | F17: [n]
A18: Selected platform & why | B18: [the chosen backbone and the reasoning it won] | F18: [n]
A19: Mechanism of action | B19: [how it works at skin/biological level] | F19: [n]
A20: Why SUPERIOR to current market | B20: [the specific, demonstrable advantage vs competitors in Sheet 2 — faster/gentler/higher potency/novel delivery] | F20: [n]
A21: Critical-to-quality attributes | B21: [the parameters that MUST be controlled for it to work — feeds Potency_Process_Control] | F21: [n]
A22: Evidence maturity | B22: [proven / emerging / theoretical — grade using Sheet 6 hierarchy] | F22: [n]
A23: Patent / IP landscape | B23: [own IP, freedom to operate, competitor patents to design around] | F23: [n]
A24: SKU / portfolio transfer | B24: [which other products this platform can carry into — feeds portfolio architecture] | F24: [n]
A26: SECTION 3 — SIGN-OFF (TPP + platform agreed before formula work begins)
A27: Project Manager: [Chris] ____ Head of Department: [George] ____ R&I: ____ Date: ____ Status: DRAFT — hold formula work until this profile is signed off.

Sheet 4. Evidence & Claim Support
A1: MBc360 — EVIDENCE PLAN & CLAIM SUPPORT MATRIX | [Product / SKU]
A2: Plan the proof BEFORE the formula is locked, then trace every claim to it. Section 1 = prospective plan (define endpoint, comparator, method & pass/fail BEFORE seeing results). Section 3 = permanent claim IDs feeding Tuan-Formula_BOM and George- efficacy sheets.
A4: SECTION 1 — PROSPECTIVE EVIDENCE PLAN (agree BEFORE formula lock — Gate 3/5)
A5: # | B5: Claim / benefit to prove | C5: Endpoint / what is measured | D5: Comparator (vs what) | E5: Method / study type | F5: Minimum acceptable result (pass) | G5: Failure definition
A6: 1 | B6: [intended claim] | C6: [objective endpoint] | D6: [placebo / competitor / baseline] | E6: [in-vitro / clinical / consumer] | F6: [pass threshold + timepoint] | G6: [what counts as fail]
A7: 2 | B7: [intended claim] | C7: [objective endpoint] | D7: [comparator] | E7: [method] | F7: [pass threshold] | G7: [fail definition]
A8: 3 | B8: [intended claim] | C8: [objective endpoint] | D8: [comparator] | E8: [method] | F8: [pass threshold] | G8: [fail definition]
A9: 4 | B9: [add rows as needed]
A11: SECTION 2 — DETAILED TEST PROTOCOL (complete once prototype exists — Gate 8)
A12: # | B12: Test / method | C12: Sample size & rationale | D12: Conditions / timepoints | E12: Acceptance limit | F12: Report / evidence link | G12: Owner
A13: 1 | B13: [method ref] | C13: [n + justification] | D13: [conditions] | E13: [limit] | F13: [George-Test_Report_Index link] | G13: [owner]
A14: 2 | B14: [method ref] | C14: [n] | D14: [conditions] | E14: [limit] | F14: [link] | G14: [owner]
A15: 3 | B15: [add rows as needed]
A17: SECTION 3 — CLAIM → EVIDENCE TRACEABILITY (permanent claim IDs)
A18: Claim ID | B18: Approved claim wording | C18: Mechanism (Sheet 3) | D18: Evidence grade (Sheet 6) | E18: Supporting evidence / report | F18: Status (supported / pending) | G18: Approved by / date
A19: CLM-001 | B19: [exact approved wording] | C19: [platform mechanism] | D19: [grade A/B/C] | E19: [report link / DOI/PMID] | F19: [status] | G19: [approver / date]
A20: CLM-002 | B20: [wording] | C20: [mechanism] | D20: [grade] | E20: [evidence] | F20: [status] | G20: [approver / date]
A21: CLM-003 | B21: [add rows as needed]
A23: SECTION 4 — CONTROL RULE
A24: No claim may appear on artwork, HCP material or sales material unless it has a Claim ID here with status 'supported'. Defining pass/fail BEFORE results prevents outcome-shopping. Cross-check George-Mechanism_Claims and ChiChu-SKU_Claims_PIF.

Sheet 5. Ingredient Monograph
A1: MBc360 — INGREDIENT / ACTIVE EVIDENCE MONOGRAPH | [Material / INCI]
A2: One monograph per key active/functional ingredient. Fixes the exact material used, its provenance/story, patents, external trial history and how far that evidence transfers to OUR product. Complete at Gate 4/5; feeds Sheet 3 (mechanism), Sheet 4 (claims) and Chidkamon-Supplier_RM.
A4: SECTION 1 — EXACT MATERIAL IDENTITY (no ambiguity)
A5: Field | B5: Detail (dot points) | D5: Reference [n] / link
A6: INCI / chemical name | B6: [exact INCI] | D6: [n]
A7: Trade name & supplier | B7: [branded material + manufacturer] | D7: [n]
A8: Grade / spec / concentration used | B8: [grade, actives %, purity, CAS] | D8: [n]
A9: Form / extraction / process | B9: [how it is made — matters for evidence transfer] | D9: [n]
A11: SECTION 2 — PROVENANCE & STORY
A12: Field | B12: Detail (dot points) | D12: Reference [n] / link
A13: Origin / source story | B13: [where it comes from, sustainability, narrative] | D13: [n]
A14: Why chosen for this product | B14: [link to Sheet 1 need + Sheet 3 platform] | D14: [n]
A16: SECTION 3 — IP & EXTERNAL EVIDENCE
A17: Field | B17: Detail (dot points) | D17: Reference [n] / link
A18: Patent / IP status | B18: [own IP, licensed, off-patent, FTO notes] | D18: [n]
A19: External clinical / trial history | B19: [published human/in-vitro studies on THIS material] | D19: [n]
A20: Study conditions (dose, vehicle, population) | B20: [the exact conditions of that evidence] | D20: [n]
A22: SECTION 4 — TRANSFERABILITY TO OUR PRODUCT (critical)
A23: Field | B23: Detail (dot points) | D23: Reference [n] / link
A24: Does evidence transfer? | B24: [same dose/vehicle/population? Y/N + why] | D24: [n]
A25: Inference vs proof | B25: [what is proven here vs only inferred — grade via Sheet 6] | D25: [n]
A26: Gap / test needed in OUR formula | B26: [what must still be tested — feeds Sheet 4] | D26: [n]
A28: SECTION 5 — APPROVED WORDING
A29: Field | B29: Detail (dot points) | D29: Reference [n] / link
A30: Professional / HCP explanation | B30: [approved technical wording] | D30: [n]
A31: Consumer explanation | B31: [approved lay wording] | D31: [n]
A32: Wording to AVOID | B32: [claims not supported / regulatory no-go] | D32: [n]

Sheet 6. Evidence & Search Rules
A1: MBc360 — EVIDENCE HIERARCHY & LITERATURE-SEARCH STANDARD
A2: The corporate rulebook that keeps every claim honest: how evidence is graded, when it transfers vs is only inferred, and how literature is searched and cited. Applies to Sheets 1-5 and all efficacy sheets.
A4: SECTION 1 — EVIDENCE HIERARCHY (how strong is the proof?)
A5: Grade | B5: Evidence type | C5: When it may support a claim | D5: Limitations / conditions
A6: A | B6: Systematic review / meta-analysis, or ≥2 well-controlled human RCTs on the FINISHED product or identical formula | C6: Directly supports a strong efficacy/benefit claim for this product | D6: Must be on the finished formula or a matrix-equivalent formula; register + protocol on file
A7: B | B7: Single well-controlled human study on the product, OR robust human data on the SAME active at the SAME use level/vehicle | C7: Supports a qualified claim (e.g. "shown to…" with method footnote) | D7: Confirm dose, vehicle and exposure match; note sample size and duration
A8: C | B8: Ex-vivo / in-vitro / mechanistic data, or human data on the active in a DIFFERENT vehicle or dose | C8: Supports a mechanism or "designed to" statement only — NOT a finished-product efficacy claim | D8: Flag as inference; cannot stand alone for a consumer efficacy claim
A9: D | B9: Ingredient-supplier data, monographs, reviews, or secondary/lay sources | C9: Background & hypothesis generation only | D9: Replace with primary source before claims stage; never sole support
A10: E | B10: Traditional use / anecdote / marketing collateral | C10: Not usable to support a regulated claim | D10: Record for context only
A11: — | B11: Safety evidence (tox, CPSR, patch/HRIPT) | C11: Required for safety substantiation regardless of efficacy grade | D11: Governed by the Safety / PIF sheets, not this efficacy scale
A13: SECTION 2 — TRANSFERABILITY & INFERENCE RULES (does the evidence actually apply to THIS product?)
A14: Test | B14: Question to answer | C14: PASS = transfers directly | D14: FAIL = inference only (downgrade grade)
A15: Same active | B15: Is it the same molecule/extract (INCI, chemotype, extraction)? | C15: Identical active | D15: Different salt, extract or grade
A16: Same dose | B16: Is the use level >= the level shown effective in the source? | C16: At or above effective level | D16: Below effective level or unknown
A17: Same vehicle | B17: Is the carrier/matrix comparable (leave-on vs rinse-off, emulsion type)? | C17: Comparable vehicle | D17: Different vehicle -> bioavailability differs
A18: Same exposure | B18: Same site, frequency, duration and user group (incl. infant/maternal)? | C18: Matches intended use | D18: Different population or regimen
A19: Same endpoint | B19: Does the source measure the SAME outcome being claimed? | C19: Same measured endpoint | D19: Surrogate or different endpoint
A20: Combination effect | B20: Could other ingredients enhance/inhibit the effect? | C20: No material interaction expected | D20: Interaction plausible -> test on finished formula
A22: RULE: If ANY test fails, the claim is an inference (max Grade C) and must be labelled as mechanism / "designed to" language until confirmed on the finished formula. Per the MBc360 'more than one reference' rule, no single source — and no lay source — may be the sole support for a market claim.
A24: SECTION 3 — LITERATURE-SEARCH & REFERENCING STANDARD (how we find and record the evidence)
A25: Element | B25: Standard / requirement | C25: What to record on the sheet | D25: Owner
A26: Databases | B26: Search recognised sources: PubMed / MEDLINE, Embase, Cochrane, Google Scholar, plus patent (Espacenet, Google Patents) and trial registries (ClinicalTrials.gov, ANZCTR) | C26: List every database searched | D26: R&I
A27: Search strings | B27: Record the exact Boolean strings (active AND endpoint AND population) used per question | C27: Paste full search string(s) | D27: R&I
A28: Search dates | B28: Record the date each search was run and the date range covered | C28: dd-mmm-yyyy run date | D28: R&I
A29: Inclusion / exclusion | B29: Define criteria up front: species, human vs in-vitro, language, study design, dose/vehicle relevance | C29: State criteria + count included/excluded | D29: R&I
A30: Study identifiers | B30: Capture DOI and/or PMID for every journal source; register ID for trials | C30: DOI: 10.xxxx / PMID: xxxxxxx | D30: R&I
A31: Patent citation | B31: Cite as: Applicant, Title, Patent no. (e.g. US1234567B2), grant/priority date | C31: Full patent number + status | D31: R&I / Legal
A32: Full https links | B32: Every reference must carry a full working https link for one-click verification | C32: Paste live URL | D32: R&I
A33: Two-reference rule | B33: Confirm each need/claim meets the MBc360 'more than one reference' rule; replace any lay/secondary source with the primary article at claims stage | C33: Tick when >=2 primary sources on file | D33: R&I -> Regulatory
A35: SECTION 4 — CONTROL & SIGN-OFF
A36: This standard is mandatory for Sheets 1-5 and every efficacy/claim sheet. No need or claim may progress to formula or label without: (a) an assigned evidence Grade (Sec 1), (b) a passed transferability check or an explicit inference flag (Sec 2), and (c) a complete, dated, linked search record (Sec 3).
A38: Prepared by (R&I): __________________ Date: __________
A39: Approved by (Head of Dept / Regulatory): __________________ Date: __________

Sheet Tuan-Formula_BOM
A1: REVIEW OWNER: Tuan (Formulation) | Co-review: Sankar (Quality – Formula BOM & sensory testing) | Co-sign: Chris (Project Manager)
A2: MBc360 Development & Quality System
A3: Formula BOM / Direct Formula Costing
A4: Enter each raw material once. Cost and batch quantity fields are formula-driven from Costing_Calc; attach evidence links for each raw material.
A6: FORMULA BOM
A7: Line | B7: RM Code | C7: Ingredient / INCI | D7: Function | E7: Supplier | F7: % w/w | G7: Batch kg | H7: kg needed | I7: Cost / kg | J7: Cost / batch | K7: Cost / unit | L7: Evidence link | M7: Method ref | N7: Notes
A8: 1 | G8: ='Hannah-Costing_Calc'!$B$8 -> 100 | H8: =IFERROR(IF(OR(F8="",G8=""),"",F8*G8/100),"") | J8: =IFERROR(H8*I8,"") | K8: =IFERROR(J8/'Hannah-Costing_Calc'!$B$10,"")
A9: 2 | G9: ='Hannah-Costing_Calc'!$B$8 -> 100 | H9: =IFERROR(IF(OR(F9="",G9=""),"",F9*G9/100),"") | J9: =IFERROR(H9*I9,"") | K9: =IFERROR(J9/'Hannah-Costing_Calc'!$B$10,"")
A10: 3 | G10: ='Hannah-Costing_Calc'!$B$8 -> 100 | H10: =IFERROR(IF(OR(F10="",G10=""),"",F10*G10/100),"") | J10: =IFERROR(H10*I10,"") | K10: =IFERROR(J10/'Hannah-Costing_Calc'!$B$10,"")
A11: 4 | G11: ='Hannah-Costing_Calc'!$B$8 -> 100 | H11: =IFERROR(IF(OR(F11="",G11=""),"",F11*G11/100),"") | J11: =IFERROR(H11*I11,"") | K11: =IFERROR(J11/'Hannah-Costing_Calc'!$B$10,"")
A12: 5 | G12: ='Hannah-Costing_Calc'!$B$8 -> 100 | H12: =IFERROR(IF(OR(F12="",G12=""),"",F12*G12/100),"") | J12: =IFERROR(H12*I12,"") | K12: =IFERROR(J12/'Hannah-Costing_Calc'!$B$10,"")
A13: 6 | G13: ='Hannah-Costing_Calc'!$B$8 -> 100 | H13: =IFERROR(IF(OR(F13="",G13=""),"",F13*G13/100),"") | J13: =IFERROR(H13*I13,"") | K13: =IFERROR(J13/'Hannah-Costing_Calc'!$B$10,"")
A14: 7 | G14: ='Hannah-Costing_Calc'!$B$8 -> 100 | H14: =IFERROR(IF(OR(F14="",G14=""),"",F14*G14/100),"") | J14: =IFERROR(H14*I14,"") | K14: =IFERROR(J14/'Hannah-Costing_Calc'!$B$10,"")
A15: 8 | G15: ='Hannah-Costing_Calc'!$B$8 -> 100 | H15: =IFERROR(IF(OR(F15="",G15=""),"",F15*G15/100),"") | J15: =IFERROR(H15*I15,"") | K15: =IFERROR(J15/'Hannah-Costing_Calc'!$B$10,"")
A16: 9 | G16: ='Hannah-Costing_Calc'!$B$8 -> 100 | H16: =IFERROR(IF(OR(F16="",G16=""),"",F16*G16/100),"") | J16: =IFERROR(H16*I16,"") | K16: =IFERROR(J16/'Hannah-Costing_Calc'!$B$10,"")
A17: 10 | G17: ='Hannah-Costing_Calc'!$B$8 -> 100 | H17: =IFERROR(IF(OR(F17="",G17=""),"",F17*G17/100),"") | J17: =IFERROR(H17*I17,"") | K17: =IFERROR(J17/'Hannah-Costing_Calc'!$B$10,"")
A18: 11 | G18: ='Hannah-Costing_Calc'!$B$8 -> 100 | H18: =IFERROR(IF(OR(F18="",G18=""),"",F18*G18/100),"") | J18: =IFERROR(H18*I18,"") | K18: =IFERROR(J18/'Hannah-Costing_Calc'!$B$10,"")
A19: 12 | G19: ='Hannah-Costing_Calc'!$B$8 -> 100 | H19: =IFERROR(IF(OR(F19="",G19=""),"",F19*G19/100),"") | J19: =IFERROR(H19*I19,"") | K19: =IFERROR(J19/'Hannah-Costing_Calc'!$B$10,"")
... A107: 100 | G107: ='Hannah-Costing_Calc'!$B$8 -> 100 | H107: =IFERROR(IF(OR(F107="",G107=""),"",F107*G107/100),"") | J107: =IFERROR(H107*I107,"") | K107: =IFERROR(J107/'Hannah-Costing_Calc'!$B$10,"")
A109: Total formula cost / unit | K109: =IFERROR(SUM(K8:K107),0) -> 0

Sheet Tuan-Batch_Formula_Trace
A1: REVIEW OWNER: Tuan (Formulation) | Co-sign: Chris (Project Manager)
A2: MBc360 Development & Quality System
A3: Batch Formula Trace
A4: Link production batch records, formula version and release evidence. Keep GMP records in the controlled GMP system.
A6: BATCH TRACEABILITY
A7: Product/SKU | B7: Formula version | C7: Batch / lot | D7: Manufacturing date | E7: Master Formula_BOM version | F7: Actual batch record link | G7: Deviation / CAPA link | H7: CoA / release link | I7: Stability sample link | J7: PIF / PMF link | K7: Status | L7: Owner | M7: Notes
A8: CONTROL POINTER - see Released Label Control | K8: Not Started | L8: Hannah / Lily / Anki | M8: Every shipment out must also be logged in Lily-Released_Label_Ctrl (Block C) with exact batch details + exact released label artwork version before release.
K9: Not Started
K10: Not Started
K11: Not Started
K12: Not Started
K13: Not Started
K14: Not Started
K15: Not Started
K16: Not Started
K17: Not Started
K18: Not Started
K19: Not Started
K20: Not Started
K21: Not Started

Sheet Tuan-Formulation_Chg_Reg
A1: REVIEW OWNER: Tuan (Formulation) | Co-sign: Chris (Project Manager)
A2: MBc360 Development & Quality System
A3: Formulation Change Register (NP Controlled)
A4: Every formulation change (preservative system, active up/down, any ingredient change) must be recorded here BEFORE implementation. Manufacturing treating a change as a new code does NOT remove the need to control and communicate it. Note: formula changes require ~6 months re-registration for Vietnam (VN) - NP must be involved for commercial implications.
A6: FORMULATION CHANGE LOG
A7: Change ID | B7: Product Family / SKU | C7: Change requested by NPD team | D7: Date change requested by NPD | E7: Approved by NP? (commercial) | F7: NP approval date | G7: Change title | H7: Explanation - exactly what changed | I7: Reasons | J7: Changed by | K7: Action: NPD (Tuan/George/Chris) | L7: Action: Reg - new registration/label? (Chi) | M7: Action: Manufacturing (inform only) | N7: Action: Marketing & Sales (NP decides) | O7: New VN registration required? (~6 months) | P7: Market communication required? | Q7: Communicated to market? (Y/N) | R7: Closed? (Y/N) | S7: Overall status | T7: NP sign-off (name) | U7: Communication acknowledged by (name / date)
S8: =IF(AND($A8="",$G8=""),"",IF(OR($E8="",$E8="Pending NP decision"),"Awaiting NP decision",IF($E8="Rejected","Rejected - no change",IF($E8="On hold","On hold",IF($E8="Approved",IF($T8="","Awaiting NP sign-off",IF($R8="Yes","Closed",IF(AND($P8="Yes",$Q8<>"Yes"),"Approved - market comms pending",IF($O8="Yes","Approved - VN re-registration pending","Approved - open")))),"Awaiting NP decision")))))
S9: =IF(AND($A9="",$G9=""),"",IF(OR($E9="",$E9="Pending NP decision"),"Awaiting NP decision",IF($E9="Rejected","Rejected - no change",IF($E9="On hold","On hold",IF($E9="Approved",IF($T9="","Awaiting NP sign-off",IF($R9="Yes","Closed",IF(AND($P9="Yes",$Q9<>"Yes"),"Approved - market comms pending",IF($O9="Yes","Approved - VN re-registration pending","Approved - open")))),"Awaiting NP decision")))))
S10: =IF(AND($A10="",$G10=""),"",IF(OR($E10="",$E10="Pending NP decision"),"Awaiting NP decision",IF($E10="Rejected","Rejected - no change",IF($E10="On hold","On hold",IF($E10="Approved",IF($T10="","Awaiting NP sign-off",IF($R10="Yes","Closed",IF(AND($P10="Yes",$Q10<>"Yes"),"Approved - market comms pending",IF($O10="Yes","Approved - VN re-registration pending","Approved - open")))),"Awaiting NP decision")))))
S11: =IF(AND($A11="",$G11=""),"",IF(OR($E11="",$E11="Pending NP decision"),"Awaiting NP decision",IF($E11="Rejected","Rejected - no change",IF($E11="On hold","On hold",IF($E11="Approved",IF($T11="","Awaiting NP sign-off",IF($R11="Yes","Closed",IF(AND($P11="Yes",$Q11<>"Yes"),"Approved - market comms pending",IF($O11="Yes","Approved - VN re-registration pending","Approved - open")))),"Awaiting NP decision")))))
S12: =IF(AND($A12="",$G12=""),"",IF(OR($E12="",$E12="Pending NP decision"),"Awaiting NP decision",IF($E12="Rejected","Rejected - no change",IF($E12="On hold","On hold",IF($E12="Approved",IF($T12="","Awaiting NP sign-off",IF($R12="Yes","Closed",IF(AND($P12="Yes",$Q12<>"Yes"),"Approved - market comms pending",IF($O12="Yes","Approved - VN re-registration pending","Approved - open")))),"Awaiting NP decision")))))
S13: =IF(AND($A13="",$G13=""),"",IF(OR($E13="",$E13="Pending NP decision"),"Awaiting NP decision",IF($E13="Rejected","Rejected - no change",IF($E13="On hold","On hold",IF($E13="Approved",IF($T13="","Awaiting NP sign-off",IF($R13="Yes","Closed",IF(AND($P13="Yes",$Q13<>"Yes"),"Approved - market comms pending",IF($O13="Yes","Approved - VN re-registration pending","Approved - open")))),"Awaiting NP decision")))))
S14: =IF(AND($A14="",$G14=""),"",IF(OR($E14="",$E14="Pending NP decision"),"Awaiting NP decision",IF($E14="Rejected","Rejected - no change",IF($E14="On hold","On hold",IF($E14="Approved",IF($T14="","Awaiting NP sign-off",IF($R14="Yes","Closed",IF(AND($P14="Yes",$Q14<>"Yes"),"Approved - market comms pending",IF($O14="Yes","Approved - VN re-registration pending","Approved - open")))),"Awaiting NP decision")))))
S15: =IF(AND($A15="",$G15=""),"",IF(OR($E15="",$E15="Pending NP decision"),"Awaiting NP decision",IF($E15="Rejected","Rejected - no change",IF($E15="On hold","On hold",IF($E15="Approved",IF($T15="","Awaiting NP sign-off",IF($R15="Yes","Closed",IF(AND($P15="Yes",$Q15<>"Yes"),"Approved - market comms pending",IF($O15="Yes","Approved - VN re-registration pending","Approved - open")))),"Awaiting NP decision")))))
S16: =IF(AND($A16="",$G16=""),"",IF(OR($E16="",$E16="Pending NP decision"),"Awaiting NP decision",IF($E16="Rejected","Rejected - no change",IF($E16="On hold","On hold",IF($E16="Approved",IF($T16="","Awaiting NP sign-off",IF($R16="Yes","Closed",IF(AND($P16="Yes",$Q16<>"Yes"),"Approved - market comms pending",IF($O16="Yes","Approved - VN re-registration pending","Approved - open")))),"Awaiting NP decision")))))
S17: =IF(AND($A17="",$G17=""),"",IF(OR($E17="",$E17="Pending NP decision"),"Awaiting NP decision",IF($E17="Rejected","Rejected - no change",IF($E17="On hold","On hold",IF($E17="Approved",IF($T17="","Awaiting NP sign-off",IF($R17="Yes","Closed",IF(AND($P17="Yes",$Q17<>"Yes"),"Approved - market comms pending",IF($O17="Yes","Approved - VN re-registration pending","Approved - open")))),"Awaiting NP decision")))))
S18: =IF(AND($A18="",$G18=""),"",IF(OR($E18="",$E18="Pending NP decision"),"Awaiting NP decision",IF($E18="Rejected","Rejected - no change",IF($E18="On hold","On hold",IF($E18="Approved",IF($T18="","Awaiting NP sign-off",IF($R18="Yes","Closed",IF(AND($P18="Yes",$Q18<>"Yes"),"Approved - market comms pending",IF($O18="Yes","Approved - VN re-registration pending","Approved - open")))),"Awaiting NP decision")))))
S19: =IF(AND($A19="",$G19=""),"",IF(OR($E19="",$E19="Pending NP decision"),"Awaiting NP decision",IF($E19="Rejected","Rejected - no change",IF($E19="On hold","On hold",IF($E19="Approved",IF($T19="","Awaiting NP sign-off",IF($R19="Yes","Closed",IF(AND($P19="Yes",$Q19<>"Yes"),"Approved - market comms pending",IF($O19="Yes","Approved - VN re-registration pending","Approved - open")))),"Awaiting NP decision")))))
... S57: =IF(AND($A57="",$G57=""),"",IF(OR($E57="",$E57="Pending NP decision"),"Awaiting NP decision",IF($E57="Rejected","Rejected - no change",IF($E57="On hold","On hold",IF($E57="Approved",IF($T57="","Awaiting NP sign-off",IF($R57="Yes","Closed",IF(AND($P57="Yes",$Q57<>"Yes"),"Approved - market comms pending",IF($O57="Yes","Approved - VN re-registration pending","Approved - open")))),"Awaiting NP decision")))))
A60: CLOSURE CONTROL SUMMARY (live)
A61: Metric | B61: Value
A62: Total changes logged | B62: =COUNTIF($A$8:$A$57,"?*") -> 0
A63: Awaiting NP decision | B63: =COUNTIF($S$8:$S$57,"Awaiting NP decision") -> 0
A64: Approved but still open | B64: =COUNTIF($S$8:$S$57,"Approved - open") -> 0
A65: Market comms pending | B65: =COUNTIF($S$8:$S$57,"Approved - market comms pending") -> 0
A66: VN re-registration pending | B66: =COUNTIF($S$8:$S$57,"Approved - VN re-registration pending") -> 0
A67: Closed | B67: =COUNTIF($S$8:$S$57,"Closed") -> 0
A68: Rejected | B68: =COUNTIF($S$8:$S$57,"Rejected - no change") -> 0
A69: Awaiting NP sign-off | B69: =COUNTIF($S$8:$S$57,"Awaiting NP sign-off") -> 0

Sheet Tuan-Formula_Chg_Control
A1: REVIEW OWNER: Tuan (Formulation) | Co-sign: Chris (Project Manager)
A2: MBc360 Development & Quality System
A3: Formula Change Control
A4: Use for any formula, ingredient, supplier, pH, process, potency, preservative, fragrance, active-level or manufacturing instruction change.
A6: FORMULA CHANGE TRIGGERS
A7: Formula change trigger | B7: Examples | C7: Potential impact areas | D7: Mandatory actions | E7: Person in charge | F7: Technical sign-off | G7: Reg/QA sign-off | H7: Sales/Marketing output required | I7: Template/form | J7: Evidence required | K7: Closure criteria | L7: Change_Control_Comm ID | M7: Old version | N7: New version | O7: Status
A8: Ingredient added or removed | B8: New active, preservative, fragrance or problematic ingredient removed | C8: Safety, efficacy, claims, label INCI, PIF, stability, cost | D8: Update Formula_BOM; screen safety lists; assess claim and label impact | E8: R&I / Formulation | F8: R&I | G8: Regulatory + Quality | H8: Yes | I8: Formula Change Comparison | J8: Old/new formula, rationale, safety evidence | K8: Updated version controlled | O8: Not Started
A9: Ingredient percentage or active level changed | B9: Active increase/decrease, preservative or humectant balance | C9: Efficacy, irritation, preservation, stability, cost | D9: Re-check claim map, potency controls and evidence need | E9: R&I | F9: R&I / Scientific Review | G9: Quality + Regulatory where impacted | H9: Yes if claim/label/customer-facing | I9: Formula Change Comparison | J9: Batch trial, pH, stability/micro plan | K9: Evidence updated before release | O9: Not Started
A10: pH range or process changed | B10: Heat/cool order, addition temperature, homogenisation, hold time | C10: Potency, microbiology, stability, repeatability | D10: Update process instructions and critical control points | E10: R&I + Manufacturing | F10: R&I + Manufacturing | G10: Quality | H10: If customer-facing | I10: Process Change Control | J10: Process redline, batch record, trial result | K10: Manufacturing instructions updated | O10: Not Started
A11: Supplier/raw material/manufacturer change | B11: New supplier, grade, site or manufacturer | C11: Contaminants, allergens, potency, claims, cost, availability | D11: Re-qualify material and compare specs | E11: Procurement + R&I | F11: R&I | G11: Quality + Regulatory | H11: If story/claim/cost/supply impacted | I11: Supplier/RM Change Form | J11: SDS, CoA, TDS, allergen, spec comparison | K11: Supplier approved and evidence filed | O11: Not Started
A12: Fragrance/allergen/sensory change | B12: Perfume changed/removed, essential oil level, odour/colour/texture | C12: Allergen declaration, PBW caution, consumer perception, complaints | D12: Update allergen and caution checks; update artwork if needed | E12: R&I + Regulatory | F12: R&I | G12: Regulatory + Quality | H12: Yes | I12: Sensory/Fragrance Change Form | J12: IFRA/allergen data, label impact | K12: Sales/Marketing notified | O12: Not Started

Sheet Tuan-Product_Dev_Report
A1: REVIEW OWNER: Tuan (Formulation – Product Development Reporting) | Co-sign: Chris (Project Manager)
A2: MBc360 Development & Quality System
A3: Product Development Report
A4: Records the iterative development of new SKUs: each formula improvement by NPD (Tuan), the team feedback that drove it, competitor benchmarking and the decision trail - the way Supplement/Pharma capture it. Links to Formulation_Change_Register, Product_Feedback_Form and Product_Family_Register.
A6: PRODUCT / PROJECT IDENTIFICATION
A7: Product / SKU | G7: Product Family
A8: Project ID | G8: Formula version (current)
A9: NPD lead (formulator) | G9: Target markets
A10: Project owner | G10: Report date
A11: Competitor benchmarks | C11: e.g. Massata, Kangaroo Mommy | G11: Overall status
A13: DEVELOPMENT ITERATION LOG (each improved formula version and what drove it)
A14: Iteration # | B14: Date | C14: Formula version | D14: What changed (formula / process) | E14: Reason / trigger (feedback source) | F14: Feedback ref (Feedback Form / tester) | G14: Result / observation | H14: Decision | I14: Next action | J14: Owner | K14: Linked Change ID | L14: Status
A47: TEAM FEEDBACK & COMPETITOR BENCHMARK NOTES
A48: Date | B48: Source (name / dept / market) | C48: Feedback / benchmark note | D48: Competitor (if any) | E48: Our position vs competitor | F48: Action taken / planned | G48: Owner | H48: Status

Sheet Sekar-GMP_Links
A1: REVIEW OWNER: Sekar (Quality & GMP) | Co-sign: Chris (Project Manager)
A2: MBc360 Development & Quality System
A3: GMP Manufacturing Links
A4: Controlled GMP records remain in the GMP manufacturing system. MBc360 records links, status and traceability only.
A6: GMP FILE LINKS
A7: Product/SKU | B7: Market | C7: Manufacturing site | D7: GMP system reference | E7: GMP file type | F7: GMP file / document name | G7: GMP owner / system | H7: Link / location | I7: Version / batch / date | J7: Status | K7: Linked MBc360 gate / sheet | L7: Notes / action
A8: [SKU] | B8: [market] | C8: [site] | D8: [GMP system ID] | E8: GMP certificate / site approval | F8: [document name] | G8: GMP manufacturing system | H8: [link] | I8: [version/date] | J8: Not Started | K8: 10/11/PIF | L8: Link only; do not recreate in MBc360
A9: [SKU] | B9: [market] | C9: [site] | D9: [GMP system ID] | E9: Manufacturing BOM | F9: [document name] | G9: GMP manufacturing system | H9: [link] | I9: [version/date] | J9: Not Started | K9: Formula_BOM / 11 | L9: GMP team maintains master file
A10: [SKU] | B10: [market] | C10: [site] | D10: [GMP system ID] | E10: Production schedule | F10: [document name] | G10: GMP manufacturing system | H10: [link] | I10: [version/date] | J10: Not Started | K10: 11 | L10: Link current approved schedule or batch plan
A11: [SKU] | B11: [market] | C11: [site] | D11: [GMP system ID] | E11: Batch manufacturing record | F11: [document name] | G11: GMP manufacturing system | H11: [link] | I11: [batch/date] | J11: Not Started | K11: Batch_Formula_Trace | L11: Required for production/release traceability
A12: [SKU] | B12: [market] | C12: [site] | D12: [GMP system ID] | E12: In-process QC record | F12: [document name] | G12: GMP manufacturing system | H12: [link] | I12: [batch/date] | J12: Not Started | K12: Micro_PET_Evidence / Stability_Release | L12: pH, temperature, hold time, mixing/fill records
A13: [SKU] | B13: [market] | C13: [site] | D13: [GMP system ID] | E13: Finished product CoA / release | F13: [document name] | G13: GMP manufacturing system | H13: [link] | I13: [batch/date] | J13: Not Started | K13: Stability_Release / PIF_Evidence_Export | L13: Attach/link controlled report for PIF
A14: [SKU] | B14: [market] | C14: [site] | D14: [GMP system ID] | E14: Deviation / CAPA | F14: [document name] | G14: GMP/QMS system | H14: [link] | I14: [ID/date] | J14: Not Started | K14: PostMarket_CAPA / Change_Control_Comm | L14: Closure remains in GMP/QMS

Sheet Sekar-Micro_PET_Evidence
A1: REVIEW OWNER: Sekar (Quality & GMP) | Co-sign: Tuan (Formulation – PET), Chris (Project Manager)
A2: MBc360 Development & Quality System
A3: Microbiology & PET Evidence
A4: Capture micro limits, PET/challenge testing and preservation rationale once. Link reports to Test_Report_Index and PIF export.
A6: MICRO / PRESERVATION EVIDENCE
A7: Product/SKU | B7: Formula version | C7: Batch / sample | D7: Test type | E7: Method / lab | F7: Acceptance criteria | G7: Result / score | H7: Conclusion | I7: Report link | J7: Raw data link | K7: Status | L7: Owner | M7: Notes
K8: Not Started
K9: Not Started
K10: Not Started
K11: Not Started
K12: Not Started
K13: Not Started
K14: Not Started
K15: Not Started
K16: Not Started
K17: Not Started
K18: Not Started
K19: Not Started
... K21: Not Started

Sheet Sankar-Stability_Release
A1: REVIEW OWNER: Sekar (Quality & GMP) | Co-sign: Tuan (Formulation – Stability), Chris (Project Manager)
A2: MBc360 Development & Quality System
A3: Stability, Compatibility & Release Evidence
A4: Use for accelerated/real-time stability, package compatibility and final release evidence. Do not duplicate raw reports; link them.
A6: STABILITY / RELEASE LOG
A7: Product/SKU | B7: Formula version | C7: Pack / component | D7: Batch | E7: Condition | F7: Timepoint | G7: Parameter | H7: Acceptance criteria | I7: Result | J7: Report link | K7: Release decision | L7: Status | M7: Owner | N7: Notes
L8: Not Started
L9: Not Started
L10: Not Started
L11: Not Started
L12: Not Started
L13: Not Started
L14: Not Started
L15: Not Started
L16: Not Started
L17: Not Started
L18: Not Started
L19: Not Started
... L27: Not Started

Sheet George-Test_Report_Index
A1: REVIEW OWNER: Sankar (Quality) | Co-sign: Lani (HR/Quality), Chris (Project Manager)
A2: MBc360 Development & Quality System
A3: Test Report Index
A4: Record method, score, acceptance limit, conclusion and final report link once. All other tabs should link back to this index.
A6: CONTROLLED REPORT INDEX
A7: Report ID | B7: Product/SKU | C7: Evidence type | D7: Test / study name | E7: Method / protocol | F7: Endpoint | G7: Acceptance criteria | H7: Result / score | I7: Conclusion | J7: Report link | K7: Raw data link | L7: Status | M7: Owner | N7: Linked gate | O7: PIF attached?
A8: TR-001 | L8: Not Started
A9: TR-002 | L9: Not Started
A10: TR-003 | L10: Not Started
A11: TR-004 | L11: Not Started
A12: TR-005 | L12: Not Started
A13: TR-006 | L13: Not Started
A14: TR-007 | L14: Not Started
A15: TR-008 | L15: Not Started
A16: TR-009 | L16: Not Started
A17: TR-010 | L17: Not Started
A18: TR-011 | L18: Not Started
A19: TR-012 | L19: Not Started
... A27: TR-020 | L27: Not Started

Sheet George-Eye_Safety_Evid
A1: REVIEW OWNER: Sankar (Quality) | Co-sign: Lani (HR/Quality), Chris (Project Manager)
A2: MBc360 Development & Quality System
A3: Eye Safety Evidence
A4: Use where eye-area use, baby-contact use, low-irritation or eye-safe language is relevant.
A6: EYE SAFETY / IRRITATION EVIDENCE
A7: Product/SKU | B7: Formula version | C7: Use scenario | D7: Method / model | E7: Endpoint / score | F7: Safe-zone limit | G7: Result | H7: Conclusion | I7: Report link | J7: Raw data link | K7: Status | L7: Owner | M7: Notes
K8: Not Started
K9: Not Started
K10: Not Started
K11: Not Started
K12: Not Started
K13: Not Started
K14: Not Started
K15: Not Started
K16: Not Started
K17: Not Started
K18: Not Started
K19: Not Started

Sheet George-Product_Evid_Summ
A1: REVIEW OWNER: Sankar (Quality) | Co-sign: Lani (HR/Quality), Chris (Project Manager)
A2: MBc360 Development & Quality System
A3: Product Evidence Summary
A4: One row per evidence workstream. Link out to the controlled evidence source instead of copying reports into multiple tabs.
A6: EVIDENCE STATUS SUMMARY
A7: Evidence area | B7: Required? | C7: Trigger | D7: Primary template | E7: Secondary inputs | F7: Evidence link / folder | G7: Owner | H7: Status | I7: Gate | J7: PIF / PMF section | K7: Notes
A8: Project / SKU identity | B8: Y | C8: Project opened or SKU added | D8: PHASE 1; GATE 1-3 (MARKETING) | E8: Stage_Map / project folder | G8: Project owner | H8: Not Started | I8: 01-03 | J8: Product summary
A9: Formula BOM / costing | B9: Y | C9: Formula route or cost decision | D9: Formula_BOM; Costing_Calc | E9: Packaging_BOM | G9: R&I / Finance | H9: Not Started | I9: 05 | J9: Formula / composition
A10: Raw material supplier evidence | B10: Y | C10: Any raw material used | D10: Supplier_RM_Evidence | E10: Formula_BOM | G10: Procurement / Quality | H10: Not Started | I10: 04/05 | J10: Raw material docs
A11: Full formulation safety | B11: Y | C11: Formula version locked | D11: Formulation_Safety | E11: Prohibited_Ingredients; PB_Caution_Limits; Fragrance_Safety | G11: Safety / Regulatory | H11: Not Started | I11: 07/10 | J11: Safety assessment
A12: Fragrance / allergen safety | B12: Conditional | C12: Fragrance, essential oil or allergen present | D12: Fragrance_Safety | E12: PB_Caution_Limits | G12: R&I / Regulatory | H12: Not Started | I12: 07/10 | J12: Label / IFRA
A13: Packaging specs and artwork | B13: Y | C13: Pack selected or market artwork needed | D13: Packaging_Specs_Artwork | E13: Packaging_BOM; Artwork_Change_Control | G13: Packaging / Regulatory | H13: Not Started | I13: 06/10/11 | J13: Artwork / specs
A14: Micro / PET | B14: Conditional | C14: Aqueous/preserved product or micro spec required | D14: Micro_PET_Evidence | E14: Test_Report_Index | G14: Quality | H14: Not Started | I14: 08 | J14: Micro / PET
A15: Stability / release | B15: Y | C15: Formula/pack ready for testing or launch | D15: Stability_Release | E15: Test_Report_Index; GMP_Links | G15: Quality | H15: Not Started | I15: 09/11 | J15: Stability / release
A16: Eye safety | B16: Conditional | C16: Eye-area, baby-contact or irritation-safe claim | D16: Eye_Safety_Evidence | E16: Formulation_Safety | G16: Safety / Quality | H16: Not Started | I16: 07/08 | J16: Safety / report
A17: Functional efficacy | B17: Conditional | C17: Functional or performance claim | D17: Functional_Efficacy | E17: Mechanism_Claims_Map; Efficacy_Assurance | G17: R&I / Quality | H17: Not Started | I17: 08/10 | J17: Claim support
A18: Clinical / human evidence | B18: Conditional | C18: Human claim or HCP-facing proof required | D18: Clinical_Human_Evidence | E18: Study_Protocol; Efficacy_Study_Plan | G18: Clinical / R&I | H18: Not Started | I18: 08/10 | J18: Human evidence
A19: PIF / dossier | B19: Y | C19: Market launch or external product file | D19: PIF_Checklist_ASEAN | E19: ASEAN_PIF_Map; PIF_Evidence_Export | G19: Regulatory | H19: Not Started | I19: 10/11 | J19: PIF
... A23: Post-market / CAPA | B23: Y | C23: After launch or complaint/adverse event | D23: PostMarket_CAPA | E23: GMP_Links; PIF_Evidence_Closure | G23: Quality / PV-PMS | H23: Not Started | I23: 12 | J23: Post-market

Sheet George-Formulation_Safety
A1: REVIEW OWNER: Tuan (Formulation) | Co-sign: Chris (Project Manager)
A2: MBc360 Development & Quality System
A3: Full Formulation Safety Evidence
A4: This is the product-level safety control sheet. It pulls ingredient identity from Formula_BOM and records links to every safety proof needed for review, PIF and external answers.
A6: PRODUCT SAFETY PROFILE
A7: Field | B7: Value | C7: Evidence link | D7: Owner | E7: Status | F7: Notes
A8: Product/SKU | D8: Project owner | E8: Not Started
A9: Formula version | D9: R&I | E9: Not Started | F9: Must match Formula_BOM.
A10: Target user / restriction | B10: Pregnancy / breastfeeding / baby-contact as applicable | D10: Marketing + Safety | E10: Not Started
A11: Use area and leave-on/rinse-off | D11: R&I / Regulatory | E11: Not Started
A13: INGREDIENT-LEVEL SAFETY MATRIX
A14: Line | B14: Ingredient / INCI | C14: % w/w | D14: Function | E14: Supplier | F14: Prohibited match | G14: PB caution match | H14: Exposure / MoS rationale | I14: Irritation / sensitisation | J14: Allergen / IFRA | K14: Impurity / heavy metal proof | L14: Evidence link | M14: Safety decision | N14: Notes
A15: =IF('Tuan-Formula_BOM'!$C8="","",'Tuan-Formula_BOM'!$A8) | B15: =IF('Tuan-Formula_BOM'!$C8="","",'Tuan-Formula_BOM'!$C8) | C15: =IF('Tuan-Formula_BOM'!$C8="","",'Tuan-Formula_BOM'!$F8) | D15: =IF('Tuan-Formula_BOM'!$C8="","",'Tuan-Formula_BOM'!$D8) | E15: =IF('Tuan-Formula_BOM'!$C8="","",'Tuan-Formula_BOM'!$E8) | F15: =IF(B15="","",COUNTIF('ChiChu-Prohibited_Ingred'!$A:$A,"*"&B15&"*")) | G15: =IF(B15="","",COUNTIF('ChiChu-PB_Caution_Limits'!$A:$A,"*"&B15&"*")) | M15: =IF(B15="","",IF(OR(F15>0,G15>0),"Needs Review","No listed match"))
A16: =IF('Tuan-Formula_BOM'!$C9="","",'Tuan-Formula_BOM'!$A9) | B16: =IF('Tuan-Formula_BOM'!$C9="","",'Tuan-Formula_BOM'!$C9) | C16: =IF('Tuan-Formula_BOM'!$C9="","",'Tuan-Formula_BOM'!$F9) | D16: =IF('Tuan-Formula_BOM'!$C9="","",'Tuan-Formula_BOM'!$D9) | E16: =IF('Tuan-Formula_BOM'!$C9="","",'Tuan-Formula_BOM'!$E9) | F16: =IF(B16="","",COUNTIF('ChiChu-Prohibited_Ingred'!$A:$A,"*"&B16&"*")) | G16: =IF(B16="","",COUNTIF('ChiChu-PB_Caution_Limits'!$A:$A,"*"&B16&"*")) | M16: =IF(B16="","",IF(OR(F16>0,G16>0),"Needs Review","No listed match"))
A17: =IF('Tuan-Formula_BOM'!$C10="","",'Tuan-Formula_BOM'!$A10) | B17: =IF('Tuan-Formula_BOM'!$C10="","",'Tuan-Formula_BOM'!$C10) | C17: =IF('Tuan-Formula_BOM'!$C10="","",'Tuan-Formula_BOM'!$F10) | D17: =IF('Tuan-Formula_BOM'!$C10="","",'Tuan-Formula_BOM'!$D10) | E17: =IF('Tuan-Formula_BOM'!$C10="","",'Tuan-Formula_BOM'!$E10) | F17: =IF(B17="","",COUNTIF('ChiChu-Prohibited_Ingred'!$A:$A,"*"&B17&"*")) | G17: =IF(B17="","",COUNTIF('ChiChu-PB_Caution_Limits'!$A:$A,"*"&B17&"*")) | M17: =IF(B17="","",IF(OR(F17>0,G17>0),"Needs Review","No listed match"))
A18: =IF('Tuan-Formula_BOM'!$C11="","",'Tuan-Formula_BOM'!$A11) | B18: =IF('Tuan-Formula_BOM'!$C11="","",'Tuan-Formula_BOM'!$C11) | C18: =IF('Tuan-Formula_BOM'!$C11="","",'Tuan-Formula_BOM'!$F11) | D18: =IF('Tuan-Formula_BOM'!$C11="","",'Tuan-Formula_BOM'!$D11) | E18: =IF('Tuan-Formula_BOM'!$C11="","",'Tuan-Formula_BOM'!$E11) | F18: =IF(B18="","",COUNTIF('ChiChu-Prohibited_Ingred'!$A:$A,"*"&B18&"*")) | G18: =IF(B18="","",COUNTIF('ChiChu-PB_Caution_Limits'!$A:$A,"*"&B18&"*")) | M18: =IF(B18="","",IF(OR(F18>0,G18>0),"Needs Review","No listed match"))
A19: =IF('Tuan-Formula_BOM'!$C12="","",'Tuan-Formula_BOM'!$A12) | B19: =IF('Tuan-Formula_BOM'!$C12="","",'Tuan-Formula_BOM'!$C12) | C19: =IF('Tuan-Formula_BOM'!$C12="","",'Tuan-Formula_BOM'!$F12) | D19: =IF('Tuan-Formula_BOM'!$C12="","",'Tuan-Formula_BOM'!$D12) | E19: =IF('Tuan-Formula_BOM'!$C12="","",'Tuan-Formula_BOM'!$E12) | F19: =IF(B19="","",COUNTIF('ChiChu-Prohibited_Ingred'!$A:$A,"*"&B19&"*")) | G19: =IF(B19="","",COUNTIF('ChiChu-PB_Caution_Limits'!$A:$A,"*"&B19&"*")) | M19: =IF(B19="","",IF(OR(F19>0,G19>0),"Needs Review","No listed match"))
A20: =IF('Tuan-Formula_BOM'!$C13="","",'Tuan-Formula_BOM'!$A13) | B20: =IF('Tuan-Formula_BOM'!$C13="","",'Tuan-Formula_BOM'!$C13) | C20: =IF('Tuan-Formula_BOM'!$C13="","",'Tuan-Formula_BOM'!$F13) | D20: =IF('Tuan-Formula_BOM'!$C13="","",'Tuan-Formula_BOM'!$D13) | E20: =IF('Tuan-Formula_BOM'!$C13="","",'Tuan-Formula_BOM'!$E13) | F20: =IF(B20="","",COUNTIF('ChiChu-Prohibited_Ingred'!$A:$A,"*"&B20&"*")) | G20: =IF(B20="","",COUNTIF('ChiChu-PB_Caution_Limits'!$A:$A,"*"&B20&"*")) | M20: =IF(B20="","",IF(OR(F20>0,G20>0),"Needs Review","No listed match"))
A21: =IF('Tuan-Formula_BOM'!$C14="","",'Tuan-Formula_BOM'!$A14) | B21: =IF('Tuan-Formula_BOM'!$C14="","",'Tuan-Formula_BOM'!$C14) | C21: =IF('Tuan-Formula_BOM'!$C14="","",'Tuan-Formula_BOM'!$F14) | D21: =IF('Tuan-Formula_BOM'!$C14="","",'Tuan-Formula_BOM'!$D14) | E21: =IF('Tuan-Formula_BOM'!$C14="","",'Tuan-Formula_BOM'!$E14) | F21: =IF(B21="","",COUNTIF('ChiChu-Prohibited_Ingred'!$A:$A,"*"&B21&"*")) | G21: =IF(B21="","",COUNTIF('ChiChu-PB_Caution_Limits'!$A:$A,"*"&B21&"*")) | M21: =IF(B21="","",IF(OR(F21>0,G21>0),"Needs Review","No listed match"))
A22: =IF('Tuan-Formula_BOM'!$C15="","",'Tuan-Formula_BOM'!$A15) | B22: =IF('Tuan-Formula_BOM'!$C15="","",'Tuan-Formula_BOM'!$C15) | C22: =IF('Tuan-Formula_BOM'!$C15="","",'Tuan-Formula_BOM'!$F15) | D22: =IF('Tuan-Formula_BOM'!$C15="","",'Tuan-Formula_BOM'!$D15) | E22: =IF('Tuan-Formula_BOM'!$C15="","",'Tuan-Formula_BOM'!$E15) | F22: =IF(B22="","",COUNTIF('ChiChu-Prohibited_Ingred'!$A:$A,"*"&B22&"*")) | G22: =IF(B22="","",COUNTIF('ChiChu-PB_Caution_Limits'!$A:$A,"*"&B22&"*")) | M22: =IF(B22="","",IF(OR(F22>0,G22>0),"Needs Review","No listed match"))
A23: =IF('Tuan-Formula_BOM'!$C16="","",'Tuan-Formula_BOM'!$A16) | B23: =IF('Tuan-Formula_BOM'!$C16="","",'Tuan-Formula_BOM'!$C16) | C23: =IF('Tuan-Formula_BOM'!$C16="","",'Tuan-Formula_BOM'!$F16) | D23: =IF('Tuan-Formula_BOM'!$C16="","",'Tuan-Formula_BOM'!$D16) | E23: =IF('Tuan-Formula_BOM'!$C16="","",'Tuan-Formula_BOM'!$E16) | F23: =IF(B23="","",COUNTIF('ChiChu-Prohibited_Ingred'!$A:$A,"*"&B23&"*")) | G23: =IF(B23="","",COUNTIF('ChiChu-PB_Caution_Limits'!$A:$A,"*"&B23&"*")) | M23: =IF(B23="","",IF(OR(F23>0,G23>0),"Needs Review","No listed match"))
A24: =IF('Tuan-Formula_BOM'!$C17="","",'Tuan-Formula_BOM'!$A17) | B24: =IF('Tuan-Formula_BOM'!$C17="","",'Tuan-Formula_BOM'!$C17) | C24: =IF('Tuan-Formula_BOM'!$C17="","",'Tuan-Formula_BOM'!$F17) | D24: =IF('Tuan-Formula_BOM'!$C17="","",'Tuan-Formula_BOM'!$D17) | E24: =IF('Tuan-Formula_BOM'!$C17="","",'Tuan-Formula_BOM'!$E17) | F24: =IF(B24="","",COUNTIF('ChiChu-Prohibited_Ingred'!$A:$A,"*"&B24&"*")) | G24: =IF(B24="","",COUNTIF('ChiChu-PB_Caution_Limits'!$A:$A,"*"&B24&"*")) | M24: =IF(B24="","",IF(OR(F24>0,G24>0),"Needs Review","No listed match"))
A25: =IF('Tuan-Formula_BOM'!$C18="","",'Tuan-Formula_BOM'!$A18) | B25: =IF('Tuan-Formula_BOM'!$C18="","",'Tuan-Formula_BOM'!$C18) | C25: =IF('Tuan-Formula_BOM'!$C18="","",'Tuan-Formula_BOM'!$F18) | D25: =IF('Tuan-Formula_BOM'!$C18="","",'Tuan-Formula_BOM'!$D18) | E25: =IF('Tuan-Formula_BOM'!$C18="","",'Tuan-Formula_BOM'!$E18) | F25: =IF(B25="","",COUNTIF('ChiChu-Prohibited_Ingred'!$A:$A,"*"&B25&"*")) | G25: =IF(B25="","",COUNTIF('ChiChu-PB_Caution_Limits'!$A:$A,"*"&B25&"*")) | M25: =IF(B25="","",IF(OR(F25>0,G25>0),"Needs Review","No listed match"))
A26: =IF('Tuan-Formula_BOM'!$C19="","",'Tuan-Formula_BOM'!$A19) | B26: =IF('Tuan-Formula_BOM'!$C19="","",'Tuan-Formula_BOM'!$C19) | C26: =IF('Tuan-Formula_BOM'!$C19="","",'Tuan-Formula_BOM'!$F19) | D26: =IF('Tuan-Formula_BOM'!$C19="","",'Tuan-Formula_BOM'!$D19) | E26: =IF('Tuan-Formula_BOM'!$C19="","",'Tuan-Formula_BOM'!$E19) | F26: =IF(B26="","",COUNTIF('ChiChu-Prohibited_Ingred'!$A:$A,"*"&B26&"*")) | G26: =IF(B26="","",COUNTIF('ChiChu-PB_Caution_Limits'!$A:$A,"*"&B26&"*")) | M26: =IF(B26="","",IF(OR(F26>0,G26>0),"Needs Review","No listed match"))
... A64: =IF('Tuan-Formula_BOM'!$C57="","",'Tuan-Formula_BOM'!$A57) | B64: =IF('Tuan-Formula_BOM'!$C57="","",'Tuan-Formula_BOM'!$C57) | C64: =IF('Tuan-Formula_BOM'!$C57="","",'Tuan-Formula_BOM'!$F57) | D64: =IF('Tuan-Formula_BOM'!$C57="","",'Tuan-Formula_BOM'!$D57) | E64: =IF('Tuan-Formula_BOM'!$C57="","",'Tuan-Formula_BOM'!$E57) | F64: =IF(B64="","",COUNTIF('ChiChu-Prohibited_Ingred'!$A:$A,"*"&B64&"*")) | G64: =IF(B64="","",COUNTIF('ChiChu-PB_Caution_Limits'!$A:$A,"*"&B64&"*")) | M64: =IF(B64="","",IF(OR(F64>0,G64>0),"Needs Review","No listed match"))
A66: FINAL SAFETY SIGN-OFF
A67: Safety question / gate | B67: Acceptance requirement | C67: Required evidence | D67: Evidence link | E67: Status | F67: Owner | G67: Decision date | H67: Notes
A68: Formula identity locked | B68: Current formula version and Formula_BOM match | C68: Formula_BOM / batch formula / version record | E68: Not Started | F68: R&I
A69: Toxicology / safety assessment | B69: Safety assessment or CPSR-style rationale covers all ingredients and finished use | C69: Safety assessment link | E69: Not Started | F69: Safety / Regulatory
A70: Pregnancy / breastfeeding assessment | B70: PB caution table reviewed and risks addressed | C70: PB_Caution_Limits + rationale link | E70: Not Started | F70: Safety
A71: Baby-contact / nipple-use assessment | B71: Use area, transfer risk and warnings assessed where applicable | C71: Use scenario / safety rationale | E71: Not Started | F71: Safety / Regulatory
A72: Preservation / microbiology | B72: Micro/PET evidence supports formula and pack | C72: Micro_PET_Evidence / report link | E72: Not Started | F72: Quality
A73: Impurities / heavy metals | B73: Supplier CoA or finished test confirms limits | C73: Supplier_RM_Evidence / report link | E73: Not Started | F73: Quality
A74: Fragrance / allergen | B74: IFRA, allergen and PB caution review complete | C74: Fragrance_Safety link | E74: Not Started | F74: Regulatory / R&I
A75: Stability / compatibility | B75: Formula remains safe and in specification across shelf life | C75: Stability_Release link | E75: Not Started | F75: Quality
A76: Label warnings / directions | B76: Safety restrictions transferred to artwork/public wording | C76: Packaging_Specs_Artwork / Published_Info_Approval | E76: Not Started | F76: Regulatory
A77: Final safety release | B77: All safety gaps closed or formally risk-accepted | C77: Final sign-off link | E77: Not Started | F77: Accountable approver

Sheet George-Mechanism_Claims
A1: REVIEW OWNER: George (R&I) | Co-sign: Chris (Project Manager)
A2: MBc360 Development & Quality System
A3: Mechanism & Claims Evidence Map
A4: Map each claim to the underlying problem, mechanism, ingredients, evidence level and approved wording before external use.
A6: CLAIM MECHANISM MAP
A7: Claim / benefit | B7: User problem | C7: Mechanism of action | D7: Key ingredient / technology | E7: Formula/process control | F7: Evidence level | G7: Evidence link | H7: Approved wording / limitation | I7: Status | J7: Notes
I8: Not Started
I9: Not Started
I10: Not Started
I11: Not Started
I12: Not Started
I13: Not Started
I14: Not Started
I15: Not Started
I16: Not Started
I17: Not Started
I18: Not Started
I19: Not Started

Sheet George-Twinkle5_Claims
A1: REVIEW OWNER: George (R&I) | Co-sign: Chris (Project Manager)
A2: MBc360 Development & Quality System
A3: Twinkle 5 Claims Map
A4: Connect skin-quality principles to evidence and claim controls. Use only where Twinkle 5 language is relevant.
A6: TWINKLE 5 EVIDENCE MAP
A7: Principle | B7: Plain-English benefit | C7: Allowed wording | D7: Evidence type | E7: Evidence link | F7: Limitations / do-not-say | G7: Status | H7: Notes
A8: Barrier | B8: Skin barrier support / comfort | G8: Not Started
A9: Hydration | B9: Water retention / moisturisation | G9: Not Started
A10: Texture | B10: Smoothness / softness / sensory | G10: Not Started
A11: Tone / appearance | B11: Even-looking skin / glow | G11: Not Started
A12: Protection | B12: Support against environmental stressors | G12: Not Started

Sheet George-Efficacy_Assur
A1: REVIEW OWNER: George (R&I) | Co-sign: Chris (Project Manager)
A2: MBc360 Development & Quality System
A3: Efficacy Assurance Control
A4: Use this first to check that efficacy is controlled as clearly as safety. Do not duplicate reports; link to the source sheet.
A6: EFFICACY CONTROL CHECKPOINTS
A7: Control route | B7: Minimum requirement | C7: Primary evidence source | D7: Evidence link | E7: Owner | F7: Status | G7: Notes
A8: Formula efficacy route | B8: Formula contains mechanism-relevant ingredients at justified levels | C8: Formula_BOM; Mechanism_Claims_Map | E8: R&I | F8: Not Started
A9: Ingredient evidence route | B9: Ingredient evidence is relevant to dose, format and use area | C9: Supplier_RM_Evidence; literature/evidence link | E9: R&I / Claims | F9: Not Started
A10: Process/potency route | B10: Active markers and process conditions protect efficacy | C10: Potency_Process_Control | E10: R&I / Manufacturing | F10: Not Started
A11: Functional testing route | B11: In-vitro/in-use assay proves the functional outcome | C11: Functional_Efficacy; Test_Report_Index | E11: Quality / R&I | F11: Not Started
A12: Human evidence route | B12: Human or consumer evidence supports user-facing claim | C12: Clinical_Human_Evidence; Study_Protocol | E12: Clinical / R&I | F12: Not Started
A13: Approved wording route | B13: Claim wording matches evidence strength and limitations | C13: Published_Info_Approval; SKU_Claims_PIF_Register | E13: Regulatory / Claims | F13: Not Started

Sheet George-Functional_Effic
A1: REVIEW OWNER: George (R&I) | Co-sign: Chris (Project Manager)
A2: MBc360 Development & Quality System
A3: Functional Efficacy Evidence
A4: Record controlled functional assay evidence such as chlorine reduction, copper/mineral residue, moisturisation, barrier or other product-specific endpoints.
A6: FUNCTIONAL EFFICACY TESTS
A7: Product/SKU | B7: Claim / endpoint | C7: Method | D7: Comparator / control | E7: Acceptance criteria | F7: Result | G7: Conclusion | H7: Report link | I7: Raw data link | J7: Approved wording | K7: Status | L7: Owner | M7: Notes
K8: Not Started
K9: Not Started
K10: Not Started
K11: Not Started
K12: Not Started
K13: Not Started
K14: Not Started
K15: Not Started
K16: Not Started
K17: Not Started
K18: Not Started
K19: Not Started
... K21: Not Started

Sheet George-Clinical_Human_Ev
A1: REVIEW OWNER: George (R&I) | Co-sign: Chris (Project Manager)
A2: MBc360 Development & Quality System
A3: Clinical / Human Evidence
A4: Use for human, consumer, HCP or in-use evidence. Participant details live in Study_Protocol.
A6: HUMAN EVIDENCE LOG
A7: Evidence ID | B7: Product/SKU | C7: Study / protocol | D7: Claim supported | E7: Design | F7: Population | G7: Endpoint | H7: Result | I7: Acceptance / benchmark | J7: Safety findings | K7: Report link | L7: Status | M7: Owner | N7: Notes
L8: Not Started
L9: Not Started
L10: Not Started
L11: Not Started
L12: Not Started
L13: Not Started
L14: Not Started
L15: Not Started
L16: Not Started
L17: Not Started
L18: Not Started
L19: Not Started

Sheet George-Study_Protocol
A1: REVIEW OWNER: George (R&I) | Co-sign: Chris (Project Manager)
A2: MBc360 Development & Quality System
A3: Study Protocol & Participant Rationale
A4: Study participants are folded into this sheet to avoid a separate overlapping participant tab.
A6: PROTOCOL SETUP
A7: Protocol item | B7: Planned value / requirement | C7: Evidence link | D7: Owner | E7: Status | F7: Notes
A8: Study objective | D8: R&I / Clinical | E8: Not Started
A9: Claim / question | C9: Mechanism_Claims_Map | D9: Claims owner | E9: Not Started
A10: Study design | C10: Protocol link | D10: Clinical / R&I | E10: Not Started
A11: Sample size rationale | C11: Rationale link | D11: Clinical | E11: Not Started
A12: Inclusion / exclusion | C12: Criteria link | D12: Clinical | E12: Not Started
A13: Endpoint / measurement | C13: Method link | D13: R&I / Quality | E13: Not Started
A14: Safety / AE monitoring | C14: AE plan link | D14: Clinical / Quality | E14: Not Started
A15: Data handling / report | C15: Report link | D15: Clinical | E15: Not Started
A17: PARTICIPANT / SAMPLE LOG
A18: Participant / sample ID | B18: Demographic group | C18: Consent / ethics link | D18: Inclusion status | E18: Baseline details | F18: Visit / timepoint | G18: Status | H18: AE / issue | I18: Notes
A19: P-001 | G19: Not Started
A20: P-002 | G20: Not Started
A21: P-003 | G21: Not Started
A22: P-004 | G22: Not Started
A23: P-005 | G23: Not Started
A24: P-006 | G24: Not Started
A25: P-007 | G25: Not Started
A26: P-008 | G26: Not Started
A27: P-009 | G27: Not Started
A28: P-010 | G28: Not Started
A29: P-011 | G29: Not Started
A30: P-012 | G30: Not Started
... A38: P-020 | G38: Not Started

Sheet George-Efficacy_Std_Plan
A1: REVIEW OWNER: George (R&I) | Co-sign: Chris (Project Manager)
A2: MBc360 Development & Quality System
A3: Efficacy Study Plan
A4: Use when claims need proof beyond ingredient rationale. Link final protocols and reports rather than duplicating them.
A6: EFFICACY STUDY PLANNING
A7: Claim / endpoint | B7: Study type | C7: Method / instrument | D7: Comparator / control | E7: Sample / participant plan | F7: Acceptance criteria | G7: Timeline | H7: Protocol link | I7: Report link | J7: Status | K7: Notes
J8: Not Started
J9: Not Started
J10: Not Started
J11: Not Started
J12: Not Started
J13: Not Started
J14: Not Started
J15: Not Started
J16: Not Started
J17: Not Started
J18: Not Started
J19: Not Started

Sheet George-Potency_Proc_Ctrl
A1: REVIEW OWNER: George (R&I) | Co-sign: Chris (Project Manager)
A2: MBc360 Development & Quality System
A3: Potency & Process Control Evidence
A4: Control supply quality, active markers, heat/light/oxygen/pH/process risks and GMP evidence.
A6: POTENCY / PROCESS CONTROLS
A7: Ingredient / active | B7: Marker or critical attribute | C7: Risk factor | D7: Target / spec | E7: Process control | F7: Test / method | G7: Supplier/GMP evidence | H7: Batch evidence link | I7: Impact on claim | J7: Status | K7: Notes
J8: Not Started
J9: Not Started
J10: Not Started
J11: Not Started
J12: Not Started
J13: Not Started
J14: Not Started
J15: Not Started
J16: Not Started
J17: Not Started
J18: Not Started
J19: Not Started

Sheet George-Medical_Summary
A1: REVIEW OWNER: George (R&I) | Co-sign: Chris (Project Manager)
A2: MBc360 Development & Quality System
A3: Medical / Safety Summary
A4: Ready-to-answer HCP/distributor evidence pack. Use approved wording and links, not draft data.
A6: SAFETY / MEDICAL SUMMARY
A7: Summary item | B7: Approved summary | C7: Evidence source | D7: Evidence link | E7: Owner | F7: Status | G7: Notes
A8: Product identity and use | C8: Stage_Map / Formula_BOM | E8: Project owner | F8: Not Started
A9: Formulation safety conclusion | C9: Formulation_Safety | E9: Safety | F9: Not Started
A10: Pregnancy / breastfeeding position | C10: PB_Caution_Limits | E10: Safety / Regulatory | F10: Not Started
A11: Fragrance/allergen position | C11: Fragrance_Safety | E11: Regulatory | F11: Not Started
A12: Micro/stability/release position | C12: Micro_PET_Evidence; Stability_Release | E12: Quality | F12: Not Started
A13: Adverse event / post-market pathway | C13: PostMarket_CAPA | E13: Quality / PV-PMS | F13: Not Started
A15: READY-TO-ANSWER PACK
A16: Audience question | B16: Approved answer | C16: Source evidence | D16: Approved wording link | E16: Status | F16: Owner | G16: Notes
E17: Not Started
E18: Not Started
E19: Not Started
E20: Not Started
E21: Not Started
E22: Not Started
E23: Not Started
E24: Not Started

Sheet ChiChu-Prohibited_Ingred
A1: REVIEW OWNER: Chi Chu (Regulatory) | Co-sign: George (R&I), Chris (Project Manager)
A2: MBc360 Development & Quality System
A3: Prohibited Ingredient Watch-list
A4: Product-specific absence proof. Regulatory must confirm current market status before external use.
A6: MASTER WATCH-LIST
A7: Ingredient / group | B7: Function | C7: Status / level | D7: Why it matters for maternal skincare | E7: Applicable products | F7: Reference / source | G7: Formula match count | H7: Product status | I7: Evidence link | J7: Owner | K7: Linked gate | L7: Notes
A8: Parabens | B8: Preservatives | C8: Restricted; example levels include 0.4% individually / 0.14% combined | D8: Endocrine and reproductive-health concerns for longer-chain parabens | E8: All cosmetics | F8: Safety validation table / current market reference | G8: =COUNTIF('Tuan-Formula_BOM'!$B:$B,"*"&A8&"*")+COUNTIF('Tuan-Formula_BOM'!$C:$C,"*"&A8&"*") -> 0 | H8: =IF(G8>0,"REVIEW - possible formula match","No formula match recorded") -> No formula match recorded | J8: Regulatory | K8: 04_Ingredient_Screening | L8: Confirm current market limits before release.
A9: Phthalates | B9: Plasticizers / solvents / fragrance stabilizers | C9: Restricted/prohibited for DEHP, DBP, DIBP, BBP under REACH classifications | D9: Endocrine disruption and reproductive toxicity concerns | E9: Fragrances, nail polish, sprays, washes, lotions | F9: Safety validation table / current market reference | G9: =COUNTIF('Tuan-Formula_BOM'!$B:$B,"*"&A9&"*")+COUNTIF('Tuan-Formula_BOM'!$C:$C,"*"&A9&"*") -> 0 | H9: =IF(G9>0,"REVIEW - possible formula match","No formula match recorded") -> No formula match recorded | J9: Regulatory | K9: 04_Ingredient_Screening | L9: Check fragrance and packaging-contact documents.
A10: Cyclomethicone D4/D5/D6 | B10: Emollients / solvents | C10: D4 banned; D5/D6 restricted in some contexts | D10: Bioaccumulation, reproductive and PBT/vPvB concerns | E10: Wash-off and leave-on cosmetics | F10: Safety validation table / current market reference | G10: =COUNTIF('Tuan-Formula_BOM'!$B:$B,"*"&A10&"*")+COUNTIF('Tuan-Formula_BOM'!$C:$C,"*"&A10&"*") -> 0 | H10: =IF(G10>0,"REVIEW - possible formula match","No formula match recorded") -> No formula match recorded | J10: Regulatory | K10: 04_Ingredient_Screening | L10: Check exact substance and product type.
A11: Triclosan | B11: Preservative / antimicrobial | C11: Restricted in specific product types | D11: Endocrine/thyroid and fetal neurodevelopment concerns | E11: Toothpaste, soaps, deodorants, nail products | F11: Safety validation table / current market reference | G11: =COUNTIF('Tuan-Formula_BOM'!$B:$B,"*"&A11&"*")+COUNTIF('Tuan-Formula_BOM'!$C:$C,"*"&A11&"*") -> 0 | H11: =IF(G11>0,"REVIEW - possible formula match","No formula match recorded") -> No formula match recorded | J11: Regulatory | K11: 04_Ingredient_Screening | L11: Confirm product-specific permissibility.
A12: Benzophenone | B12: UV filter / light stabilizer / fragrance ingredient | C12: Prohibited/restricted in some markets | D12: Carcinogenicity, endocrine activity and transplacental-exposure concern | E12: Sunscreens, anti-ageing creams, fragrances | F12: Safety validation table / current market reference | G12: =COUNTIF('Tuan-Formula_BOM'!$B:$B,"*"&A12&"*")+COUNTIF('Tuan-Formula_BOM'!$C:$C,"*"&A12&"*") -> 0 | H12: =IF(G12>0,"REVIEW - possible formula match","No formula match recorded") -> No formula match recorded | J12: Regulatory | K12: 04_Ingredient_Screening | L12: Also review oxybenzone/BP-3 caution rows.
A13: Methanol | B13: Denaturant | C13: Restricted level in denatured alcohol systems | D13: Neurotoxicity and placental-transfer concern at high exposure | E13: Products containing denatured alcohol | F13: Safety validation table / current market reference | G13: =COUNTIF('Tuan-Formula_BOM'!$B:$B,"*"&A13&"*")+COUNTIF('Tuan-Formula_BOM'!$C:$C,"*"&A13&"*") -> 0 | H13: =IF(G13>0,"REVIEW - possible formula match","No formula match recorded") -> No formula match recorded | J13: Regulatory | K13: 04_Ingredient_Screening | L13: Check CoA/specification.
A14: Heavy metals Pb Hg Cd As | B14: Contaminants / impurities | C14: Prohibited; trace limits vary by market | D14: Neurotoxicity, nephrotoxicity, carcinogenicity and fetal-development concern | E14: All cosmetics | F14: CoA/heavy metal test / market reference | G14: =COUNTIF('Tuan-Formula_BOM'!$B:$B,"*"&A14&"*")+COUNTIF('Tuan-Formula_BOM'!$C:$C,"*"&A14&"*") -> 0 | H14: =IF(G14>0,"REVIEW - possible formula match","No formula match recorded") -> No formula match recorded | J14: Quality | K14: 04_Ingredient_Screening | L14: Attach CoA or finished-product heavy metal report.
A15: Lilial BMHCA | B15: Fragrance ingredient | C15: Prohibited in EU and high concern for maternal products | D15: Reproductive toxicity classification and breast milk detection concern | E15: Fragranced cosmetics | F15: IFRA / allergen / market reference | G15: =COUNTIF('Tuan-Formula_BOM'!$B:$B,"*"&A15&"*")+COUNTIF('Tuan-Formula_BOM'!$C:$C,"*"&A15&"*") -> 0 | H15: =IF(G15>0,"REVIEW - possible formula match","No formula match recorded") -> No formula match recorded | J15: Regulatory | K15: 04_Ingredient_Screening | L15: Attach fragrance declaration.
A16: Retinol Retinyl Palmitate Tretinoin | B16: Anti-ageing active | C16: Restricted; pregnancy caution / contraindication logic | D16: Teratogenicity and cumulative exposure concerns | E16: Body lotions, face creams, serums | F16: Safety validation table / current market reference | G16: =COUNTIF('Tuan-Formula_BOM'!$B:$B,"*"&A16&"*")+COUNTIF('Tuan-Formula_BOM'!$C:$C,"*"&A16&"*") -> 0 | H16: =IF(G16>0,"REVIEW - possible formula match","No formula match recorded") -> No formula match recorded | J16: Regulatory / Safety | K16: 07_Maternal_Baby_Safety | L16: Assess with PB_Caution_Limits and label warnings.
A17: 4-Methylbenzylidene Camphor 4-MBC | B17: UV filter | C17: Prohibited/restricted in some markets | D17: Endocrine disruption and breast milk detection concern | E17: Sunscreens, SPF day creams | F17: Safety validation table / current market reference | G17: =COUNTIF('Tuan-Formula_BOM'!$B:$B,"*"&A17&"*")+COUNTIF('Tuan-Formula_BOM'!$C:$C,"*"&A17&"*") -> 0 | H17: =IF(G17>0,"REVIEW - possible formula match","No formula match recorded") -> No formula match recorded | J17: Regulatory | K17: 04_Ingredient_Screening | L17: Confirm exact market status.
A18: Formaldehyde releasers | B18: Preservative / hardening agent | C18: Prohibited/restricted as preservative depending on market/product | D18: Carcinogenicity, sensitisation and reproductive concern | E18: Hair straightening, eyelash glues, preserved products | F18: Safety validation table / current market reference | G18: =COUNTIF('Tuan-Formula_BOM'!$B:$B,"*"&A18&"*")+COUNTIF('Tuan-Formula_BOM'!$C:$C,"*"&A18&"*") -> 0 | H18: =IF(G18>0,"REVIEW - possible formula match","No formula match recorded") -> No formula match recorded | J18: Regulatory / Safety | K18: 04_Ingredient_Screening | L18: Check preservative system and supplier declaration.
A19: Bisphenol S | B19: Plasticizer / stabilizer | C19: Prohibited/restricted in some contexts | D19: Endocrine/reproductive toxicity concern | E19: Packaging-contact risk, nail products, coatings | F19: Packaging/contact-material reference | G19: =COUNTIF('Tuan-Formula_BOM'!$B:$B,"*"&A19&"*")+COUNTIF('Tuan-Formula_BOM'!$C:$C,"*"&A19&"*") -> 0 | H19: =IF(G19>0,"REVIEW - possible formula match","No formula match recorded") -> No formula match recorded | J19: Regulatory | K19: 06_Packaging_Artwork | L19: Review packaging-contact evidence.

Sheet ChiChu-PB_Caution_Limits
A1: REVIEW OWNER: Chi Chu (Regulatory) | Co-sign: Chris (Project Manager)
A2: MBc360 Development & Quality System
A3: Pregnancy / Breastfeeding Caution Limits
A4: Product-specific concentration and exposure check for maternal products. Use alongside Formula_BOM and Formulation_Safety.
A6: CAUTION LIMIT ASSESSMENT
A7: Ingredient / group | B7: Function | C7: Status / default limit guidance | D7: Why caution is required | E7: Applicable products | F7: Reference / source | G7: Formula % / exposure | H7: Product status | I7: Evidence link | J7: Owner | K7: Linked gate | L7: Notes
A8: Oxybenzone (Benzophenone-3) | B8: Chemical UV filter | C8: Caution; mineral alternatives often preferred for pregnancy positioning | D8: Systemic absorption, breast milk detection and endocrine activity concerns | E8: Sunscreens, SPF moisturizers | F8: Caution table / current market reference | H8: Not assessed | J8: Regulatory / Safety | K8: 07_Maternal_Baby_Safety | L8: Record exact % and market limits.
A9: Homosalate | B9: Chemical UV filter | C9: Restricted/caution in some markets | D9: Endocrine and systemic absorption concerns | E9: SPF face products | F9: Caution table / current market reference | H9: Not assessed | J9: Regulatory / Safety | K9: 07_Maternal_Baby_Safety | L9: Check current SCCS/market status.
A10: Hydroquinone | B10: Skin-lightening active | C10: Caution/avoid pregnancy; high absorption concern | D10: High dermal absorption and insufficient pregnancy data | E10: Melasma/brightening products | F10: Caution table / current market reference | H10: Not assessed | J10: Regulatory / Safety | K10: 07_Maternal_Baby_Safety | L10: Use substitution sheet if excluded.
A11: Essential oils | B11: Fragrance / therapeutic / antimicrobial | C11: Caution; specify exact oil and level | D11: Placental transfer potential and specific oil/lactation concerns | E11: Fragranced skincare, body oils | F11: Caution table / IFRA / supplier declaration | H11: Not assessed | J11: Safety / R&I | K11: 07_Maternal_Baby_Safety | L11: Attach IFRA/allergen details.
A12: Caffeine topical | B12: Antioxidant / vasoconstrictor | C12: Caution; consider total caffeine exposure | D12: Cumulative exposure with dietary caffeine | E12: Eye/body/scalp products | F12: Caution table / tox rationale | H12: Not assessed | J12: Safety | K12: 07_Maternal_Baby_Safety | L12: Record MoS/exposure rationale.
A13: Arnica montana | B13: Anti-inflammatory / anti-bruising botanical | C13: Caution; topical only; avoid near nipples | D13: Neonatal/breastfeeding transfer and sensitisation concerns | E13: Anti-bruising creams, massage balms | F13: Caution table / botanical safety | H13: Not assessed | J13: Safety | K13: 07_Maternal_Baby_Safety | L13: Define use-area restrictions.
A14: BHT | B14: Antioxidant / stabiliser | C14: Caution; check current max and endocrine review | D14: Systemic organ effects at high doses and weak endocrine signals | E14: Moisturisers, SPF, lip products | F14: Caution table / market reference | H14: Not assessed | J14: Safety / Regulatory | K14: 07_Maternal_Baby_Safety | L14: Attach concentration justification.
A15: BHA | B15: Antioxidant / preservative | C15: Caution; low permitted level contexts | D15: Carcinogenicity/endocrine/reproductive concern in animal data | E15: Leave-on skincare, lip balms | F15: Caution table / market reference | H15: Not assessed | J15: Safety / Regulatory | K15: 07_Maternal_Baby_Safety | L15: Attach concentration justification.
A16: Kojic acid | B16: Brightening active | C16: Caution; check current limit | D16: Limited pregnancy data and endocrine thyroid flags | E16: Brightening/melasma products | F16: Caution table / market reference | H16: Not assessed | J16: Safety / Regulatory | K16: 07_Maternal_Baby_Safety | L16: Assess if safer substitute exists.
A17: Licorice root extract | B17: Brightening / soothing botanical | C17: Caution; check glycyrrhizin content | D17: Placental cortisol-barrier mechanism and oral exposure concerns | E17: Brightening/soothing products | F17: Caution table / supplier spec | H17: Not assessed | J17: Safety / R&I | K17: 07_Maternal_Baby_Safety | L17: Attach botanical spec and active content.
A18: Salicylic acid / salicylates | B18: BHA exfoliant / anti-acne | C18: Caution; topical limits and product type matter | D18: Dermal absorption, breast milk transfer and high-dose salicylate concern | E18: Acne, toners, cleansers | F18: Caution/substitution table | H18: Not assessed | J18: Safety / Regulatory | K18: 07_Maternal_Baby_Safety | L18: Assess total salicylate exposure.
A19: Glycerin for vulvovaginal use | B19: Humectant / solvent | C19: Caution for intimate products | D19: Vaginal epithelial permeability/osmotic concerns | E19: Feminine washes/intimate products | F19: Caution table / tox rationale | H19: Not assessed | J19: Safety / R&I | K19: 07_Maternal_Baby_Safety | L19: Only relevant to intimate-use products.

Sheet ChiChu-Fragrance_Safety
A1: REVIEW OWNER: Chi Chu (Regulatory) | Co-sign: Chris (Project Manager)
A2: MBc360 Development & Quality System
A3: Fragrance Safety & Allergen Evidence
A4: Six-step fragrance workflow from supplier selection through post-market surveillance.
A6: FRAGRANCE WORKFLOW
A7: Step | B7: Control point | C7: Minimum requirement | D7: Evidence link | E7: Owner | F7: Status | G7: Notes
A8: 1 | B8: Supplier qualification | C8: Supplier approved; IFRA/allergen/quality docs available | E8: R&I / Procurement | F8: Not Started
A9: 2 | B9: Fragrance composition screen | C9: Prohibited and PB caution ingredients checked | E9: Regulatory / Safety | F9: Not Started
A10: 3 | B10: IFRA category review | C10: Applicable category and max use level documented | E10: Regulatory | F10: Not Started
A11: 4 | B11: Allergen label review | C11: Allergens and thresholds reviewed for each market | E11: Regulatory / Artwork | F11: Not Started
A12: 5 | B12: Formula and sensory impact | C12: Use level, odour profile, stability and complaints risk assessed | E12: R&I / Quality | F12: Not Started
A13: 6 | B13: Post-market surveillance | C13: Fragrance complaint/AE trends monitored | E13: Quality / PV-PMS | F13: Not Started
A15: FRAGRANCE / ALLERGEN LOG
A16: Fragrance code | B16: Supplier | C16: Use level % | D16: IFRA category | E16: IFRA link | F16: Allergen statement link | G16: PB caution review | H16: Status | I16: Notes
H17: Not Started
H18: Not Started
H19: Not Started
H20: Not Started
H21: Not Started
H22: Not Started
H23: Not Started
H24: Not Started
H25: Not Started
H26: Not Started

Sheet ChiChu-ASEAN_PIF_Map
A1: REVIEW OWNER: Chi Chu (Regulatory) | Co-sign: Chris (Project Manager)
A2: MBc360 Development & Quality System
A3: ASEAN PIF / Dossier Map
A4: High-level dossier overview. The detailed closure checklist is PIF_Checklist_ASEAN.
A6: PIF / DOSSIER REQUIREMENTS
A7: PIF / dossier requirement | B7: Required document / record | C7: Owner | D7: Status | E7: Location / link | F7: Linked gate | G7: Evidence link | H7: Notes
A8: Part I - Product Summary | B8: Product name, product type, intended use, presentation, responsible persons | C8: Regulatory | D8: Not Started | F8: 10_Dossier_Claims | H8: Use market-specific template where applicable
A9: Product notification / acknowledgement | B9: Notification receipt or acknowledgement | C9: Regulatory | D9: Not Started | F9: 10_Dossier_Claims | H9: Country-specific
A10: NIB / company registration | B10: NIB, company registration or equivalent | C10: Regulatory | D10: Not Started | F10: 10_Dossier_Claims | H10: Indonesia/market-specific where needed
A11: Letter of Appointment / authorisation | B11: LoA, importer/distributor authorisation | C11: Regulatory / Commercial | D11: Not Started | F11: 10_Dossier_Claims | H11: Required where distributor/agent acts for company
A12: Ownership confirmation | B12: Brand/product ownership confirmation | C12: Regulatory / Legal | D12: Not Started | F12: 10_Dossier_Claims | H12: Attach signed ownership/authority file
A13: Formula / composition | B13: Full formula, INCI, % range, function and supplier | C13: R&I | D13: Not Started | F13: 05_Formula_BOM_Costing | H13: Formula_BOM must be current
A14: Manufacturing method | B14: Process flow, manufacturing instruction, batch record reference | C14: Manufacturing / Quality | D14: Not Started | F14: 11_Launch_SignOff | H14: Controlled manufacturing version
A15: GMP evidence | B15: GMP certificate, site evidence, manufacturer qualification | C15: Quality | D15: Not Started | F15: 11_Launch_SignOff | H15: Link site qualification
A16: Safety assessment / CPSR | B16: Safety assessment and toxicological review | C16: Safety / Regulatory | D16: Not Started | F16: 07_Maternal_Baby_Safety | H16: Use Formulation_Safety
A17: Raw material documentation | B17: SDS, CoA, TDS/spec, allergens, impurities, heavy metals | C17: R&I / Procurement | D17: Not Started | F17: 04_Ingredient_Screening | H17: Use Supplier_RM_Evidence
A18: Stability and compatibility | B18: Accelerated/real-time stability, pack compatibility | C18: Quality / R&I | D18: Not Started | F18: 09_Stability_Release | H18: Attach protocol and report
A19: Micro / PET / preservative efficacy | B19: Micro specs, PET/challenge, preservation rationale | C19: Quality | D19: Not Started | F19: 08_Testing_Validation | H19: Required for aqueous/preserved products
... A22: Adverse event / post-market system | B22: Complaint, AE, PV/PMS and CAPA pathway | C22: Quality / PV-PMS | D22: Not Started | F22: 12_PostMarket_Improve | H22: Must be live after launch

Sheet ChiChu-PIF_Checklist
A1: REVIEW OWNER: Chi Chu (Regulatory) | Co-sign: Chris (Project Manager)
A2: MBc360 Development & Quality System
A3: ASEAN PIF Checklist
A4: Detailed checklist for PIF closure. It should point to source evidence tabs rather than repeat their content.
A6: PIF CLOSURE CHECKLIST
A7: PIF ID | B7: PIF section | C7: Requirement | D7: Owner | E7: Status | F7: Evidence link | G7: Gate | H7: Reviewer | I7: Closure date | J7: Notes
A8: PIF-01 | B8: Product summary | C8: Product name, type, presentation, intended use, markets | D8: Regulatory | E8: Not Started | G8: 10
A9: PIF-02 | B9: Formula | C9: Full composition, INCI, function, concentration/range | D9: R&I / Regulatory | E9: Not Started | G9: 05/10
A10: PIF-03 | B10: Safety assessment | C10: Formulation safety assessment and final sign-off | D10: Safety / Regulatory | E10: Not Started | G10: 07/10
A11: PIF-04 | B11: Raw materials | C11: SDS, CoA, TDS/spec, allergen, impurity evidence | D11: R&I / Procurement | E11: Not Started | G11: 04/10
A12: PIF-05 | B12: Manufacturing | C12: GMP evidence, manufacturing method, batch record link | D12: Quality / Manufacturing | E12: Not Started | G12: 11
A13: PIF-06 | B13: Stability | C13: Stability/compatibility reports and release conclusion | D13: Quality | E13: Not Started | G13: 09/10
A14: PIF-07 | B14: Micro/PET | C14: Micro limits, challenge/PET, preservation rationale | D14: Quality | E14: Not Started | G14: 08/10
A15: PIF-08 | B15: Packaging/artwork | C15: Label/artwork, component specs, warnings and directions | D15: Packaging / Regulatory | E15: Not Started | G15: 06/10
A16: PIF-09 | B16: Claims | C16: Claim wording, evidence and limitations | D16: Claims / Regulatory | E16: Not Started | G16: 03/10
A17: PIF-10 | B17: Post-market | C17: Complaint/AE/CAPA process and live owner | D17: Quality / PV-PMS | E17: Not Started | G17: 12

Sheet ChiChu-PIF_Evid_Export
A1: REVIEW OWNER: Chi Chu (Regulatory) | Co-sign: Chris (Project Manager)
A2: MBc360 Development & Quality System
A3: PIF Evidence Export
A4: Use this as the export pack when reports, claims or safety/performance evidence are moved into the product PIF / Product Master File.
A6: PIF EXPORT REGISTER
A7: Product/SKU | B7: Market | C7: PIF section | D7: Evidence item | E7: Source template | F7: Source evidence link | G7: PIF folder link | H7: Version / date | I7: Status | J7: Owner | K7: Notes
I8: Not Started
I9: Not Started
I10: Not Started
I11: Not Started
I12: Not Started
I13: Not Started
I14: Not Started
I15: Not Started
I16: Not Started
I17: Not Started
I18: Not Started
I19: Not Started
... I25: Not Started

Sheet ChiChu-SKU_Claims_PIF
A1: REVIEW OWNER: Chi Chu (Regulatory) | Co-sign: Chris (Project Manager)
A2: MBc360 Development & Quality System
A3: SKU Claims / PIF Register
A4: Register each SKU-level claim and the PIF evidence that supports it. No claim is external until evidence and wording are approved.
A6: SKU CLAIMS REGISTER
A7: Product/SKU | B7: Market | C7: Claim / wording | D7: Claim category | E7: Evidence type | F7: Evidence source | G7: Evidence link | H7: Approved limitation | I7: PIF link | J7: Status | K7: Owner | L7: Notes
J8: Not Started
J9: Not Started
J10: Not Started
J11: Not Started
J12: Not Started
J13: Not Started
J14: Not Started
J15: Not Started
J16: Not Started
J17: Not Started
J18: Not Started
J19: Not Started
... J23: Not Started

Sheet ChiChu-PIF_Evid_Closure
A1: REVIEW OWNER: Chi Chu (Regulatory) | Co-sign: Chris (Project Manager)
A2: MBc360 Development & Quality System
A3: PIF Evidence Closure
A4: Workflow control sheet for moving MBc360 evidence into the PIF / Product Master File.
A6: PIF CLOSURE WORKFLOW
A7: Trigger | B7: Required action | C7: Person in charge | D7: Supporting template / sheet | E7: Closure evidence | F7: Linked gate | G7: Blocks external use until closed? | H7: Status | I7: Notes
A8: New product launch or new market | B8: Open PIF_Evidence_Export; confirm mandatory sections and attachments | C8: Regulatory / PIF owner | D8: PIF_Checklist_ASEAN; PIF_Evidence_Export | E8: PIF folder link + sign-off | F8: 10/11 | G8: Y | H8: Not Started
A9: In-market catch-up review | B9: Attach current claims, safety and performance reports to each SKU PIF | C9: Regulatory / Project owner | D9: PIF_Evidence_Export | E9: SKU status visible | F9: 10/12 | G9: Y | H9: Not Started
A10: New or changed claim | B10: Add claim to SKU_Claims_PIF_Register and attach support | C10: Regulatory / Claims owner | D10: SKU_Claims_PIF_Register | E10: Claim approved and attached | F10: 03/10 | G10: Y | H10: Not Started
A11: New test report | B11: Index report and attach to PIF if required | C11: R&I / Quality | D11: Test_Report_Index | E11: Report saved in PIF | F11: 08/10 | G11: Y | H11: Not Started
A12: Formula/supplier/fragrance/pH/process/artwork change | B12: Assess evidence validity and update linked PIF records | C12: R&I / Regulatory / QA | D12: Change_Control_Comm | E12: PIF evidence current | F12: ALL | G12: Y | H12: Not Started
A13: Distributor/pharmacy/HCP question | B13: Answer only from approved PMF/PIF evidence and wording | C13: Regulatory / Scientific Review | D13: HCP_Test_Report_Pack | E13: Final answer saved | F13: 10/11 | G13: Y | H13: Not Started
A14: Updated public information | B14: Check publication approval and attach final record | C14: Content owner / Regulatory | D14: Published_Info_Approval | E14: Final public link captured | F14: 10/11 | G14: Y | H14: Not Started

Sheet ChiChu-Published_Info_Ap
A1: REVIEW OWNER: Chi Chu (Regulatory) | Co-sign: Chris (Project Manager)
A2: MBc360 Development & Quality System
A3: Published Information Approval
A4: Approve any product information, technical statement, claim wording or evidence summary before release outside controlled internal use.
A6: PUBLICATION RULES
A7: Publication rule | B7: Requirement
A8: What may be published | B8: Only approved wording, terminology, claim category, evidence level, limitation, applicable SKU/market/version and final public link.
A9: What must not be published | B9: Draft data, unsupported superlatives, unreviewed translations, therapeutic implications, raw report excerpts without approved interpretation, confidential formula details or claims without PMF/PIF support.
A10: Minimum sign-off | B10: Content owner, technical/safety reviewer where technical claims are made, regulatory/claims reviewer, quality where safety/release/PIF is affected, brand owner and final approver where required.
A12: PUBLICATION APPROVAL REGISTER
A13: Record ID | B13: Product/SKU | C13: Material type | D13: Channel | E13: Market | F13: Published information item | G13: Audience | H13: Claim / terminology category | I13: Exact wording / technical statement | J13: Evidence type required | K13: Evidence / PMF / PIF link | L13: Allowed? | M13: Required reviewers / functions | N13: Status | O13: Date approved | P13: Expiry / review date | Q13: Final published link | R13: Closure / notes
A14: PUB-001 | L14: Conditional | N14: Not Started
A15: PUB-001 | L15: Conditional | N15: Not Started
A16: PUB-001 | L16: Conditional | N16: Not Started
A17: PUB-001 | L17: Conditional | N17: Not Started
A18: PUB-001 | L18: Conditional | N18: Not Started
A19: PUB-001 | L19: Conditional | N19: Not Started
A20: PUB-001 | L20: Conditional | N20: Not Started
A21: PUB-001 | L21: Conditional | N21: Not Started
A22: PUB-001 | L22: Conditional | N22: Not Started
A23: PUB-001 | L23: Conditional | N23: Not Started

Sheet Lily-Released_Label_Ctrl
A1: REVIEW OWNER: Lily (Packaging) | Anki (Digital / Platforms) | Co-sign: Chris (Project Manager)
A2: MBc360 Development & Quality System
A3: Released Label Control - Current vs New Label, Platform Rollout & Shipment Verification
A4: Separate control project for label/artwork changes. Record what has changed or will change (incl. LEMC serum cartoon), current vs new label, market-release status, 3D asset status, platform rollout with stock confirmation, and per-shipment label + batch verification. No silent label changes - use Artwork_Change_Control for the formal change record.
A6: BLOCK A - RELEASED LABEL vs CURRENT ARTWORK REGISTER (what changed / will change, market status, 3D status)
A7: Record ID | B7: Product / SKU | C7: Product code | D7: Change type | E7: What has changed / will change | F7: Current label version | G7: Current artwork file | H7: New label version | I7: New artwork file | J7: New label released to market? | K7: Market release date | L7: Markets affected | M7: 3D asset exists? | N7: 3D asset link | O7: Artwork_Change_Control ref | P7: Owner | Q7: Status | R7: Notes / action
A8: LBL-001 | Q8: Not Started
A9: LBL-002 | Q9: Not Started
A10: LBL-003 | Q10: Not Started
A11: LBL-004 | Q11: Not Started
A12: LBL-005 | Q12: Not Started
A13: LBL-006 | Q13: Not Started
A14: LBL-007 | Q14: Not Started
A15: LBL-008 | Q15: Not Started
A16: LBL-009 | Q16: Not Started
A17: LBL-010 | Q17: Not Started
A18: LBL-011 | Q18: Not Started
A19: LBL-012 | Q19: Not Started
A20: LBL-013 | Q20: Not Started
A22: BLOCK B - PLATFORM / CHANNEL ROLLOUT & STOCK CONFIRMATION (Anki - update every platform only when correct stock is available)
A23: Rollout ID | B23: Linked Record ID (Block A) | C23: Product / SKU | D23: Platform / channel | E23: Platform URL / location | F23: Current image on platform | G23: Correct new artwork file | H23: New-label stock available? | I23: Stock confirmed by | J23: Old image removed? | K23: Image updated on platform? | L23: Date updated | M23: Verified by | N23: Screenshot / evidence link | O23: Owner | P23: Status | Q23: Notes | R23: Follow-up date
A24: RLT-001 | P24: Not Started
A25: RLT-002 | P25: Not Started
A26: RLT-003 | P26: Not Started
A27: RLT-004 | P27: Not Started
A28: RLT-005 | P28: Not Started
A29: RLT-006 | P29: Not Started
A30: RLT-007 | P30: Not Started
A31: RLT-008 | P31: Not Started
A32: RLT-009 | P32: Not Started
A33: RLT-010 | P33: Not Started
A34: RLT-011 | P34: Not Started
A35: RLT-012 | P35: Not Started
A36: RLT-013 | P36: Not Started
A38: BLOCK C - SHIPMENT LABEL & BATCH VERIFICATION (every shipment out must record exact batch details + exact label artwork version)
A39: Shipment ID | B39: Linked Record ID (Block A) | C39: Product / SKU | D39: Destination / customer / market | E39: Ship date | F39: Batch / lot no. | G39: Batch record link | H39: Label artwork version shipped | I39: Label artwork file / proof link | J39: Artwork matches current released label? | K39: Batch details match physical stock? | L39: Verified by | M39: Batch_Formula_Trace ref | N39: Photo / evidence link | O39: Owner | P39: Status | Q39: Hold / release | R39: Notes
A40: SHP-001 | P40: Not Started
A41: SHP-002 | P41: Not Started
A42: SHP-003 | P42: Not Started
A43: SHP-004 | P43: Not Started
A44: SHP-005 | P44: Not Started
A45: SHP-006 | P45: Not Started
A46: SHP-007 | P46: Not Started
A47: SHP-008 | P47: Not Started
A48: SHP-009 | P48: Not Started
A49: SHP-010 | P49: Not Started
A50: SHP-011 | P50: Not Started
A51: SHP-012 | P51: Not Started
A52: SHP-013 | P52: Not Started

Sheet Lily-Packaging_BOM
A1: REVIEW OWNER: Lily (Packaging) | Co-sign: Chris (Project Manager)
A2: MBc360 Development & Quality System
A3: Packaging BOM / Component Costing
A4: Enter each packaging component once. Link the current component spec, artwork proof or supplier evidence rather than duplicating documents.
A6: PACKAGING BOM
A7: Line | B7: Component | C7: Component type | D7: Supplier | E7: Units per finished unit | F7: Unit cost | G7: Wastage % | H7: Cost / unit | I7: Lead time | J7: MOQ | K7: Evidence link | L7: Method ref | M7: Notes | N7: Approval
A8: 1 | H8: =IFERROR(E8*F8*(1+G8),"") -> 0
A9: 2 | H9: =IFERROR(E9*F9*(1+G9),"") -> 0
A10: 3 | H10: =IFERROR(E10*F10*(1+G10),"") -> 0
A11: 4 | H11: =IFERROR(E11*F11*(1+G11),"") -> 0
A12: 5 | H12: =IFERROR(E12*F12*(1+G12),"") -> 0
A13: 6 | H13: =IFERROR(E13*F13*(1+G13),"") -> 0
A14: 7 | H14: =IFERROR(E14*F14*(1+G14),"") -> 0
A15: 8 | H15: =IFERROR(E15*F15*(1+G15),"") -> 0
A16: 9 | H16: =IFERROR(E16*F16*(1+G16),"") -> 0
A17: 10 | H17: =IFERROR(E17*F17*(1+G17),"") -> 0
A18: 11 | H18: =IFERROR(E18*F18*(1+G18),"") -> 0
A19: 12 | H19: =IFERROR(E19*F19*(1+G19),"") -> 0
... A107: 100 | H107: =IFERROR(E107*F107*(1+G107),"") -> 0
A109: Total packaging cost / unit | H109: =IFERROR(SUM(H8:H107),0) -> 0

Sheet Lily-Packaging_Specs_Art
A1: REVIEW OWNER: Lily (Packaging) | Co-sign: Chris (Project Manager)
A2: MBc360 Development & Quality System
A3: Packaging Specs & Artwork Evidence
A4: Use for planned package/artwork evidence. Use Artwork_Change_Control only when a released or controlled version changes.
A6: PACKAGING COMPONENT EVIDENCE
A7: Component | B7: Material / construction | C7: Supplier | D7: Spec link | E7: Compatibility evidence | F7: Migration/contact risk | G7: Artwork / label version | H7: Pack code / barcode | I7: Market | J7: Evidence link | K7: Approval | L7: Owner | M7: Status | N7: Notes
K8: Not Started
K9: Not Started
K10: Not Started
K11: Not Started
K12: Not Started
K13: Not Started
K14: Not Started
K15: Not Started
K16: Not Started
K17: Not Started
K18: Not Started
K19: Not Started
... K23: Not Started
A25: ARTWORK / LABEL REVIEW CHECKLIST
A26: Review item | B26: Requirement | C26: Evidence link | D26: Owner | E26: Status | F26: Notes
A27: Product identity | B27: Product name, SKU, net content and market match project record | D27: Regulatory / Brand | E27: Not Started
A28: Ingredient list / INCI | B28: Formula_BOM version and INCI order reviewed | D28: Regulatory / R&I | E28: Not Started
A29: Directions / warnings | B29: Use instructions, pregnancy/BF restrictions and safety warnings included | D29: Regulatory / Safety | E29: Not Started
A30: Claims and benefit wording | B30: All claims match approved wording and evidence level | D30: Marketing / Regulatory | E30: Not Started
A31: Barcode / pack codes | B31: Barcode, item code, lot/date coding and pack dimensions verified | D31: Packaging / Supply | E31: Not Started
A32: Market language / symbols | B32: Local language, mandatory marks and distributor/importer details checked | D32: Regulatory | E32: Not Started
A33: Final proof release | B33: Approved print-ready file released and obsolete versions archived | D33: Packaging / QA | E33: Not Started
A34: Tags for Proprietary Extracts on Labels | B34: * SALVOTECT™, ** STACREGENIX™, ***MBC BIOFLORAL HONEY (lovingly harvested from our resident bees). Proprietary ingredients exclusive to Max Biocare Research Parks, Gippsland ****UVALIFE ANTIOXIDANT BLEND™ Proprietary ingredient exclusive to Max Biocare Pty Ltd | D34: Packaging / QA | E34: Not Started | F34: Use exactly as is
A35: Correct names for PI | B35: Salvia microphylla water extract | C35: Salvotect™ (MBc Research Parks PI)
A36: Correct names for PI | B36: Stachys byzantina water extract | C36: Stacregenix™ (MBc Research Parks PI)
A37: Correct names for PI | B37: Honey | C37: MBc Biofloral Honey (MBc Research Parks PI; changed from MBc Herbal Honey since 30 June 2026)
A38: Correct names for PI | B38: [VITIS VINIFERA (GRAPE) SEED EXTRACT, VITIS VINIFERA (GRAPE) FRUIT EXTRACT, WINE (RED WINE) EXTRACT], | C38: Uvalife® Antioxidant Blend (MBc Proprietary Blend)
A39: Correct names for PI | B39: Aqua (mineral water) | C39: Aquadene®Mineral-Rich Water (MBc Research Parks PI)

Sheet Lily-Artwork_Chg_Control
A1: REVIEW OWNER: Lily (Packaging) | Co-sign: Chris (Project Manager)
A2: MBc360 Development & Quality System
A3: Artwork Change Control
A4: Use only when artwork, label, carton, pack copy, proof or printer file changes. Planned artwork evidence belongs in Packaging_Specs_Artwork.
A6: ARTWORK CHANGE TRIGGERS
A7: Trigger / event | B7: Examples | C7: Immediate action | D7: Person in charge | E7: Required sign-offs | F7: Evidence to save | G7: Communication required | H7: Template / form | I7: Closure criteria | J7: Gate / sheet link | K7: Status
A8: Artwork error discovered | B8: Wrong wording, typo, ingredient list, warning, barcode or country text | C8: Raise Change_Control_Comm; freeze current file; create redline | D8: Artwork / Packaging owner | E8: Regulatory + Quality + Marketing/Sales where label-facing | F8: Old proof, redline, corrected proof, approval trail | G8: Notify impacted functions and distributor if affected | H8: Artwork Change Sign-off Form | I8: Final PDF released and obsolete file archived | J8: 06/10/11 | K8: Not Started
A9: Formula change affects label | B9: INCI order, ingredient addition/removal, active level, allergen/fragrance | C9: Link Formula_Change_Control and hold label release until formula locked | D9: R&I + Artwork owner | E9: R&I + Regulatory + QA | F9: Formula comparison, label impact assessment | G9: Sales/Marketing approved explanation | H9: Formula Change Comparison | I9: Label/PIF/claim materials updated | J9: 05/06/10 | K9: Not Started
A10: Regulatory or market update | B10: New country label requirement, warning, language or symbol | C10: Identify affected SKUs/materials and route to review | D10: Regulatory owner | E10: Regulatory + QA + market owner | F10: Regulatory note, translation, final proof | G10: Notify market/distributor/sales | H10: Regulatory Artwork Change Form | I10: Market-specific artwork and dossier updated | J10: 10/11 | K10: Not Started
A11: Marketing/claim copy change | B11: New or revised claim/HCP/website/leaflet wording | C11: Map claim to evidence; no live use until approved | D11: Marketing/Claims owner | E11: Regulatory + Scientific Review | F11: Claim substantiation and approved copy | G11: Notify Sales/Marketing and training owner | H11: Claims Change Control Form | I11: All collateral uses approved wording | J11: 03/10 | K11: Not Started
A12: Released label / market image mismatch | B12: Live product image or shipped label does not match current released label (e.g. website/marketplace out-of-date) | C12: Log in Released_Label_Ctrl (Block A); freeze wrong image; raise Change_Control_Comm | D12: Packaging (Lily) + Digital (Anki) | E12: Regulatory + Quality + Marketing/Sales | F12: Current vs new artwork files, platform screenshots, corrected proof, approval trail | G12: Notify Sales/Marketing, distributor and affected markets | H12: Released Label Control (Lily-Released_Label_Ctrl) | I12: All platforms and shipments carry the current released label; obsolete image archived | J12: 06/10/11 -> Lily-Released_Label_Ctrl | K12: Not Started

Sheet Chidkamon-Supplier_RM
A1: REVIEW OWNER: Chidkamon (Raw Material Operations) | Co-sign: Chris (Project Manager)
A2: MBc360 Development & Quality System
A3: Supplier & Raw Material Evidence
A4: Capture supplier documents once per material and link them into Formula_BOM, Formulation_Safety and PIF evidence.
A6: RAW MATERIAL DOCUMENT CONTROL
A7: RM code | B7: Ingredient / INCI | C7: Raw Material Evaluation Link (CH/CC) | D7: Approved For Use? | E7: Supplier | F7: Grade / trade name | G7: SDS link | H7: CoA link | I7: TDS / spec link | J7: Allergen statement | K7: Impurities / heavy metals | L7: Micro / preservative info | M7: Origin / vegan / natural proof | N7: Regulatory status | O7: Approved supplier evidence | P7: Owner | Q7: Status | R7: Notes
A8: RM-001 | D8: FALSE | Q8: Not Started
A9: RM-002 | D9: FALSE | Q9: Not Started
A10: RM-003 | D10: FALSE | Q10: Not Started
A11: RM-004 | D11: FALSE | Q11: Not Started
A12: RM-005 | D12: FALSE | Q12: Not Started
A13: RM-006 | D13: FALSE | Q13: Not Started
A14: RM-007 | D14: FALSE | Q14: Not Started
A15: RM-008 | D15: FALSE | Q15: Not Started
A16: RM-009 | D16: FALSE | Q16: Not Started
A17: RM-010 | D17: FALSE | Q17: Not Started
A18: RM-011 | D18: FALSE | Q18: Not Started
A19: RM-012 | D19: FALSE | Q19: Not Started
... A27: RM-020 | D27: FALSE | Q27: Not Started

Sheet Chidkamon-Ingred_Substit
A1: REVIEW OWNER: Chidkamon (Raw Material Operations) | Co-sign: Chris (Project Manager)
A2: MBc360 Development & Quality System
A3: Ingredient Substitution Evidence
A4: Use only when an ingredient is excluded, replaced or materially changed. This prevents repeated substitution notes across safety, claims and change sheets.
A6: SUBSTITUTION DECISION LOG
A7: Trigger ingredient | B7: Reason for substitution | C7: Proposed substitute | D7: Function replaced | E7: Required proof | F7: Formula impact | G7: Safety impact | H7: Efficacy / claim impact | I7: Cost impact | J7: Evidence links | K7: Decision | L7: Owner | M7: Status | N7: Notes
K8: Not Started
K9: Not Started
K10: Not Started
K11: Not Started
K12: Not Started
K13: Not Started
K14: Not Started
K15: Not Started
K16: Not Started
K17: Not Started
K18: Not Started
K19: Not Started

Sheet Chidkamon-Prod_Family_Reg
A1: REVIEW OWNER: Chidkamon (Raw Material Operations) | Co-sign: Chris (Project Manager)
A2: MBc360 Development & Quality System
A3: Product Family & Version Register
A4: One family = one consumer-facing product. Every formula change that manufacturing treats as a NEW product code is recorded here as a NEW VERSION of the SAME family, so Sales, Marketing, distributors and the market can see all versions of a product together. Requested by Anki / NP.
A6: PRODUCT FAMILY & VERSION LOG
A7: Product Family Name | B7: Family Code | C7: Version / Formula No. | D7: Manufacturing Product Code | E7: Formula version (Formula_BOM) | F7: Effective date | G7: Superseded date | H7: Current market version? (Y/N) | I7: Change register ID | J7: Market communication needed? | K7: Communicated to market? (Y/N) | L7: Owner | M7: Notes
A50: FAMILY ROLL-UP (live count of versions per family)
A51: Family Code | B51: Product Family Name | C51: No. of versions on record | D51: Current market version | E51: Any version needing market comms?
B52: =IF($A52="","",IFERROR(INDEX($A$8:$A$47,MATCH($A52,$B$8:$B$47,0)),"— code not found —")) | C52: =IF($A52="","",COUNTIF($B$8:$B$47,$A52)) | D52: {=IF($A52="","",IFERROR(INDEX($D$8:$D$47,MATCH(1,INDEX(($B$8:$B$47=$A52)*($H$8:$H$47="Yes"),0),0)),"none marked current"))} | E52: =IF($A52="","",IF(COUNTIFS($B$8:$B$47,$A52,$J$8:$J$47,"Yes")>0,"YES - comms needed",IF(COUNTIFS($B$8:$B$47,$A52,$J$8:$J$47,"To assess")>0,"To assess","No")))
B53: =IF($A53="","",IFERROR(INDEX($A$8:$A$47,MATCH($A53,$B$8:$B$47,0)),"— code not found —")) | C53: =IF($A53="","",COUNTIF($B$8:$B$47,$A53)) | D53: {=IF($A53="","",IFERROR(INDEX($D$8:$D$47,MATCH(1,INDEX(($B$8:$B$47=$A53)*($H$8:$H$47="Yes"),0),0)),"none marked current"))} | E53: =IF($A53="","",IF(COUNTIFS($B$8:$B$47,$A53,$J$8:$J$47,"Yes")>0,"YES - comms needed",IF(COUNTIFS($B$8:$B$47,$A53,$J$8:$J$47,"To assess")>0,"To assess","No")))
B54: =IF($A54="","",IFERROR(INDEX($A$8:$A$47,MATCH($A54,$B$8:$B$47,0)),"— code not found —")) | C54: =IF($A54="","",COUNTIF($B$8:$B$47,$A54)) | D54: {=IF($A54="","",IFERROR(INDEX($D$8:$D$47,MATCH(1,INDEX(($B$8:$B$47=$A54)*($H$8:$H$47="Yes"),0),0)),"none marked current"))} | E54: =IF($A54="","",IF(COUNTIFS($B$8:$B$47,$A54,$J$8:$J$47,"Yes")>0,"YES - comms needed",IF(COUNTIFS($B$8:$B$47,$A54,$J$8:$J$47,"To assess")>0,"To assess","No")))
B55: =IF($A55="","",IFERROR(INDEX($A$8:$A$47,MATCH($A55,$B$8:$B$47,0)),"— code not found —")) | C55: =IF($A55="","",COUNTIF($B$8:$B$47,$A55)) | D55: {=IF($A55="","",IFERROR(INDEX($D$8:$D$47,MATCH(1,INDEX(($B$8:$B$47=$A55)*($H$8:$H$47="Yes"),0),0)),"none marked current"))} | E55: =IF($A55="","",IF(COUNTIFS($B$8:$B$47,$A55,$J$8:$J$47,"Yes")>0,"YES - comms needed",IF(COUNTIFS($B$8:$B$47,$A55,$J$8:$J$47,"To assess")>0,"To assess","No")))
B56: =IF($A56="","",IFERROR(INDEX($A$8:$A$47,MATCH($A56,$B$8:$B$47,0)),"— code not found —")) | C56: =IF($A56="","",COUNTIF($B$8:$B$47,$A56)) | D56: {=IF($A56="","",IFERROR(INDEX($D$8:$D$47,MATCH(1,INDEX(($B$8:$B$47=$A56)*($H$8:$H$47="Yes"),0),0)),"none marked current"))} | E56: =IF($A56="","",IF(COUNTIFS($B$8:$B$47,$A56,$J$8:$J$47,"Yes")>0,"YES - comms needed",IF(COUNTIFS($B$8:$B$47,$A56,$J$8:$J$47,"To assess")>0,"To assess","No")))
B57: =IF($A57="","",IFERROR(INDEX($A$8:$A$47,MATCH($A57,$B$8:$B$47,0)),"— code not found —")) | C57: =IF($A57="","",COUNTIF($B$8:$B$47,$A57)) | D57: {=IF($A57="","",IFERROR(INDEX($D$8:$D$47,MATCH(1,INDEX(($B$8:$B$47=$A57)*($H$8:$H$47="Yes"),0),0)),"none marked current"))} | E57: =IF($A57="","",IF(COUNTIFS($B$8:$B$47,$A57,$J$8:$J$47,"Yes")>0,"YES - comms needed",IF(COUNTIFS($B$8:$B$47,$A57,$J$8:$J$47,"To assess")>0,"To assess","No")))
B58: =IF($A58="","",IFERROR(INDEX($A$8:$A$47,MATCH($A58,$B$8:$B$47,0)),"— code not found —")) | C58: =IF($A58="","",COUNTIF($B$8:$B$47,$A58)) | D58: {=IF($A58="","",IFERROR(INDEX($D$8:$D$47,MATCH(1,INDEX(($B$8:$B$47=$A58)*($H$8:$H$47="Yes"),0),0)),"none marked current"))} | E58: =IF($A58="","",IF(COUNTIFS($B$8:$B$47,$A58,$J$8:$J$47,"Yes")>0,"YES - comms needed",IF(COUNTIFS($B$8:$B$47,$A58,$J$8:$J$47,"To assess")>0,"To assess","No")))
B59: =IF($A59="","",IFERROR(INDEX($A$8:$A$47,MATCH($A59,$B$8:$B$47,0)),"— code not found —")) | C59: =IF($A59="","",COUNTIF($B$8:$B$47,$A59)) | D59: {=IF($A59="","",IFERROR(INDEX($D$8:$D$47,MATCH(1,INDEX(($B$8:$B$47=$A59)*($H$8:$H$47="Yes"),0),0)),"none marked current"))} | E59: =IF($A59="","",IF(COUNTIFS($B$8:$B$47,$A59,$J$8:$J$47,"Yes")>0,"YES - comms needed",IF(COUNTIFS($B$8:$B$47,$A59,$J$8:$J$47,"To assess")>0,"To assess","No")))
B60: =IF($A60="","",IFERROR(INDEX($A$8:$A$47,MATCH($A60,$B$8:$B$47,0)),"— code not found —")) | C60: =IF($A60="","",COUNTIF($B$8:$B$47,$A60)) | D60: {=IF($A60="","",IFERROR(INDEX($D$8:$D$47,MATCH(1,INDEX(($B$8:$B$47=$A60)*($H$8:$H$47="Yes"),0),0)),"none marked current"))} | E60: =IF($A60="","",IF(COUNTIFS($B$8:$B$47,$A60,$J$8:$J$47,"Yes")>0,"YES - comms needed",IF(COUNTIFS($B$8:$B$47,$A60,$J$8:$J$47,"To assess")>0,"To assess","No")))
B61: =IF($A61="","",IFERROR(INDEX($A$8:$A$47,MATCH($A61,$B$8:$B$47,0)),"— code not found —")) | C61: =IF($A61="","",COUNTIF($B$8:$B$47,$A61)) | D61: {=IF($A61="","",IFERROR(INDEX($D$8:$D$47,MATCH(1,INDEX(($B$8:$B$47=$A61)*($H$8:$H$47="Yes"),0),0)),"none marked current"))} | E61: =IF($A61="","",IF(COUNTIFS($B$8:$B$47,$A61,$J$8:$J$47,"Yes")>0,"YES - comms needed",IF(COUNTIFS($B$8:$B$47,$A61,$J$8:$J$47,"To assess")>0,"To assess","No")))
B62: =IF($A62="","",IFERROR(INDEX($A$8:$A$47,MATCH($A62,$B$8:$B$47,0)),"— code not found —")) | C62: =IF($A62="","",COUNTIF($B$8:$B$47,$A62)) | D62: {=IF($A62="","",IFERROR(INDEX($D$8:$D$47,MATCH(1,INDEX(($B$8:$B$47=$A62)*($H$8:$H$47="Yes"),0),0)),"none marked current"))} | E62: =IF($A62="","",IF(COUNTIFS($B$8:$B$47,$A62,$J$8:$J$47,"Yes")>0,"YES - comms needed",IF(COUNTIFS($B$8:$B$47,$A62,$J$8:$J$47,"To assess")>0,"To assess","No")))
B63: =IF($A63="","",IFERROR(INDEX($A$8:$A$47,MATCH($A63,$B$8:$B$47,0)),"— code not found —")) | C63: =IF($A63="","",COUNTIF($B$8:$B$47,$A63)) | D63: {=IF($A63="","",IFERROR(INDEX($D$8:$D$47,MATCH(1,INDEX(($B$8:$B$47=$A63)*($H$8:$H$47="Yes"),0),0)),"none marked current"))} | E63: =IF($A63="","",IF(COUNTIFS($B$8:$B$47,$A63,$J$8:$J$47,"Yes")>0,"YES - comms needed",IF(COUNTIFS($B$8:$B$47,$A63,$J$8:$J$47,"To assess")>0,"To assess","No")))
... B66: =IF($A66="","",IFERROR(INDEX($A$8:$A$47,MATCH($A66,$B$8:$B$47,0)),"— code not found —")) | C66: =IF($A66="","",COUNTIF($B$8:$B$47,$A66)) | D66: {=IF($A66="","",IFERROR(INDEX($D$8:$D$47,MATCH(1,INDEX(($B$8:$B$47=$A66)*($H$8:$H$47="Yes"),0),0)),"none marked current"))} | E66: =IF($A66="","",IF(COUNTIFS($B$8:$B$47,$A66,$J$8:$J$47,"Yes")>0,"YES - comms needed",IF(COUNTIFS($B$8:$B$47,$A66,$J$8:$J$47,"To assess")>0,"To assess","No")))

Sheet Nguyen-Campaigns_Social
A1: REVIEW OWNER: Nguyen (Sales & Marketing) | Co-sign: Chris (Project Manager)
A2: MBc360 Development & Quality System
A3: Social Media & Marketing Campaign Register
A4: Declare every social media post and marketing campaign here (links are enough). Where a campaign references a formula/label/pack change, link the Change ID so external messaging stays aligned with what has actually been approved and communicated to the market.
A6: CAMPAIGN & SOCIAL MEDIA LOG
A7: Campaign / Post ID | B7: Product Family / SKU | C7: Channel / platform | D7: Campaign / post title | E7: Objective / message | F7: Link (URL / asset) | G7: Start date | H7: End date | I7: Owner | J7: Linked Change ID | K7: Claims approved? (Reg) | L7: Status | M7: Notes

Sheet Nguyen-HCP_Efficacy_Ans
A1: REVIEW OWNER: Nguyen (Sales & Marketing) | Co-sign: Chris (Project Manager)
A2: MBc360 Development & Quality System
A3: HCP / Distributor Efficacy Answer
A4: Generate answers only from approved evidence and approved wording. Keep raw reports in the evidence source tabs.
A6: HCP / DISTRIBUTOR ANSWER LOG
A7: Question / objection | B7: Approved answer | C7: Evidence source | D7: Evidence link | E7: Approved wording link | F7: Do-not-say / limitation | G7: Status | H7: Owner | I7: Notes
G8: Not Started
G9: Not Started
G10: Not Started
G11: Not Started
G12: Not Started
G13: Not Started
G14: Not Started
G15: Not Started
G16: Not Started
G17: Not Started
G18: Not Started
G19: Not Started

Sheet Nguyen-HCP_Test_Rpt_Pack
A1: REVIEW OWNER: Nguyen (Sales & Marketing) | Co-sign: Chris (Project Manager)
A2: MBc360 Development & Quality System
A3: HCP Test Report Pack
A4: Compile approved test-report links and plain-English interpretations for HCP/distributor use.
A6: HCP REPORT PACK
A7: Pack item | B7: Claim / question supported | C7: Report / evidence source | D7: Plain-English interpretation | E7: Approved limitation | F7: PIF / PMF link | G7: Status | H7: Owner | I7: Notes
G8: Not Started
G9: Not Started
G10: Not Started
G11: Not Started
G12: Not Started
G13: Not Started
G14: Not Started
G15: Not Started
G16: Not Started
G17: Not Started
G18: Not Started
G19: Not Started

Sheet Nguyen-Product_Feedback
A1: REVIEW OWNER: Nguyen (Sales & Marketing) | Co-sign: Chris (Project Manager)
A2: MBc360 Development & Quality System
A3: Product / Development Sample Feedback Form
A4: Staff / panel feedback on development samples. Capture texture, fragrance, oiliness/slipperiness and safety concerns. Note: Sun/Swim/Sea collection is for men AND women - record both.
A6: SAMPLE UNDER EVALUATION
A7: Product / SKU | G7: Sample / batch code
A8: Product Family | G8: Formula version
A9: Development stage | G9: Date samples issued
A10: Linked Change ID | G10: Panel coordinator
A13: SCORING GUIDE - use 1 to 5 for scored attributes
A14: 1 = Poor / unacceptable | 2 = Below expectation | 3 = Acceptable | 4 = Good | 5 = Excellent (For "Too oily / slippery?" use the Yes/No/Borderline dropdown - this is a SAFETY flag, not a preference score.)
A16: PANEL FEEDBACK LOG (one row per tester per sample)
A17: Tester name | B17: Gender (M/F) | C17: Dept / site | D17: Date tested | E17: Texture (1-5) | F17: Fragrance (1-5) | G17: Overall (1-5) | H17: Too oily / slippery? (SAFETY) | I17: Would recommend? (Y/N) | J17: Best liked | K17: Concerns / improvement ideas | L17: Follow-up action
A60: PANEL RESULT SUMMARY (live - updates as feedback is entered)
A61: Metric | C61: Value
A62: Total testers | C62: =COUNTA($A$18:$A$57) -> 0
A63: Male testers (M) | C63: =COUNTIF($B$18:$B$57,"M") -> 0
A64: Female testers (F) | C64: =COUNTIF($B$18:$B$57,"F") -> 0
A65: Average Texture (1-5) | C65: =IFERROR(ROUND(AVERAGE($E$18:$E$57),1),"-") -> -
A66: Average Fragrance (1-5) | C66: =IFERROR(ROUND(AVERAGE($F$18:$F$57),1),"-") -> -
A67: Average Overall (1-5) | C67: =IFERROR(ROUND(AVERAGE($G$18:$G$57),1),"-") -> -
A68: SAFETY: "Yes" too oily/slippery | C68: =COUNTIF($H$18:$H$57,"Yes") -> 0
A69: SAFETY: "Borderline" too oily/slippery | C69: =COUNTIF($H$18:$H$57,"Borderline") -> 0
A70: Would recommend (Yes) | C70: =COUNTIF($I$18:$I$57,"Yes") -> 0
A71: Slip-risk flag | C71: =IF(COUNTIF($H$18:$H$57,"Yes")>0,"REVIEW - slip risk reported; check marketing message","OK - no slip risk flagged") -> OK - no slip risk flagged

Sheet Nguyen-Change_Ctrl_Comm
A1: REVIEW OWNER: Nguyen (Sales & Marketing) | Co-sign: Chris (Project Manager)
A2: MBc360 Development & Quality System
A3: Change Control & Communication
A5: CHANGE LOG
A6: Change ID | B6: Trigger / event | C6: Product/SKU | D6: Affected area | E6: Old version | F6: Risk level | G6: Required action | H6: Evidence link | I6: Required sign-offs | J6: Communication required | K6: Sales/Marketing message | L6: Due date | M6: Status | N6: Closure evidence | O6: Closed date | P6: Owner | Q6: Notes
A7: CHG-001 | F7: Medium | M7: Not Started
A8: CHG-001 | F8: Medium | M8: Not Started
A9: CHG-001 | F9: Medium | M9: Not Started
A10: CHG-001 | F10: Medium | M10: Not Started
A11: CHG-001 | F11: Medium | M11: Not Started
A12: CHG-001 | F12: Medium | M12: Not Started
A13: CHG-001 | F13: Medium | M13: Not Started
A14: CHG-001 | F14: Medium | M14: Not Started
A15: CHG-001 | F15: Medium | M15: Not Started
A16: CHG-001 | F16: Medium | M16: Not Started
A17: CHG-001 | F17: Medium | M17: Not Started
A18: CHG-001 | F18: Medium | M18: Not Started
A20: RACI / CLOSURE CONTROL
A21: Function | B21: Role | C21: Required contribution | D21: Linked evidence / sheet | E21: Status | F21: Notes
A22: Project owner | B22: Accountable | C22: Opens change, coordinates owners and closure | D22: Change_Control_Comm | E22: Not Started
A23: R&I / Formulation | B23: Responsible | C23: Assesses formula/process/ingredient impact | D23: Formula_Change_Control | E23: Not Started
A24: Regulatory | B24: Approver | C24: Assesses label, claims, market and PIF impact | D24: Artwork_Change_Control; PIF_Evidence_Closure | E24: Not Started
A25: Quality | B25: Approver | C25: Assesses release, GMP, stability, deviation/CAPA impact | D25: GMP_Links; Stability_Release | E25: Not Started
A26: Sales/Marketing | B26: Informed / acknowledgement | C26: Receives approved external/customer-facing explanation | D26: Change_Templates | E26: Not Started

Sheet Nguyen-Change_Templates
A1: REVIEW OWNER: Nguyen (Sales & Marketing) | Co-sign: Chris (Project Manager)
A2: MBc360 Development & Quality System
A3: Change Templates / Forms
A4: Copy the relevant section into a controlled form, email, approval workflow or ticket. Each completed form must link back to Change_Control_Comm.
A6: CHANGE FORMS
A7: Template / form | B7: Use when | C7: Required fields | D7: Approval / recipients | E7: Saved evidence | F7: Closure rule | G7: Linked sheets | H7: Status
A8: Change Request Form | B8: Any artwork, formula, label, claim, supplier, process or market change | C8: Change ID; trigger; product/SKU; old version; new version; reason; risk level; owner; due date; affected areas | D8: Project owner plus required technical/QA/regulatory approvers | E8: Completed request, log row, attachments | F8: Actions, approvals, communications and obsolete version control complete | G8: Change_Control_Comm | H8: Not Started
A9: Artwork Change Sign-off Form | B9: Artwork/label/carton/proof/pack copy change | C9: Old proof; new proof; redline; affected markets/SKUs; label/PIF/claim impact | D9: Artwork owner; Regulatory; QA; Marketing/Sales where customer-facing | E9: Redline, final PDF, approval trail, printer release email | F9: Only approved final artwork may be printed/released | G9: Artwork_Change_Control | H9: Not Started
A10: Formula Change Comparison Summary | B10: Formula, ingredient, supplier, pH, process, active, preservative or fragrance change | C10: Old vs new formula; INCI impact; reason; safety/efficacy/regulatory/label/stability/cost impact | D10: R&I, Quality, Regulatory, Scientific Review, Manufacturing, Sales/Marketing acknowledgement | E10: Formula comparison, updated Formula_BOM, evidence and sign-offs | F10: Summary sent to Sales/Marketing when commercial/customer-facing impact exists | G10: Formula_Change_Control | H10: Not Started
A11: Sales & Marketing Change Notification | B11: Formula, label, artwork, claims, sensory, benefit story or market wording changes | C11: What changed; why; what remains unchanged; affected SKUs/markets; customer talking points; do/don't say | D11: Project owner sends; Sales/Marketing acknowledges; Regulatory approves wording where claim-facing | E11: Email/Teams/deck link and acknowledgement record | F11: No closure until acknowledgement saved or N/A rationale approved | G11: Change_Control_Comm; Medical_Summary | H11: Not Started
A12: Closure Checklist | B12: Before change is marked closed | C12: Actions done; sign-offs complete; comms complete; final version linked; obsolete versions archived; linked sheets updated | D12: Change owner; QA/Document Control; Project owner | E12: Closed log row and closure note | F12: Closed date/closed by entered in Change_Control_Comm | G12: Change_Control_Comm | H12: Not Started

Sheet Hannah-Costing_Calc
A1: REVIEW OWNER: Hannah (Supply Chain) | Co-sign: Chris (Project Manager)
A2: MBc360 Development & Quality System
A3: Costing, Volume and Pricing Calculator
A4: Use this sheet as the single source of cost assumptions; BOM sheets feed the formula-driven outputs.
A6: INPUTS
A7: Input | B7: Value | C7: Unit | D7: Notes
A8: Batch size | B8: 100 | C8: kg | D8: Drives Formula_BOM batch quantity.
A9: Fill size | B9: 100 | C9: g or mL | D9: Used for unit assumptions where needed.
A10: Target units | B10: 1000 | C10: units | D10: Used for per-unit formula costing and forecast outputs.
A11: Formula cost / unit | B11: =IFERROR(SUM('Tuan-Formula_BOM'!K8:K107),0) -> 0 | C11: auto | D11: Linked from Formula_BOM.
A12: Packaging cost / unit | B12: =IFERROR('Lily-Packaging_BOM'!H109,0) -> 0 | C12: auto | D12: Linked from Packaging_BOM total.
A13: Labour / overhead / unit | B13: 0 | C13: currency | D13: Manual input.
A14: Freight / other / unit | B14: 0 | C14: currency | D14: Manual input.
A15: Target sell price | B15: 0 | C15: currency | D15: Manual input.
A16: Distributor margin | B16: 0.3 | C16: % | D16: Optional assumption.
A17: Wastage allowance | B17: 0.05 | C17: % | D17: Applied to COGS.
A19: CALCULATED OUTPUTS
A20: Output | B20: Value | C20: Unit | D20: Notes
A21: Calculated total COGS / unit | B21: =IFERROR(SUM(B11:B14)*(1+B17),0) -> 0 | C21: currency | D21: Formula + packaging + overhead + freight, with wastage.
A22: Gross margin % | B22: =IFERROR((B15-B21)/B15,"") | C22: % | D22: Based on target sell price.
A23: Total forecast revenue | B23: =IFERROR(B15*B10,0) -> 0 | C23: currency | D23: Target units x target sell price.
A24: Total forecast gross profit | B24: =IFERROR((B15-B21)*B10,0) -> 0 | C24: currency | D24: Unit gross profit x target units.

Sheet Hannah-PostMarket_CAPA
A1: REVIEW OWNER: Hannah (Supply Chain) | Co-sign: Chris (Project Manager)
A2: MBc360 Development & Quality System
A3: Post-market, Complaint & CAPA Evidence
A4: Use after launch to capture complaints, adverse events, post-market surveillance and CAPA links.
A6: POST-MARKET / CAPA LOG
A7: Record ID | B7: Product/SKU | C7: Market | D7: Event type | E7: Complaint / AE summary | F7: Severity / risk | G7: Investigation link | H7: CAPA link | I7: PIF / PMF impact | J7: Status | K7: Owner | L7: Notes
J8: Not Started
J9: Not Started
J10: Not Started
J11: Not Started
J12: Not Started
J13: Not Started
J14: Not Started
J15: Not Started
J16: Not Started
J17: Not Started
J18: Not Started
J19: Not Started
... J21: Not Started

Sheet MBC360 FEEDBACK
A1: User | B1: Date | C1: Department | D1: Comments
